Workbook

Sheet 1. Assumptions 
B3: LIST OF ASSUMPTION USED IN THE MODEL
B4: Assumption | D4: Reasons | Q4: Economic Net Worth | R4: Total Pension Value | S4: Total Human Capital Value
B5: Salary | C5: Huyen: Bank Teller. Huyen's husband: Recruitment Assistant. We will not change the career path. | D5: Huyen works in the financial industry.
B6: Mortgage and saving rate | C6: The applicable rates will remain stable. | D6: The applicable rates are the average of 13 banks in Vietnam. | G6: Total Pension Value | J6: ='[1]3'!I19 -> #REF!
B7: Inflation | C7: Annual living expenses increase with inflation rate. | D7: We do not change our lifestyle. | G7: Total Human Capital Value | J7: ='[1]3'!I16 -> #REF!
B8: Annual salary growth rate | C8: Using inflation rate as annual salary growth rate. | D8: We will not change the career path.
B9: Risk-Free rate | C9: Vietnam 30 year bond yield is fixed through the calculated period. | D9: Vietnam's 30 year bond yield serves as the risk-free rate.
B10: Retirement age | C10: Huyen and Huyen's husband retire, regulated by a new law. Specifically, Huyen retires at 60 and Huyen's husband retires at 62. Both retire at the end of the year. | D10: Based on Decree 135/2020 ND-CP.
B11: Marriage | C11: We marry at the end of year 2025 at all parent cost, wedding money will be a part of our saving cost. | D11: Our parents will support our wedding.
B12: Insurance premiums | C12: Insurance premiums are fixed during the contract period. | D12: Most insurance contracts promise fixed premiums.
B13: Life insurance | C13: We buy life insurance when we turn 30 years old. | D13: We hedge against premature death risk during the working period.
B14: Child | C14: Our child will become independent when he turns 22 years old. | D14: He can take responsibility for his life.
B15: Travel | C15: Travel in Asia, Europe, Australia and Africa. | D15: We fulfill our dream to travel around the world.
B16: Life expectancy | C16: Both will die at the end of the year 2088. | D16: Our life expectancy is both 85 years old.
B18: Key Financial Data | C18: Link
B19: Huyen's salary | C19: https://vtcnews.vn/soi-muc-luong-pho-bien-cua-cac-vi-tri-trong-ngan-hang-ar808150.html
B20: Huyen's husband salary | C20: https://vinatrain.edu.vn/muc-luong-cua-nhan-vien-tuyen-dung/
B21: Mortgage Interest Rate | C21: https://www.vpbank.com.vn/bi-kip-va-chia-se/retail-story-and-tips/loans-category/lai-suat-vay-mua-nha
B22: Bank Deposit Rate | C22: https://vietnamnet.vn/lai-suat-ngan-hang-hom-nay-14-5-2025-ky-han-6-thang-lai-suat-cao-nhat-5-65-2400896.html
B23: Inflation | C23: Vietnam- inflation rate 2029 | Statista
B24: Risk-Free Rate | C24: Vietnam 30 Year Bond Yield - Investing.com
B25: Tax Deduction And Duty | C25: https://thuvienphapluat.vn/van-ban/Thue-Phi-Le-Phi/Luat-thue-thu-nhap-ca-nhan-2007-04-2007-QH12-59652.aspx
B26: Tax | C26: Cách tính mức lương đóng BHXH 2024 từ 01/7 khi tăng lương tối thiểu vùng? Công thức tính lương đóng bảo hiểm xã hội mới nhất hiện nay thế nào? (thuvienphapluat.vn)
B27: Pension Value | C27: https://thuvienphapluat.vn/van-ban/Bao-hiem/Nghi-dinh-115-2015-ND-CP-huong-dan-Luat-bao-hiem-xa-hoi-bat-buoc-279974.aspx?anchor=dieu_9
B28: Probility Of Death | C28: Life tables: Life tables by country Viet Nam
B29: Retirement Age | C29: https://thuvienphapluat.vn/van-ban/Lao-dong-Tien-luong/Nghi-dinh-135-2020-ND-CP-tuoi-nghi-huu-445512.aspx
... B36: Car model | C36: https://toyota-angiang5s.com/san-pham/toyota-vios/

Sheet 2. Financial goals 
B3: Personal Image
B4: Age | C4: 22
B5: Married status | C5: Single
B6: Occupation | C6: Bank teller
B7: Accommodation | C7: Renting a one-bedroom apartment
B8: Source of income | C8: Salary from employment
B9: Career Timline | C9: Planning to work until retirement
B10: Life expectancy | C10: 85 years
B14: Period | D14: Position | E14: Goal | F14: Link
B15: Establishing a strong financial foundation (22-26) | C15: 22 - 24 | D15: Bank teller | E15: Get married and start a family. Focus on building my career and gaining valuable knowledge, start saving
C16: 25-26 | D16: Promotion to Controller | E16: Achieve a promotion and ensure financial stability to cover all expenses.
B17: Strategic Wealth Growth and Accumulation (27-60) | C17: 27-30 | D17: Promotion to Deputy Head of Customer Service | E17: Give birth child
C18: 31-33 | D18: Promotion to Head of Customer Service | E18: Purchase house worth VND 2 billion 450.
C19: 34-36 | D19: Promotion to Deputy Director of Operations | E19: In process of paying mortgage debt.
C20: 37-60 | D20: Promotion to Branch Director | E20: Pay off mortgage debt. Buy car worth VND 500 million.
B21: Sustaining and Optimizing Wealth Distribution (61-85) | C21: 61-85 | D21: Retirement | E21: Enjoy a secure, worry-free retirement and travel around the world.
B22: FOR RISK MANAGEMENT
B23: Earning risk | C23: Protect earning and human capital. | D23: Pay social insurance and save frequently.
B24: Health risk | C24: Minimize large medical expenses for the family. | D24: Buy health insurance for the family.
B25: Premature death risk | C25: Protect source of income for the family. | D25: Buy life insurance for both breadwinners.
B26: FOR CAPITAL ACCUMULATION
B27: Emergency fund | C27: Cover shorfall in income to ensure the minimum living standard.
B28: Savings fund | C28: Have savings fund by adding surplus left at the end of each period to next year saving amount.
B29: Investment fund | C29: Invest in stock and bond fund to earn interest and ensure cash inflow.

Sheet 3. Financial drivers 
B2: Taxable Income | F2: Applicable Interest Rate for Mortgage in 2025 | I2: Link | J2: Applicable Interest Rate for Deposit in 12 months | M2: Link
B3: Tax grade | C3: Taxable income/year (VND million) | D3: Tax rate | E3: Link | F3: No | G3: Bank's Name | H3: Applicable Interest Rate | J3: No | K3: Bank's Name | L3: Applicable Interest Rate
B4: 1 | C4: Up to 60 | D4: 0.05 | F4: 1 | G4: BIDV | H4: 0.05 | J4: 1 | K4: BIDV | L4: 0.047
B5: 2 | C5: Between over 60 and 120 | D5: 0.1 | F5: =F4+1 -> 2 | G5: Vietcombank | H5: 0.055 | J5: =J4+1 -> 2 | K5: Vietcombank | L5: 0.046
B6: 3 | C6: Between over 120 and 216 | D6: 0.15 | F6: =F5+1 -> 3 | G6: Agribank | H6: 0.06 | J6: =J5+1 -> 3 | K6: Agribank | L6: 0.048
B7: 4 | C7: Between over 216 and 384 | D7: 0.2 | F7: =F6+1 -> 4 | G7: Vietinbank | H7: 0.06 | J7: =J6+1 -> 4 | K7: Vietinbank | L7: 0.047
B8: 5 | C8: Between over 384 and 624 | D8: 0.25 | F8: =F7+1 -> 5 | G8: VIB | H8: 0.065 | J8: =J7+1 -> 5 | K8: VIB | L8: 0.049
B9: 6 | C9: Between over 624 and 960 | D9: 0.3 | F9: =F8+1 -> 6 | G9: Techcombank | H9: 0.067 | J9: =J8+1 -> 6 | K9: Techcombank | L9: 0.0475
B10: 7 | C10: Over 960 | D10: 0.35 | F10: =F9+1 -> 7 | G10: VPBank | H10: 0.072 | J10: =J9+1 -> 7 | K10: VPBank | L10: 0.05
F11: =F10+1 -> 8 | G11: TPBank | H11: 0.066 | J11: =J10+1 -> 8 | K11: TPBank | L11: 0.052
B12: Tax Deduction | D12: VND/year | F12: =F11+1 -> 9 | G12: ACB | H12: 0.07 | J12: =J11+1 -> 9 | K12: ACB | L12: 0.049
B13: Personal exemption | D13: 132000000 | E13: Link | F13: =F12+1 -> 10 | G13: Sacombank | H13: 0.07 | J13: =J12+1 -> 10 | K13: Sacombank | L13: 0.054
B14: Dependent exemption/ per dependent | D14: =4400000*12 -> 52800000 | E14: Link | F14: =F13+1 -> 11 | G14: MSB | H14: 0.062 | J14: =J13+1 -> 11 | K14: MSB | L14: 0.056
F15: =F14+1 -> 12 | G15: HDBank | H15: 0.065 | J15: =J14+1 -> 12 | K15: HDBank | L15: 0.056
F16: =F15+1 -> 13 | G16: MBBank | H16: 0.079 | J16: =J15+1 -> 13 | K16: MBBank | L16: 0.05
B17: Remaining Car Value | E17: Link | F17: Average | H17: =AVERAGE(H4:H16) -> 0.064692308 | J17: Average | L17: =MAX(L4:L16) -> 0.056
B18: Recently bought | D18: 1
B19: Within 1 year after buying | D19: 0.9
B20: Within over 1 year and 3 years after buying | D20: 0.7 | F20: Inflation Rate | H20: Link | J20: Calculations Of Discount Rate For Human Capital
B21: Within over 3 years and 6 years after buying | D21: 0.5 | F21: Year | G21: Rate | J21: Risk Free Rate (Vietnam Government Bond 20Y) | L21: 0.03474 | M21: Link
B22: Within over 6 years and 10 years after buying | D22: 0.3 | F22: 2021 | G22: 0.0184 | J22: Risk Premium Relating to Huyen's income | L22: 0.035
B23: Over 10 years after buying | D23: 0.2 | F23: =F22+1 -> 2022 | G23: 0.0316 | J23: Risk Premium Relating to Huyen's husband ncome | L23: 0.035
F24: =F23+1 -> 2023 | G24: 0.0325 | J24: Discount Rate For Huyen's income | L24: =L22+L21 -> 0.06974
B25: Huyen's Car Model | E25: Link | F25: =F24+1 -> 2024 | G25: 0.0362 | J25: Discount Rate For Huyen's husband income | L25: =L23+L21 -> 0.06974
B26: Huyen's Car | D26: VIOS 1.5E-MT | F26: =F25+1 -> 2025 | G26: 0.0295
B27: Buying price (in 2035) | D27: 458000000 | F27: =F26+1 -> 2026 | G27: 0.0249
F28: =F27+1 -> 2027 | G28: 0.028
F29: =F28+1 -> 2028 | G29: 0.029
F30: =F29+1 -> 2029 | G30: 0.029
F31: =F30+1 -> 2030 | G31: 0.029
F32: 2030 Afterwards | G32: =AVERAGE(G22:G31) -> 0.02881

Sheet 4. Balance sheet 
B2: Traditional Balance Sheet at the end of 2025, unit VND | K2: Economic Balance Sheet, unit VND
B4: ASSETS | C4: VND | D4: % | F4: LIABILITIES | G4: VND | H4: % | K4: ASSETS | L4: VND | M4: % | O4: LIABILITIES | P4: VND | Q4: %
B5: Liquid Assets | F5: Liabilities | K5: Assets | O5: Liabilities
B6: Cash | C6: 10000000 | D6: =C6/$C$18 -> 0.033757553 | F6: Short-term Liabilities | G6: 0 | H6: 0 | K6: Liquid Assets | O6: Short-term Liabilities | P6: 0 | Q6: 0
B7: Saving Account | C7: 70000000 | D7: =C7/$C$18 -> 0.23630287 | F7: Long-term Liabilities | G7: 0 | H7: 0 | K7: Cash | L7: 10000000 | M7: =L7/$L$25 -> 0.00055795519 | O7: Long-term Liabilities | P7: 0 | Q7: 0
B8: Checking Account | C8: 20000000 | D8: =C8/$C$18 -> 0.067515107 | F8: Others | G8: 0 | H8: 0 | K8: Saving Account | L8: 70000000 | M8: =L8/$L$25 -> 0.0039056864 | O8: Others | P8: 0 | Q8: 0
B9: Total liquid assets | C9: =SUM(C6:C8) -> 100000000 | D9: =C9/$C$18 -> 0.33757553 | F9: TOTAL LIABILITIES | G9: =SUM(G6:G8) -> 0 | K9: Checking Account | L9: 20000000 | M9: =L9/$L$25 -> 0.0011159104 | O9: Present Value of Lifetime Consumption Needs | P9: ='7. Human capital & pension valu'!C59 -> 3.0672922e+10
B10: Tangible Assets | F10: Net Worth | G10: =C18-G9 -> 296230000 | K10: Total liquid assets | L10: =SUM(L7:L9) -> 100000000 | O10: Economic Net Worth | P10: =L25-P9 -> -1.2750335e+10
B11: iPhone 15 promax | C11: 25000000 | D11: =C11/$C$18 -> 0.084393883 | F11: TOTAL LIABILITIES & NET WORTH | G11: =G10+G9 -> 296230000 | K11: Tangible Assets
B12: iPhone 16 promax | C12: 27990000 | D12: =C12/$C$18 -> 0.094487392 | K12: iPhone 15 promax | L12: 25000000 | M12: =L12/$L$25 -> 0.001394888
B13: Macbook Air 2017 | C13: 25000000 | D13: =C13/$C$18 -> 0.084393883 | K13: iPhone 16 promax | L13: 27990000 | M13: =L13/$L$25 -> 0.0015617166
B14: iPad | C14: 18000000 | D14: =C14/$C$18 -> 0.060763596 | F14: Short-term Liabilities | K14: Macbook Air 2017 | L14: 25000000 | M14: =L14/$L$25 -> 0.001394888
B15: Honda Scoopy | C15: 56000000 | D15: =C15/$C$18 -> 0.1890423 | K15: iPad | L15: 18000000 | M15: =L15/$L$25 -> 0.0010043194
B16: AirBlade 160 | C16: 44240000 | D16: =C16/$C$18 -> 0.14934342 | K16: Honda Scoopy | L16: 56000000 | M16: =L16/$L$25 -> 0.0031245491
B17: Total tangible assets | C17: =SUM(C11:C16) -> 196230000 | D17: =C17/$C$18 -> 0.66242447 | F17: Long-term Liabilities | G17: =G7 -> 0 | K17: AirBlade 160 | L17: 44240000 | M17: =L17/$L$25 -> 0.0024683938
B18: TOTAL ASSETS | C18: =C9+C17 -> 296230000 | K18: Total tangible assets | L18: =SUM(L12:L17) -> 196230000
K19: Human Capital
K20: Huyen's Human Capital | L20: ='7. Human capital & pension valu'!C21 -> 6.0981099e+09 | M20: =L20/$L$25 -> 0.34024721
B21: Key Ratio | C21: Formula | D21: Calculation | K21: Huyen's husband Human Capital | L21: ='7. Human capital & pension valu'!C34 -> 6.9863372e+09 | M21: =L21/$L$25 -> 0.38980632
B22: Solvency Ratio | C22: Net Worth/Total assets | D22: =G10/C18 -> 1 | K22: Pension Value
K23: Huyen's Pension Value | L23: ='7. Human capital & pension valu'!AP45 -> 2.2998207e+09 | M23: =L23/$L$25 -> 0.12831969
K24: Huyen's husband Pension Value | L24: ='7. Human capital & pension valu'!AP53 -> 2.2420883e+09 | M24: =L24/$L$25 -> 0.12509848
K25: TOTAL ASSETS | L25: =L10+L18+SUM(L20:L24) -> 1.7922586e+10

Sheet 5. Cash Flow
B2: Cash Flow Statement for the family at the end of 2025 | F2: Financial ratios | G2: Formula | H2: Calculation
B3: Income | C3: VND | D3: % | F3: Saving ratio | G3: Cash surplus/ income after tax | H3: =C11/('7. Human capital & pension valu'!C17+'7. Human capital & pension valu'!C30) -> 0.011603749
B4: Huyen's gross salary | C4: ='7. Human capital & pension valu'!C12 -> 179400000 | D4: =C4/C7 -> 0.47420173
B5: Huyen's husband gross salary | C5: ='7. Human capital & pension valu'!C25 -> 195000000 | D5: =C5/C7 -> 0.51543667
B6: Interest | C6: ='8. Budget Estimate'!C13 -> 3920000 | D6: =C6/C7 -> 0.010361599
B7: TOTAL INCOME | C7: =SUM(C4:C6) -> 378320000
B8: Expenses
B9: Living expense | C9: ='8. Budget Estimate'!C39 -> 374388000 | D9: =C9/C10 -> 1
B10: TOTAL EXPENSE | C10: =C9 -> 374388000
B11: Surplus/Deficit | C11: =C7-C10 -> 3932000

Sheet 6. Salary
B3: HUYEN | I3: HUYEN'S HUSBAND
B4: Year | C4: Age | D4: Position | E4: Monthly Salary | F4: Yearly Bonus | G4: Monthly Income | I4: Year | J4: Age | K4: Position | L4: Monthly Salary | M4: Yearly Bonus | N4: Monthly Income
B5: 2025 | C5: 22 | D5: Bank Teller | E5: 13800000 | F5: =E5 -> 13800000 | G5: =E5+F5/12 -> 14950000 | H5: Link | I5: 2025 | J5: 22 | K5: Recruitment Assistant | L5: 15000000 | M5: =L5 -> 15000000 | N5: =L5+M5/12 -> 16250000 | O5: Link
B6: =B5+1 -> 2026 | C6: =C5+1 -> 23 | E6: 13800000 | F6: =E6 -> 13800000 | G6: =E6+F6/12 -> 14950000 | H6: Link | I6: =I5+1 -> 2026 | J6: =J5+1 -> 23 | L6: 15000000 | M6: =L6 -> 15000000 | N6: =L6+M6/12 -> 16250000 | O6: Link
B7: =B6+1 -> 2027 | C7: =C6+1 -> 24 | E7: 13800000 | F7: =E7 -> 13800000 | G7: =E7+F7/12 -> 14950000 | H7: Link | I7: =I6+1 -> 2027 | J7: =J6+1 -> 24 | L7: 15000000 | M7: =L7 -> 15000000 | N7: =L7+M7/12 -> 16250000
B8: =B7+1 -> 2028 | C8: =C7+1 -> 25 | D8: Controller | E8: 17600000 | F8: =E8 -> 17600000 | G8: =E8+F8/12 -> 19066667 | I8: =I7+1 -> 2028 | J8: =J7+1 -> 25 | K8: Recruitment Specialist | L8: 20000000 | M8: =L8 -> 20000000 | N8: =L8+M8/12 -> 21666667
B9: =B8+1 -> 2029 | C9: =C8+1 -> 26 | E9: 17600000 | F9: =E9 -> 17600000 | G9: =E9+F9/12 -> 19066667 | I9: =I8+1 -> 2029 | J9: =J8+1 -> 26 | L9: 20000000 | M9: =L9 -> 20000000 | N9: =L9+M9/12 -> 21666667
B10: =B9+1 -> 2030 | C10: =C9+1 -> 27 | D10: Deputy Head of Customer Service | E10: 20000000 | F10: =E10 -> 20000000 | G10: =E10+F10/12 -> 21666667 | I10: =I9+1 -> 2030 | J10: =J9+1 -> 27 | L10: 20000000 | M10: =L10 -> 20000000 | N10: =L10+M10/12 -> 21666667
B11: =B10+1 -> 2031 | C11: =C10+1 -> 28 | E11: 20000000 | F11: =E11 -> 20000000 | G11: =E11+F11/12 -> 21666667 | I11: =I10+1 -> 2031 | J11: =J10+1 -> 28 | K11: Recruitment Team Leader | L11: 25000000 | M11: =L11 -> 25000000 | N11: =L11+M11/12 -> 27083333
B12: =B11+1 -> 2032 | C12: =C11+1 -> 29 | E12: 20000000 | F12: =E12 -> 20000000 | G12: =E12+F12/12 -> 21666667 | I12: =I11+1 -> 2032 | J12: =J11+1 -> 29 | L12: 25000000 | M12: =L12 -> 25000000 | N12: =L12+M12/12 -> 27083333
B13: =B12+1 -> 2033 | C13: =C12+1 -> 30 | E13: 20000000 | F13: =E13 -> 20000000 | G13: =E13+F13/12 -> 21666667 | I13: =I12+1 -> 2033 | J13: =J12+1 -> 30 | K13: Recruitment Manager | L13: 35000000 | M13: =L13 -> 35000000 | N13: =L13+M13/12 -> 37916667
B14: =B13+1 -> 2034 | C14: =C13+1 -> 31 | D14: Head of Customer Service | E14: 25000000 | F14: =E14 -> 25000000 | G14: =E14+F14/12 -> 27083333 | I14: =I13+1 -> 2034 | J14: =J13+1 -> 31 | L14: 35000000 | M14: =L14 -> 35000000 | N14: =L14+M14/12 -> 37916667
B15: =B14+1 -> 2035 | C15: =C14+1 -> 32 | E15: 25000000 | F15: =E15 -> 25000000 | G15: =E15+F15/12 -> 27083333 | I15: =I14+1 -> 2035 | J15: =J14+1 -> 32 | L15: 35000000 | M15: =L15 -> 35000000 | N15: =L15+M15/12 -> 37916667
B16: =B15+1 -> 2036 | C16: =C15+1 -> 33 | E16: 25000000 | F16: =E16 -> 25000000 | G16: =E16+F16/12 -> 27083333 | I16: =I15+1 -> 2036 | J16: =J15+1 -> 33 | L16: 35000000 | M16: =L16 -> 35000000 | N16: =L16+M16/12 -> 37916667
B17: =B16+1 -> 2037 | C17: =C16+1 -> 34 | D17: Deputy Director of Operations | E17: 40000000 | F17: =E17 -> 40000000 | G17: =E17+F17/12 -> 43333333 | I17: =I16+1 -> 2037 | J17: =J16+1 -> 34 | L17: 35000000 | M17: =L17 -> 35000000 | N17: =L17+M17/12 -> 37916667
B18: =B17+1 -> 2038 | C18: =C17+1 -> 35 | E18: 40000000 | F18: =E18 -> 40000000 | G18: =E18+F18/12 -> 43333333 | I18: =I17+1 -> 2038 | J18: =J17+1 -> 35 | K18: Recruitment Director | L18: 45000000 | M18: =L18 -> 45000000 | N18: =L18+M18/12 -> 48750000
B19: =B18+1 -> 2039 | C19: =C18+1 -> 36 | E19: 40000000 | F19: =E19 -> 40000000 | G19: =E19+F19/12 -> 43333333 | I19: =I18+1 -> 2039 | J19: =J18+1 -> 36 | L19: 45000000 | M19: =L19 -> 45000000 | N19: =L19+M19/12 -> 48750000
B20: =B19+1 -> 2040 | C20: =C19+1 -> 37 | D20: Branch manager | E20: 70000000 | F20: =E20 -> 70000000 | G20: =E20+F20/12 -> 75833333 | I20: =I19+1 -> 2040 | J20: =J19+1 -> 37 | L20: 45000000 | M20: =L20 -> 45000000 | N20: =L20+M20/12 -> 48750000
B21: =B20+1 -> 2041 | C21: =C20+1 -> 38 | E21: 70000000 | F21: =E21 -> 70000000 | G21: =E21+F21/12 -> 75833333 | I21: =I20+1 -> 2041 | J21: =J20+1 -> 38 | L21: 45000000 | M21: =L21 -> 45000000 | N21: =L21+M21/12 -> 48750000
B22: =B21+1 -> 2042 | C22: =C21+1 -> 39 | E22: 70000000 | F22: =E22 -> 70000000 | G22: =E22+F22/12 -> 75833333 | I22: =I21+1 -> 2042 | J22: =J21+1 -> 39 | K22: HR Director | L22: 80000000 | M22: =L22 -> 80000000 | N22: =L22+M22/12 -> 86666667
B23: =B22+1 -> 2043 | C23: =C22+1 -> 40 | E23: 70000000 | F23: =E23 -> 70000000 | G23: =E23+F23/12 -> 75833333 | I23: =I22+1 -> 2043 | J23: =J22+1 -> 40 | L23: 80000000 | M23: =L23 -> 80000000 | N23: =L23+M23/12 -> 86666667
B24: =B23+1 -> 2044 | C24: =C23+1 -> 41 | E24: 70000000 | F24: =E24 -> 70000000 | G24: =E24+F24/12 -> 75833333 | I24: =I23+1 -> 2044 | J24: =J23+1 -> 41 | L24: 80000000 | M24: =L24 -> 80000000 | N24: =L24+M24/12 -> 86666667
B25: =B24+1 -> 2045 | C25: =C24+1 -> 42 | E25: 70000000 | F25: =E25 -> 70000000 | G25: =E25+F25/12 -> 75833333 | I25: =I24+1 -> 2045 | J25: =J24+1 -> 42 | L25: 80000000 | M25: =L25 -> 80000000 | N25: =L25+M25/12 -> 86666667
B26: =B25+1 -> 2046 | C26: =C25+1 -> 43 | E26: 70000000 | F26: =E26 -> 70000000 | G26: =E26+F26/12 -> 75833333 | I26: =I25+1 -> 2046 | J26: =J25+1 -> 43 | L26: 80000000 | M26: =L26 -> 80000000 | N26: =L26+M26/12 -> 86666667
B27: =B26+1 -> 2047 | C27: =C26+1 -> 44 | E27: 70000000 | F27: =E27 -> 70000000 | G27: =E27+F27/12 -> 75833333 | I27: =I26+1 -> 2047 | J27: =J26+1 -> 44 | L27: 80000000 | M27: =L27 -> 80000000 | N27: =L27+M27/12 -> 86666667
B28: =B27+1 -> 2048 | C28: =C27+1 -> 45 | E28: 70000000 | F28: =E28 -> 70000000 | G28: =E28+F28/12 -> 75833333 | I28: =I27+1 -> 2048 | J28: =J27+1 -> 45 | L28: 80000000 | M28: =L28 -> 80000000 | N28: =L28+M28/12 -> 86666667
B29: =B28+1 -> 2049 | C29: =C28+1 -> 46 | E29: 70000000 | F29: =E29 -> 70000000 | G29: =E29+F29/12 -> 75833333 | I29: =I28+1 -> 2049 | J29: =J28+1 -> 46 | L29: 80000000 | M29: =L29 -> 80000000 | N29: =L29+M29/12 -> 86666667
B30: =B29+1 -> 2050 | C30: =C29+1 -> 47 | E30: 70000000 | F30: =E30 -> 70000000 | G30: =E30+F30/12 -> 75833333 | I30: =I29+1 -> 2050 | J30: =J29+1 -> 47 | L30: 80000000 | M30: =L30 -> 80000000 | N30: =L30+M30/12 -> 86666667
B31: =B30+1 -> 2051 | C31: =C30+1 -> 48 | E31: 70000000 | F31: =E31 -> 70000000 | G31: =E31+F31/12 -> 75833333 | I31: =I30+1 -> 2051 | J31: =J30+1 -> 48 | L31: 80000000 | M31: =L31 -> 80000000 | N31: =L31+M31/12 -> 86666667
B32: =B31+1 -> 2052 | C32: =C31+1 -> 49 | E32: 70000000 | F32: =E32 -> 70000000 | G32: =E32+F32/12 -> 75833333 | I32: =I31+1 -> 2052 | J32: =J31+1 -> 49 | L32: 80000000 | M32: =L32 -> 80000000 | N32: =L32+M32/12 -> 86666667
B33: =B32+1 -> 2053 | C33: =C32+1 -> 50 | E33: 70000000 | F33: =E33 -> 70000000 | G33: =E33+F33/12 -> 75833333 | I33: =I32+1 -> 2053 | J33: =J32+1 -> 50 | L33: 80000000 | M33: =L33 -> 80000000 | N33: =L33+M33/12 -> 86666667
B34: =B33+1 -> 2054 | C34: =C33+1 -> 51 | E34: 70000000 | F34: =E34 -> 70000000 | G34: =E34+F34/12 -> 75833333 | I34: =I33+1 -> 2054 | J34: =J33+1 -> 51 | L34: 80000000 | M34: =L34 -> 80000000 | N34: =L34+M34/12 -> 86666667
... B43: =B42+1 -> 2063 | C43: =C42+1 -> 60 | E43: 70000000 | F43: =E43 -> 70000000 | G43: =E43+F43/12 -> 75833333 | I43: =I42+1 -> 2063 | J43: =J42+1 -> 60 | L43: 80000000 | M43: =L43 -> 80000000 | N43: =L43+M43/12 -> 86666667
I44: =I43+1 -> 2064 | J44: =J43+1 -> 61 | L44: 80000000 | M44: =L44 -> 80000000 | N44: =L44+M44/12 -> 86666667
I45: =I44+1 -> 2065 | J45: =J44+1 -> 62 | L45: 80000000 | M45: =L45 -> 80000000 | N45: =L45+M45/12 -> 86666667

Sheet 7. Human capital & pension valu
A1: Time Line | B1: 2024 | C1: 2025 | D1: =C1+1 -> 2026 | E1: =D1+1 -> 2027 | F1: =E1+1 -> 2028 | G1: =F1+1 -> 2029 | H1: =G1+1 -> 2030 | I1: =H1+1 -> 2031 | J1: =I1+1 -> 2032 | K1: =J1+1 -> 2033 | ... BN1: =BM1+1 -> 2088
A2: Period | B2: 0 | C2: 1 | D2: 2 | E2: =D2+1 -> 3 | F2: =E2+1 -> 4 | G2: =F2+1 -> 5 | H2: =G2+1 -> 6 | I2: =H2+1 -> 7 | J2: =I2+1 -> 8 | K2: =J2+1 -> 9 | L2: =K2+1 -> 10 | ... BN2: =BM2+1 -> 64
A3: Inflation rate | C3: ='3. Financial drivers '!G26 -> 0.0295 | D3: ='3. Financial drivers '!G27 -> 0.0249 | E3: ='3. Financial drivers '!G28 -> 0.028 | F3: ='3. Financial drivers '!G29 -> 0.029 | G3: ='3. Financial drivers '!G30 -> 0.029 | H3: ='3. Financial drivers '!G31 -> 0.029 | I3: ='3. Financial drivers '!$G$32 -> 0.02881 | J3: ='3. Financial drivers '!$G$32 -> 0.02881 | K3: ='3. Financial drivers '!$G$32 -> 0.02881 | L3: ='3. Financial drivers '!$G$32 -> 0.02881 | M3: ='3. Financial drivers '!$G$32 -> 0.02881 | N3: ='3. Financial drivers '!$G$32 -> 0.02881 | O3: ='3. Financial drivers '!$G$32 -> 0.02881 | P3: ='3. Financial drivers '!$G$32 -> 0.02881 | ... BN3: ='3. Financial drivers '!$G$32 -> 0.02881
A4: Huyen | C4: Bank Teller | F4: Controller | H4: Deputy Head of Customer Service | L4: Head of Customer Service | O4: Deputy Director of Operations | R4: Branch manager | AO4: Huyen retires | BN4: Pass away
A5: Huyen's husband | C5: Recruitment Assistant | F5: Recruitment Specialist | I5: Recruitment Team Leader | K5: Recruitment Manager | P5: Recruitment Director | T5: HR director | AQ5: Huyen's husband retires
A6: Young Children | H6: Give birth and Huyen's 6 months maternity leave | Z6: Start university | AD6: Become independent
A7: Our family | M7: Buy house and pay off mortgage | Z7: Buy car | AS7: Vacation period
A10: HUMAN CAPITAL
A11: Human captial - Huyen
A12: Pre tax income | C12: ='6. Salary'!G5*12 -> 179400000 | D12: =C12*(1+D3) -> 183867060 | E12: =D12*(1+E3) -> 1.8901534e+08 | F12: ='6. Salary'!G8*12 -> 228800000 | G12: =F12*(1+G3) -> 2.354352e+08 | H12: ='6. Salary'!G10*6 -> 130000000 | I12: ='6. Salary'!G10*12*(1+I3) -> 267490600 | J12: =I12*(1+J3) -> 2.75197e+08 | K12: =J12*(1+K3) -> 2.8312543e+08 | L12: ='6. Salary'!G14*12 -> 325000000 | M12: =L12*(1+M3) -> 334363250 | N12: =M12*(1+N3) -> 3.4399626e+08 | O12: ='6. Salary'!G17*12 -> 520000000 | P12: =O12*(1+P3) -> 534981200 | Q12: =P12*(1+Q3) -> 5.5039401e+08 | R12: ='6. Salary'!G20*12 -> 910000000 | S12: =R12*(1+S3) -> 936217100 | T12: =S12*(1+T3) -> 9.6318951e+08 | U12: =T12*(1+U3) -> 9.90939e+08 | V12: =U12*(1+V3) -> 1.019488e+09 | W12: =V12*(1+W3) -> 1.0488594e+09 | X12: =W12*(1+X3) -> 1.079077e+09 | Y12: =X12*(1+Y3) -> 1.1101653e+09 | Z12: =Y12*(1+Z3) -> 1.1421491e+09 | ... AO12: =AN12*(1+AO3) -> 1.7488415e+09
A13: Total deduction | C13: =11000000*12 -> 132000000 | D13: =11000000*12 -> 132000000 | E13: =11000000*12 -> 132000000 | F13: =11000000*12 -> 132000000 | G13: =11000000*12 -> 132000000 | H13: =11000000*6 -> 66000000 | I13: =11000000*12 -> 132000000 | J13: =11000000*12 -> 132000000 | K13: =11000000*12 -> 132000000 | L13: =11000000*12 -> 132000000 | M13: =11000000*12 -> 132000000 | N13: =11000000*12 -> 132000000 | O13: =11000000*12 -> 132000000 | P13: =11000000*12 -> 132000000 | ... AO13: =11000000*12 -> 132000000
A14: Social insurance | C14: =C12*$C$66 -> 18837000 | D14: =D12*$C$66 -> 19306041 | E14: =E12*$C$66 -> 19846610 | F14: =F12*$C$66 -> 24024000 | G14: =G12*$C$66 -> 24720696 | H14: =H12*$C$66 -> 13650000 | I14: =I12*$C$66 -> 28086513 | J14: =J12*$C$66 -> 28895685 | ... AO14: =AO12*$C$66 -> 1.8362836e+08
A15: Assessable income | C15: =C12-SUM(C13:C14) -> 28563000 | D15: =D12-SUM(D13:D14) -> 32561019 | E15: =E12-SUM(E13:E14) -> 37168727 | F15: =F12-SUM(F13:F14) -> 72776000 | G15: =G12-SUM(G13:G14) -> 78714504 | H15: =H12-SUM(H14) -> 116350000 | I15: =I12-SUM(I13:I14) -> 107404087 | J15: =J12-SUM(J13:J14) -> 1.1430132e+08 | K15: =K12-SUM(K13:K14) -> 1.2139726e+08 | L15: =L12-SUM(L13:L14) -> 158875000 | M15: =M12-SUM(M13:M14) -> 1.6725511e+08 | N15: =N12-SUM(N13:N14) -> 1.7587665e+08 | O15: =O12-SUM(O13:O14) -> 333400000 | P15: =P12-SUM(P13:P14) -> 346808174 | ... AO15: =AO12-SUM(AO13:AO14) -> 1.4332132e+09
A16: Income tax | C16: =IF(C15<=60000000,C15*0.5,IF(C15<=120000000,60000000*0.5+(C15-60000000)*0.1,IF(C15<=216000000,60000000*0.5+60000000*0.1+(C15-120000000)*0.15,IF(C15<=384000000,60000000*0.5+60000000*0.1+96000000*0.15+(C15-216000000)*0.2,IF(C15<=624000000,60000000*0.5+60000000*0.1+96000000*0.15+168000000*0.2+(C15-384000000)*0.25,IF(C15<=960000000,60000000*0.5+60000000*0.1+96000000*0.15+168000000*0.2+240000000*0.25+(C15-624000000)*0.3,60000000*0.5+60000000*0.1+96000000*0.15+168000000*0.2+240000000*0.25+336000000*0.3+(C15-960000000)*0.35)))))) -> 14281500 | D16: =IF(D15<=60000000,D15*0.5,IF(D15<=120000000,60000000*0.5+(D15-60000000)*0.1,IF(D15<=216000000,60000000*0.5+60000000*0.1+(D15-120000000)*0.15,IF(D15<=384000000,60000000*0.5+60000000*0.1+96000000*0.15+(D15-216000000)*0.2,IF(D15<=624000000,60000000*0.5+60000000*0.1+96000000*0.15+168000000*0.2+(D15-384000000)*0.25,IF(D15<=960000000,60000000*0.5+60000000*0.1+96000000*0.15+168000000*0.2+240000000*0.25+(D15-624000000)*0.3,60000000*0.5+60000000*0.1+96000000*0.15+168000000*0.2+240000000*0.25+336000000*0.3+(D15-960000000)*0.35)))))) -> 16280509 | E16: =IF(E15<=60000000,E15*0.5,IF(E15<=120000000,60000000*0.5+(E15-60000000)*0.1,IF(E15<=216000000,60000000*0.5+60000000*0.1+(E15-120000000)*0.15,IF(E15<=384000000,60000000*0.5+60000000*0.1+96000000*0.15+(E15-216000000)*0.2,IF(E15<=624000000,60000000*0.5+60000000*0.1+96000000*0.15+168000000*0.2+(E15-384000000)*0.25,IF(E15<=960000000,60000000*0.5+60000000*0.1+96000000*0.15+168000000*0.2+240000000*0.25+(E15-624000000)*0.3,60000000*0.5+60000000*0.1+96000000*0.15+168000000*0.2+240000000*0.25+336000000*0.3+(E15-960000000)*0.35)))))) -> 18584364 | F16: =IF(F15<=60000000,F15*0.5,IF(F15<=120000000,60000000*0.5+(F15-60000000)*0.1,IF(F15<=216000000,60000000*0.5+60000000*0.1+(F15-120000000)*0.15,IF(F15<=384000000,60000000*0.5+60000000*0.1+96000000*0.15+(F15-216000000)*0.2,IF(F15<=624000000,60000000*0.5+60000000*0.1+96000000*0.15+168000000*0.2+(F15-384000000)*0.25,IF(F15<=960000000,60000000*0.5+60000000*0.1+96000000*0.15+168000000*0.2+240000000*0.25+(F15-624000000)*0.3,60000000*0.5+60000000*0.1+96000000*0.15+168000000*0.2+240000000*0.25+336000000*0.3+(F15-960000000)*0.35)))))) -> 31277600 | G16: =IF(G15<=60000000,G15*0.5,IF(G15<=120000000,60000000*0.5+(G15-60000000)*0.1,IF(G15<=216000000,60000000*0.5+60000000*0.1+(G15-120000000)*0.15,IF(G15<=384000000,60000000*0.5+60000000*0.1+96000000*0.15+(G15-216000000)*0.2,IF(G15<=624000000,60000000*0.5+60000000*0.1+96000000*0.15+168000000*0.2+(G15-384000000)*0.25,IF(G15<=960000000,60000000*0.5+60000000*0.1+96000000*0.15+168000000*0.2+240000000*0.25+(G15-624000000)*0.3,60000000*0.5+60000000*0.1+96000000*0.15+168000000*0.2+240000000*0.25+336000000*0.3+(G15-960000000)*0.35)))))) -> 31871450 | H16: =IF(H15<=60000000,I15*0.5,IF(H15<=120000000,60000000*0.5+(H15-60000000)*0.1,IF(H15<=216000000,60000000*0.5+60000000*0.1+(H15-120000000)*0.15,IF(H15<=384000000,60000000*0.5+60000000*0.1+96000000*0.15+(H15-216000000)*0.2,IF(H15<=624000000,60000000*0.5+60000000*0.1+96000000*0.15+168000000*0.2+(H15-384000000)*0.25,IF(H15<=960000000,60000000*0.5+60000000*0.1+96000000*0.15+168000000*0.2+240000000*0.25+(H15-624000000)*0.3,60000000*0.5+60000000*0.1+96000000*0.15+168000000*0.2+240000000*0.25+336000000*0.3+(H15-960000000)*0.35)))))) -> 35635000 | I16: =IF(I15<=60000000,I15*0.5,IF(I15<=120000000,60000000*0.5+(I15-60000000)*0.1,IF(I15<=216000000,60000000*0.5+60000000*0.1+(I15-120000000)*0.15,IF(I15<=384000000,60000000*0.5+60000000*0.1+96000000*0.15+(I15-216000000)*0.2,IF(I15<=624000000,60000000*0.5+60000000*0.1+96000000*0.15+168000000*0.2+(I15-384000000)*0.25,IF(I15<=960000000,60000000*0.5+60000000*0.1+96000000*0.15+168000000*0.2+240000000*0.25+(I15-624000000)*0.3,60000000*0.5+60000000*0.1+96000000*0.15+168000000*0.2+240000000*0.25+336000000*0.3+(I15-960000000)*0.35)))))) -> 34740409 | J16: =IF(J15<=60000000,J15*0.5,IF(J15<=120000000,60000000*0.5+(J15-60000000)*0.1,IF(J15<=216000000,60000000*0.5+60000000*0.1+(J15-120000000)*0.15,IF(J15<=384000000,60000000*0.5+60000000*0.1+96000000*0.15+(J15-216000000)*0.2,IF(J15<=624000000,60000000*0.5+60000000*0.1+96000000*0.15+168000000*0.2+(J15-384000000)*0.25,IF(J15<=960000000,60000000*0.5+60000000*0.1+96000000*0.15+168000000*0.2+240000000*0.25+(J15-624000000)*0.3,60000000*0.5+60000000*0.1+96000000*0.15+168000000*0.2+240000000*0.25+336000000*0.3+(J15-960000000)*0.35)))))) -> 35430132 | K16: =IF(K15<=60000000,K15*0.5,IF(K15<=120000000,60000000*0.5+(K15-60000000)*0.1,IF(K15<=216000000,60000000*0.5+60000000*0.1+(K15-120000000)*0.15,IF(K15<=384000000,60000000*0.5+60000000*0.1+96000000*0.15+(K15-216000000)*0.2,IF(K15<=624000000,60000000*0.5+60000000*0.1+96000000*0.15+168000000*0.2+(K15-384000000)*0.25,IF(K15<=960000000,60000000*0.5+60000000*0.1+96000000*0.15+168000000*0.2+240000000*0.25+(K15-624000000)*0.3,60000000*0.5+60000000*0.1+96000000*0.15+168000000*0.2+240000000*0.25+336000000*0.3+(K15-960000000)*0.35)))))) -> 36209589 | L16: =IF(L15<=60000000,L15*0.5,IF(L15<=120000000,60000000*0.5+(L15-60000000)*0.1,IF(L15<=216000000,60000000*0.5+60000000*0.1+(L15-120000000)*0.15,IF(L15<=384000000,60000000*0.5+60000000*0.1+96000000*0.15+(L15-216000000)*0.2,IF(L15<=624000000,60000000*0.5+60000000*0.1+96000000*0.15+168000000*0.2+(L15-384000000)*0.25,IF(L15<=960000000,60000000*0.5+60000000*0.1+96000000*0.15+168000000*0.2+240000000*0.25+(L15-624000000)*0.3,60000000*0.5+60000000*0.1+96000000*0.15+168000000*0.2+240000000*0.25+336000000*0.3+(L15-960000000)*0.35)))))) -> 41831250 | M16: =IF(M15<=60000000,M15*0.5,IF(M15<=120000000,60000000*0.5+(M15-60000000)*0.1,IF(M15<=216000000,60000000*0.5+60000000*0.1+(M15-120000000)*0.15,IF(M15<=384000000,60000000*0.5+60000000*0.1+96000000*0.15+(M15-216000000)*0.2,IF(M15<=624000000,60000000*0.5+60000000*0.1+96000000*0.15+168000000*0.2+(M15-384000000)*0.25,IF(M15<=960000000,60000000*0.5+60000000*0.1+96000000*0.15+168000000*0.2+240000000*0.25+(M15-624000000)*0.3,60000000*0.5+60000000*0.1+96000000*0.15+168000000*0.2+240000000*0.25+336000000*0.3+(M15-960000000)*0.35)))))) -> 43088266 | N16: =IF(N15<=60000000,N15*0.5,IF(N15<=120000000,60000000*0.5+(N15-60000000)*0.1,IF(N15<=216000000,60000000*0.5+60000000*0.1+(N15-120000000)*0.15,IF(N15<=384000000,60000000*0.5+60000000*0.1+96000000*0.15+(N15-216000000)*0.2,IF(N15<=624000000,60000000*0.5+60000000*0.1+96000000*0.15+168000000*0.2+(N15-384000000)*0.25,IF(N15<=960000000,60000000*0.5+60000000*0.1+96000000*0.15+168000000*0.2+240000000*0.25+(N15-624000000)*0.3,60000000*0.5+60000000*0.1+96000000*0.15+168000000*0.2+240000000*0.25+336000000*0.3+(N15-960000000)*0.35)))))) -> 44381497 | O16: =IF(O15<=60000000,O15*0.5,IF(O15<=120000000,60000000*0.5+(O15-60000000)*0.1,IF(O15<=216000000,60000000*0.5+60000000*0.1+(O15-120000000)*0.15,IF(O15<=384000000,60000000*0.5+60000000*0.1+96000000*0.15+(O15-216000000)*0.2,IF(O15<=624000000,60000000*0.5+60000000*0.1+96000000*0.15+168000000*0.2+(O15-384000000)*0.25,IF(O15<=960000000,60000000*0.5+60000000*0.1+96000000*0.15+168000000*0.2+240000000*0.25+(O15-624000000)*0.3,60000000*0.5+60000000*0.1+96000000*0.15+168000000*0.2+240000000*0.25+336000000*0.3+(O15-960000000)*0.35)))))) -> 73880000 | P16: =IF(P15<=60000000,P15*0.5,IF(P15<=120000000,60000000*0.5+(P15-60000000)*0.1,IF(P15<=216000000,60000000*0.5+60000000*0.1+(P15-120000000)*0.15,IF(P15<=384000000,60000000*0.5+60000000*0.1+96000000*0.15+(P15-216000000)*0.2,IF(P15<=624000000,60000000*0.5+60000000*0.1+96000000*0.15+168000000*0.2+(P15-384000000)*0.25,IF(P15<=960000000,60000000*0.5+60000000*0.1+96000000*0.15+168000000*0.2+240000000*0.25+(P15-624000000)*0.3,60000000*0.5+60000000*0.1+96000000*0.15+168000000*0.2+240000000*0.25+336000000*0.3+(P15-960000000)*0.35)))))) -> 76561635 | ... AO16: =IF(AO15<=60000000,AO15*0.5,IF(AO15<=120000000,60000000*0.5+(AO15-60000000)*0.1,IF(AO15<=216000000,60000000*0.5+60000000*0.1+(AO15-120000000)*0.15,IF(AO15<=384000000,60000000*0.5+60000000*0.1+96000000*0.15+(AO15-216000000)*0.2,IF(AO15<=624000000,60000000*0.5+60000000*0.1+96000000*0.15+168000000*0.2+(AO15-384000000)*0.25,IF(AO15<=960000000,60000000*0.5+60000000*0.1+96000000*0.15+168000000*0.2+240000000*0.25+(AO15-624000000)*0.3,60000000*0.5+60000000*0.1+96000000*0.15+168000000*0.2+240000000*0.25+336000000*0.3+(AO15-960000000)*0.35)))))) -> 4.1042461e+08
A17: After tax income | C17: =C12-C16 -> 165118500 | D17: =D12-D16 -> 1.6758655e+08 | E17: =E12-E16 -> 1.7043097e+08 | F17: =F12-F16 -> 197522400 | G17: =G12-G16 -> 2.0356375e+08 | H17: =H12-H16 -> 94365000 | I17: =I12-I16 -> 2.3275019e+08 | J17: =J12-J16 -> 2.3976687e+08 | ... AO17: =AO12-AO16 -> 1.3384169e+09
A18: Present value of future income | C18: =C17 -> 165118500 | D18: =D17/((1+$C$64)^D2) -> 1.4644775e+08 | E18: =E17/((1+$C$64)^E2) -> 1.3922391e+08 | F18: =F17/(1+$C$64)^F2 -> 1.5083545e+08 | G18: =G17/(1+$C$64)^G2 -> 1.453146e+08 | H18: =H17/(1+$C$64)^H2 -> 62971137 | I18: =I17/(1+$C$64)^I2 -> 1.451919e+08 | J18: =J17/(1+$C$64)^J2 -> 1.3981807e+08 | K18: =K17/(1+$C$64)^K2 -> 1.3459993e+08 | L18: =L17/(1+$C$64)^L2 -> 1.4429888e+08 | M18: =M17/(1+$C$64)^M2 -> 1.3875307e+08 | ... AO18: =AO17/(1+$C$64)^AO2 -> 96547324
A19: Age of Huyen | C19: 22 | D19: =C19+1 -> 23 | E19: =D19+1 -> 24 | F19: =E19+1 -> 25 | G19: =F19+1 -> 26 | H19: =G19+1 -> 27 | I19: =H19+1 -> 28 | J19: =I19+1 -> 29 | K19: =J19+1 -> 30 | ... AO19: =AN19+1 -> 60
A20: Probability of surviving | C20: =1-0.000416227 -> 0.99958377 | D20: =1-0.000416227 -> 0.99958377 | E20: =1-0.000416227 -> 0.99958377 | F20: =1-0.000472252 -> 0.99952775 | G20: =1-0.000472252 -> 0.99952775 | H20: =1-0.000472252 -> 0.99952775 | I20: =1-0.000472252 -> 0.99952775 | J20: =1-0.000472252 -> 0.99952775 | K20: =1-0.000615292 -> 0.99938471 | L20: =1-0.000615292 -> 0.99938471 | M20: =1-0.000615292 -> 0.99938471 | N20: =1-0.000615292 -> 0.99938471 | O20: =1-0.000615292 -> 0.99938471 | P20: =1-0.000912829 -> 0.99908717 | Q20: =1-0.000912829 -> 0.99908717 | R20: =1-0.000912829 -> 0.99908717 | S20: =1-0.000912829 -> 0.99908717 | T20: =1-0.000912829 -> 0.99908717 | U20: =1-0.001452051 -> 0.99854795 | V20: =1-0.001452051 -> 0.99854795 | W20: =1-0.001452051 -> 0.99854795 | X20: =1-0.001452051 -> 0.99854795 | Y20: =1-0.001452051 -> 0.99854795 | Z20: =1-0.002280473 -> 0.99771953 | AA20: =1-0.002280473 -> 0.99771953 | AB20: =1-0.002280473 -> 0.99771953 | AC20: =1-0.002280473 -> 0.99771953 | AD20: =1-0.002280473 -> 0.99771953 | AE20: =1-0.003585945 -> 0.99641406 | AF20: =1-0.003585945 -> 0.99641406 | AG20: =1-0.003585945 -> 0.99641406 | AH20: =1-0.003585945 -> 0.99641406 | AI20: =1-0.003585945 -> 0.99641406 | AJ20: =1-0.005487598 -> 0.9945124 | AK20: =1-0.005487598 -> 0.9945124 | AL20: =1-0.005487598 -> 0.9945124 | AM20: =1-0.005487598 -> 0.9945124 | AN20: =1-0.005487598 -> 0.9945124 | AO20: =1-0.008891343 -> 0.99110866
A21: Human capital | C21: =SUMPRODUCT(C18:AO18,C20:AO20) -> 6.0981099e+09
A24: Human captial - Huyen's husband
A25: Pre tax income | C25: ='6. Salary'!N5*12 -> 195000000 | D25: =C25*(1+D3) -> 1.998555e+08 | E25: =D25*(1+E3) -> 2.0545145e+08 | F25: ='6. Salary'!N8*12 -> 260000000 | G25: =F25*(1+G3) -> 2.6754e+08 | H25: =G25*(1+H3) -> 2.7529866e+08 | I25: ='6. Salary'!N11*12 -> 325000000 | J25: =I25*(1+J3) -> 334363250 | K25: ='6. Salary'!N13*12 -> 455000000 | L25: =K25*(1+L3) -> 468108550 | M25: =L25*(1+M3) -> 4.8159476e+08 | N25: =M25*(1+N3) -> 4.954695e+08 | O25: =N25*(1+O3) -> 5.0974398e+08 | P25: ='6. Salary'!N18*12 -> 585000000 | Q25: =P25*(1+Q3) -> 601853850 | R25: =Q25*(1+R3) -> 6.1919326e+08 | S25: =R25*(1+S3) -> 6.3703222e+08 | T25: ='6. Salary'!N22*12 -> 1040000000 | U25: =T25*(1+U3) -> 1069962400 | V25: =U25*(1+V3) -> 1.100788e+09 | W25: =V25*(1+W3) -> 1.1325017e+09 | X25: =W25*(1+X3) -> 1.1651291e+09 | Y25: =X25*(1+Y3) -> 1.1986965e+09 | Z25: =Y25*(1+Z3) -> 1.2332309e+09 | AA25: =Z25*(1+AA3) -> 1.2687603e+09 | AB25: =AA25*(1+AB3) -> 1.3053133e+09 | ... AQ25: =AP25*(1+AQ3) -> 1.9986761e+09
A26: Total deduction | C26: =11000000*12 -> 132000000 | D26: =11000000*12 -> 132000000 | E26: =11000000*12 -> 132000000 | F26: =11000000*12 -> 132000000 | G26: =11000000*12 -> 132000000 | H26: =11000000*12+4400000*12 -> 184800000 | I26: =11000000*12+4400000*12 -> 184800000 | J26: =11000000*12+4400000*12 -> 184800000 | K26: =11000000*12+4400000*12 -> 184800000 | L26: =11000000*12+4400000*12 -> 184800000 | M26: =11000000*12+4400000*12 -> 184800000 | N26: =11000000*12+4400000*12 -> 184800000 | O26: =11000000*12+4400000*12 -> 184800000 | ... AQ26: =11000000*12+4400000*12 -> 184800000
A27: Social insurance | C27: =C25*$C$66 -> 20475000 | D27: =D25*$C$66 -> 20984827 | E27: =E25*$C$66 -> 21572403 | F27: =F25*$C$66 -> 27300000 | G27: =G25*$C$66 -> 28091700 | H27: =H25*$C$66 -> 28906359 | I27: =I25*$C$66 -> 34125000 | J27: =J25*$C$66 -> 35108141 | ... AQ27: =AQ25*$C$66 -> 2.0986099e+08
A28: Assessable income | C28: =C25-SUM(C26:C27) -> 42525000 | D28: =D25-SUM(D26:D27) -> 46870672 | E28: =E25-SUM(E26:E27) -> 51879051 | F28: =F25-SUM(F26:F27) -> 100700000 | G28: =G25-SUM(G26:G27) -> 1.074483e+08 | H28: =H25-SUM(H26:H27) -> 61592301 | I28: =I25-SUM(I26:I27) -> 106075000 | J28: =J25-SUM(J26:J27) -> 1.1445511e+08 | ... AQ28: =AQ25-SUM(AQ26:AQ27) -> 1.6040151e+09
A29: Income tax | C29: =IF(C28<=60000000,C28*0.5,IF(C28<=120000000,60000000*0.5+(C28-60000000)*0.1,IF(C28<=216000000,60000000*0.5+60000000*0.1+(C28-120000000)*0.15,IF(C28<=384000000,60000000*0.5+60000000*0.1+96000000*0.15+(C28-216000000)*0.2,IF(C28<=624000000,60000000*0.5+60000000*0.1+96000000*0.15+168000000*0.2+(C28-384000000)*0.25,IF(C28<=960000000,60000000*0.5+60000000*0.1+96000000*0.15+168000000*0.2+240000000*0.25+(C28-624000000)*0.3,60000000*0.5+60000000*0.1+96000000*0.15+168000000*0.2+240000000*0.25+336000000*0.3+(C28-960000000)*0.35)))))) -> 21262500 | D29: =IF(D28<=60000000,D28*0.5,IF(D28<=120000000,60000000*0.5+(D28-60000000)*0.1,IF(D28<=216000000,60000000*0.5+60000000*0.1+(D28-120000000)*0.15,IF(D28<=384000000,60000000*0.5+60000000*0.1+96000000*0.15+(D28-216000000)*0.2,IF(D28<=624000000,60000000*0.5+60000000*0.1+96000000*0.15+168000000*0.2+(D28-384000000)*0.25,IF(D28<=960000000,60000000*0.5+60000000*0.1+96000000*0.15+168000000*0.2+240000000*0.25+(D28-624000000)*0.3,60000000*0.5+60000000*0.1+96000000*0.15+168000000*0.2+240000000*0.25+336000000*0.3+(D28-960000000)*0.35)))))) -> 23435336 | E29: =IF(E28<=60000000,E28*0.5,IF(E28<=120000000,60000000*0.5+(E28-60000000)*0.1,IF(E28<=216000000,60000000*0.5+60000000*0.1+(E28-120000000)*0.15,IF(E28<=384000000,60000000*0.5+60000000*0.1+96000000*0.15+(E28-216000000)*0.2,IF(E28<=624000000,60000000*0.5+60000000*0.1+96000000*0.15+168000000*0.2+(E28-384000000)*0.25,IF(E28<=960000000,60000000*0.5+60000000*0.1+96000000*0.15+168000000*0.2+240000000*0.25+(E28-624000000)*0.3,60000000*0.5+60000000*0.1+96000000*0.15+168000000*0.2+240000000*0.25+336000000*0.3+(E28-960000000)*0.35)))))) -> 25939526 | F29: =IF(F28<=60000000,F28*0.5,IF(F28<=120000000,60000000*0.5+(F28-60000000)*0.1,IF(F28<=216000000,60000000*0.5+60000000*0.1+(F28-120000000)*0.15,IF(F28<=384000000,60000000*0.5+60000000*0.1+96000000*0.15+(F28-216000000)*0.2,IF(F28<=624000000,60000000*0.5+60000000*0.1+96000000*0.15+168000000*0.2+(F28-384000000)*0.25,IF(F28<=960000000,60000000*0.5+60000000*0.1+96000000*0.15+168000000*0.2+240000000*0.25+(F28-624000000)*0.3,60000000*0.5+60000000*0.1+96000000*0.15+168000000*0.2+240000000*0.25+336000000*0.3+(F28-960000000)*0.35)))))) -> 34070000 | G29: =IF(G28<=60000000,G28*0.5,IF(G28<=120000000,60000000*0.5+(G28-60000000)*0.1,IF(G28<=216000000,60000000*0.5+60000000*0.1+(G28-120000000)*0.15,IF(G28<=384000000,60000000*0.5+60000000*0.1+96000000*0.15+(G28-216000000)*0.2,IF(G28<=624000000,60000000*0.5+60000000*0.1+96000000*0.15+168000000*0.2+(G28-384000000)*0.25,IF(G28<=960000000,60000000*0.5+60000000*0.1+96000000*0.15+168000000*0.2+240000000*0.25+(G28-624000000)*0.3,60000000*0.5+60000000*0.1+96000000*0.15+168000000*0.2+240000000*0.25+336000000*0.3+(G28-960000000)*0.35)))))) -> 34744830 | H29: =IF(H28<=60000000,H28*0.5,IF(H28<=120000000,60000000*0.5+(H28-60000000)*0.1,IF(H28<=216000000,60000000*0.5+60000000*0.1+(H28-120000000)*0.15,IF(H28<=384000000,60000000*0.5+60000000*0.1+96000000*0.15+(H28-216000000)*0.2,IF(H28<=624000000,60000000*0.5+60000000*0.1+96000000*0.15+168000000*0.2+(H28-384000000)*0.25,IF(H28<=960000000,60000000*0.5+60000000*0.1+96000000*0.15+168000000*0.2+240000000*0.25+(H28-624000000)*0.3,60000000*0.5+60000000*0.1+96000000*0.15+168000000*0.2+240000000*0.25+336000000*0.3+(H28-960000000)*0.35)))))) -> 30159230 | I29: =IF(I28<=60000000,I28*0.5,IF(I28<=120000000,60000000*0.5+(I28-60000000)*0.1,IF(I28<=216000000,60000000*0.5+60000000*0.1+(I28-120000000)*0.15,IF(I28<=384000000,60000000*0.5+60000000*0.1+96000000*0.15+(I28-216000000)*0.2,IF(I28<=624000000,60000000*0.5+60000000*0.1+96000000*0.15+168000000*0.2+(I28-384000000)*0.25,IF(I28<=960000000,60000000*0.5+60000000*0.1+96000000*0.15+168000000*0.2+240000000*0.25+(I28-624000000)*0.3,60000000*0.5+60000000*0.1+96000000*0.15+168000000*0.2+240000000*0.25+336000000*0.3+(I28-960000000)*0.35)))))) -> 34607500 | J29: =IF(J28<=60000000,J28*0.5,IF(J28<=120000000,60000000*0.5+(J28-60000000)*0.1,IF(J28<=216000000,60000000*0.5+60000000*0.1+(J28-120000000)*0.15,IF(J28<=384000000,60000000*0.5+60000000*0.1+96000000*0.15+(J28-216000000)*0.2,IF(J28<=624000000,60000000*0.5+60000000*0.1+96000000*0.15+168000000*0.2+(J28-384000000)*0.25,IF(J28<=960000000,60000000*0.5+60000000*0.1+96000000*0.15+168000000*0.2+240000000*0.25+(J28-624000000)*0.3,60000000*0.5+60000000*0.1+96000000*0.15+168000000*0.2+240000000*0.25+336000000*0.3+(J28-960000000)*0.35)))))) -> 35445511 | ... AQ29: =IF(AQ28<=60000000,AQ28*0.5,IF(AQ28<=120000000,60000000*0.5+(AQ28-60000000)*0.1,IF(AQ28<=216000000,60000000*0.5+60000000*0.1+(AQ28-120000000)*0.15,IF(AQ28<=384000000,60000000*0.5+60000000*0.1+96000000*0.15+(AQ28-216000000)*0.2,IF(AQ28<=624000000,60000000*0.5+60000000*0.1+96000000*0.15+168000000*0.2+(AQ28-384000000)*0.25,IF(AQ28<=960000000,60000000*0.5+60000000*0.1+96000000*0.15+168000000*0.2+240000000*0.25+(AQ28-624000000)*0.3,60000000*0.5+60000000*0.1+96000000*0.15+168000000*0.2+240000000*0.25+336000000*0.3+(AQ28-960000000)*0.35)))))) -> 4.7020527e+08
A30: After tax income | C30: =C25-C29 -> 173737500 | D30: =D25-D29 -> 1.7642016e+08 | E30: =E25-E29 -> 1.7951193e+08 | F30: =F25-F29 -> 225930000 | G30: =G25-G29 -> 2.3279517e+08 | H30: =H25-H29 -> 2.4513943e+08 | I30: =I25-I29 -> 290392500 | J30: =J25-J29 -> 2.9891774e+08 | ... AQ30: =AQ25-AQ29 -> 1.5284708e+09
A31: Present value of future income | C31: =C30 -> 173737500 | D31: =D30/(1+$C$65)^D2 -> 1.5416712e+08 | E31: =E30/(1+$C$65)^E2 -> 1.4664208e+08 | F31: =F30/(1+$C$65)^F2 -> 1.7252855e+08 | G31: =G30/(1+$C$65)^G2 -> 1.6618154e+08 | H31: =H30/(1+$C$65)^H2 -> 1.6358511e+08 | I31: =I30/(1+$C$65)^I2 -> 1.8114975e+08 | J31: =J30/(1+$C$65)^J2 -> 1.7431141e+08 | K31: =K30/(1+$C$65)^K2 -> 2.1985698e+08 | ... AQ31: =AQ30/(1+$C$65)^AQ2 -> 96349506
A32: Age of Huyen's husband | C32: 22 | D32: =C32+1 -> 23 | E32: =D32+1 -> 24 | F32: =E32+1 -> 25 | G32: =F32+1 -> 26 | H32: =G32+1 -> 27 | I32: =H32+1 -> 28 | J32: =I32+1 -> 29 | K32: =J32+1 -> 30 | ... AQ32: =AP32+1 -> 62
A33: Probability of surviving | C33: =1-0.00148833 -> 0.99851167 | D33: =1-0.00148833 -> 0.99851167 | E33: =1-0.00148833 -> 0.99851167 | F33: =1-0.001467648 -> 0.99853235 | G33: =1-0.001467648 -> 0.99853235 | H33: =1-0.001467648 -> 0.99853235 | I33: =1-0.001467648 -> 0.99853235 | J33: =1-0.001467648 -> 0.99853235 | K33: =1-0.001691763 -> 0.99830824 | L33: =1-0.001691763 -> 0.99830824 | M33: =1-0.001691763 -> 0.99830824 | N33: =1-0.001691763 -> 0.99830824 | O33: =1-0.001691763 -> 0.99830824 | P33: =1-0.002338274 -> 0.99766173 | Q33: =1-0.002338274 -> 0.99766173 | R33: =1-0.002338274 -> 0.99766173 | S33: =1-0.002338274 -> 0.99766173 | T33: =1-0.002338274 -> 0.99766173 | U33: =1-0.003645446 -> 0.99635455 | V33: =1-0.003645446 -> 0.99635455 | W33: =1-0.003645446 -> 0.99635455 | X33: =1-0.003645446 -> 0.99635455 | Y33: =1-0.003645446 -> 0.99635455 | Z33: =1-0.005916506 -> 0.99408349 | AA33: =1-0.005916506 -> 0.99408349 | AB33: =1-0.005916506 -> 0.99408349 | AC33: =1-0.005916506 -> 0.99408349 | AD33: =1-0.005916506 -> 0.99408349 | AE33: =1-0.00947506 -> 0.99052494 | AF33: =1-0.00947506 -> 0.99052494 | AG33: =1-0.00947506 -> 0.99052494 | AH33: =1-0.00947506 -> 0.99052494 | AI33: =1-0.00947506 -> 0.99052494 | AJ33: =1-0.014665436 -> 0.98533456 | AK33: =1-0.014665436 -> 0.98533456 | AL33: =1-0.014665436 -> 0.98533456 | AM33: =1-0.014665436 -> 0.98533456 | AN33: =1-0.014665436 -> 0.98533456 | AO33: =1-0.022502985 -> 0.97749701 | AP33: =1-0.022502985 -> 0.97749701 | AQ33: =1-0.022502985 -> 0.97749701
A34: Human capital | C34: =SUMPRODUCT(C33:AQ33,C31:AQ31) -> 6.9863372e+09
A36: Total human capital | C36: =C34+C21 -> 1.3084447e+10
A39: PENSION VALUE
A40: Pension value - Huyen
A41: Age of Huyen | AP41: 61 | AQ41: =AP41+1 -> 62 | AR41: =AQ41+1 -> 63 | AS41: =AR41+1 -> 64 | AT41: =AS41+1 -> 65 | AU41: =AT41+1 -> 66 | AV41: =AU41+1 -> 67 | AW41: =AV41+1 -> 68 | AX41: =AW41+1 -> 69 | ... BN41: =BM41+1 -> 85
A42: Probability of surviving | AP42: =1-0.008891343 -> 0.99110866 | AQ42: =1-0.008891343 -> 0.99110866 | AR42: =1-0.008891343 -> 0.99110866 | AS42: =1-0.008891343 -> 0.99110866 | AT42: =1-0.014746672 -> 0.98525333 | AU42: =1-0.014746672 -> 0.98525333 | AV42: =1-0.014746672 -> 0.98525333 | AW42: =1-0.014746672 -> 0.98525333 | AX42: =1-0.014746672 -> 0.98525333 | AY42: =1-0.025760369 -> 0.97423963 | AZ42: =1-0.025760369 -> 0.97423963 | BA42: =1-0.025760369 -> 0.97423963 | BB42: =1-0.025760369 -> 0.97423963 | BC42: =1-0.025760369 -> 0.97423963 | BD42: =1-0.044856567 -> 0.95514343 | BE42: =1-0.044856567 -> 0.95514343 | BF42: =1-0.044856567 -> 0.95514343 | BG42: =1-0.044856567 -> 0.95514343 | BH42: =1-0.044856567 -> 0.95514343 | BI42: =1-0.080907942 -> 0.91909206 | BJ42: =1-0.080907942 -> 0.91909206 | BK42: =1-0.080907942 -> 0.91909206 | BL42: =1-0.080907942 -> 0.91909206 | BM42: =1-0.080907942 -> 0.91909206 | BN42: =1-0.169725066 -> 0.83027493
A43: Pension | AP43: =$C$69 -> 5.4576416e+08 | AQ43: =$C$69 -> 5.4576416e+08 | AR43: =$C$69 -> 5.4576416e+08 | AS43: =$C$69 -> 5.4576416e+08 | AT43: =$C$69 -> 5.4576416e+08 | AU43: =$C$69 -> 5.4576416e+08 | AV43: =$C$69 -> 5.4576416e+08 | AW43: =$C$69 -> 5.4576416e+08 | ... BN43: =$C$69 -> 5.4576416e+08
A44: Present value of pension | AP44: =AP43/(1+$C$72)^AP2 -> 1.3923727e+08 | AQ44: =AQ43/(1+$C$72)^AQ2 -> 1.3456256e+08 | AR44: =AR43/(1+$C$72)^AR2 -> 1.3004481e+08 | AS44: =AS43/(1+$C$72)^AS2 -> 1.2567873e+08 | AT44: =AT43/(1+$C$72)^AT2 -> 1.2145923e+08 | AU44: =AU43/(1+$C$72)^AU2 -> 1.173814e+08 | AV44: =AV43/(1+$C$72)^AV2 -> 1.1344048e+08 | AW44: =AW43/(1+$C$72)^AW2 -> 1.0963187e+08 | ... BN44: =BN43/(1+$C$72)^BN2 -> 61348759
A45: Pension value | AP45: =SUMPRODUCT(AP44:BN44,AP42:BN42) -> 2.2998207e+09
A48: Pension value - Huyen's husband
A49: Age of Huyen's husband | AR49: 63 | AS49: =AR49+1 -> 64 | AT49: =AS49+1 -> 65 | AU49: =AT49+1 -> 66 | AV49: =AU49+1 -> 67 | AW49: =AV49+1 -> 68 | AX49: =AW49+1 -> 69 | AY49: =AX49+1 -> 70 | AZ49: =AY49+1 -> 71 | ... BN49: =BM49+1 -> 85
A50: Probability of surviving | AR50: =1-0.022502985 -> 0.97749701 | AS50: =1-0.022502985 -> 0.97749701 | AT50: =1-0.034346082 -> 0.96565392 | AU50: =1-0.034346082 -> 0.96565392 | AV50: =1-0.034346082 -> 0.96565392 | AW50: =1-0.034346082 -> 0.96565392 | AX50: =1-0.034346082 -> 0.96565392 | AY50: =1-0.053464327 -> 0.94653567 | AZ50: =1-0.053464327 -> 0.94653567 | BA50: =1-0.053464327 -> 0.94653567 | BB50: =1-0.053464327 -> 0.94653567 | BC50: =1-0.053464327 -> 0.94653567 | BD50: =1-0.081470516 -> 0.91852948 | BE50: =1-0.081470516 -> 0.91852948 | BF50: =1-0.081470516 -> 0.91852948 | BG50: =1-0.081470516 -> 0.91852948 | BH50: =1-0.081470516 -> 0.91852948 | BI50: =1-0.125631472 -> 0.87436853 | BJ50: =1-0.125631472 -> 0.87436853 | BK50: =1-0.125631472 -> 0.87436853 | BL50: =1-0.125631472 -> 0.87436853 | BM50: =1-0.125631472 -> 0.87436853 | BN50: =1-0.216329625 -> 0.78367038
A51: Pension | AR51: =$C$71 -> 6.2185949e+08 | AS51: =$C$71 -> 6.2185949e+08 | AT51: =$C$71 -> 6.2185949e+08 | AU51: =$C$71 -> 6.2185949e+08 | AV51: =$C$71 -> 6.2185949e+08 | AW51: =$C$71 -> 6.2185949e+08 | AX51: =$C$71 -> 6.2185949e+08 | AY51: =$C$71 -> 6.2185949e+08 | ... BN51: =$C$71 -> 6.2185949e+08
A52: Present value of pension | AR52: =AR51/((1+$C$72)^AR2) -> 1.4817682e+08 | AS52: =AS51/((1+$C$72)^AS2) -> 1.4320198e+08 | AT52: =AT51/((1+$C$72)^AT2) -> 1.3839417e+08 | AU52: =AU51/((1+$C$72)^AU2) -> 1.3374777e+08 | AV52: =AV51/((1+$C$72)^AV2) -> 1.2925737e+08 | AW52: =AW51/((1+$C$72)^AW2) -> 1.2491773e+08 | AX52: =AX51/((1+$C$72)^AX2) -> 1.2072378e+08 | AY52: =AY51/((1+$C$72)^AY2) -> 1.1667065e+08 | ... BN52: =BN51/((1+$C$72)^BN2) -> 69902553
A53: Pension value | AP53: =SUMPRODUCT(AR50:BN50,AR52:BN52) -> 2.2420883e+09
A56: CONSUMPTION NEED
A57: Annual living expense | C57: ='8. Budget Estimate'!C39 -> 374388000 | D57: ='8. Budget Estimate'!D39 -> 3.8699377e+08 | E57: ='8. Budget Estimate'!E39 -> 4.015219e+08 | F57: ='8. Budget Estimate'!F39 -> 4.4139856e+08 | G57: ='8. Budget Estimate'!G39 -> 4.535689e+08 | H57: ='8. Budget Estimate'!H39 -> 5.2017705e+08 | I57: ='8. Budget Estimate'!I39 -> 5.7361002e+08 | J57: ='8. Budget Estimate'!J39 -> 5.8948837e+08 | ... AQ57: ='8. Budget Estimate'!AQ39 -> 1.317001e+09 | AR57: ='16. Retirement '!B31 -> 7.0730746e+08 | AS57: ='16. Retirement '!C31 -> 7.9973379e+08 | AT57: ='16. Retirement '!D31 -> 9.1048159e+08 | AU57: ='16. Retirement '!E31 -> 8.7403704e+08 | AV57: ='16. Retirement '!F31 -> 1.0057172e+09 | AW57: ='16. Retirement '!G31 -> 1.366293e+09 | AX57: ='16. Retirement '!H31 -> 1.4433799e+09 | AY57: ='16. Retirement '!I31 -> 1.5627124e+09 | ... BN57: ='16. Retirement '!X31 -> 1.3176235e+09
A58: Present value | C58: =C57/(1+C3)^C2 -> 3.6366003e+08 | D58: =D57/(1+D3)^D2 -> 3.6841813e+08 | E58: =E57/(1+E3)^E2 -> 3.6959824e+08 | F58: =F57/(1+F3)^F2 -> 3.9370363e+08 | G58: =G57/(1+G3)^G2 -> 3.9315734e+08 | H58: =H57/(1+H3)^H2 -> 4.3818644e+08 | I58: =I57/(1+I3)^I2 -> 4.7018686e+08 | J58: =J57/(1+J3)^J2 -> 4.6967109e+08 | ... BN58: =BN57/(1+BN3)^BN2 -> 2.1396366e+08
A59: Life time consumption need | C59: =SUM(C58:BN58) -> 3.0672922e+10
B62: Assumptions
B63: Human capital
B64: Discount Rate For Huyen's Income | C64: ='3. Financial drivers '!L24 -> 0.06974
B65: Discount Rate For Huyen's husband Income | C65: ='3. Financial drivers '!L25 -> 0.06974
B66: Social insurance | C66: 0.105
B67: Pension value
B68: Huyen's average income before retirement | C68: =AVERAGE(C17:AO17) -> 7.2768554e+08
B69: Huyen's pension | C69: =C68*75% -> 5.4576416e+08
B70: Huyen's husband average 10-year income before retirement | C70: =AVERAGE(C30:AQ30) -> 8.2914598e+08
B71: Huyen's husband pension | C71: =C70*75% -> 6.2185949e+08
B72: Risk free rate | C72: 0.03474

Sheet 8. Budget Estimate
A1: Time Line | B1: 2024 | C1: 2025 | D1: =C1+1 -> 2026 | E1: =D1+1 -> 2027 | F1: =E1+1 -> 2028 | G1: =F1+1 -> 2029 | H1: =G1+1 -> 2030 | I1: =H1+1 -> 2031 | J1: =I1+1 -> 2032 | K1: =J1+1 -> 2033 | ... BN1: =BM1+1 -> 2088
A2: Period | B2: 0 | C2: 1 | D2: 2 | E2: =D2+1 -> 3 | F2: =E2+1 -> 4 | G2: =F2+1 -> 5 | H2: =G2+1 -> 6 | I2: =H2+1 -> 7 | J2: =I2+1 -> 8 | K2: =J2+1 -> 9 | L2: =K2+1 -> 10 | ... BN2: =BM2+1 -> 64
A3: Inflation rate | C3: ='3. Financial drivers '!G26 -> 0.0295 | D3: ='3. Financial drivers '!G27 -> 0.0249 | E3: ='3. Financial drivers '!G28 -> 0.028 | F3: ='3. Financial drivers '!G29 -> 0.029 | G3: ='3. Financial drivers '!G30 -> 0.029 | H3: ='3. Financial drivers '!G31 -> 0.029 | I3: ='3. Financial drivers '!$G$32 -> 0.02881 | J3: ='3. Financial drivers '!$G$32 -> 0.02881 | K3: ='3. Financial drivers '!$G$32 -> 0.02881 | L3: ='3. Financial drivers '!$G$32 -> 0.02881 | M3: ='3. Financial drivers '!$G$32 -> 0.02881 | N3: ='3. Financial drivers '!$G$32 -> 0.02881 | O3: ='3. Financial drivers '!$G$32 -> 0.02881 | P3: ='3. Financial drivers '!$G$32 -> 0.02881 | ... BN3: ='3. Financial drivers '!$G$32 -> 0.02881
A4: Huyen | C4: Bank Teller | F4: Controller | H4: Deputy Head of Customer Service | L4: Head of Customer Service | O4: Deputy Director of Operations | R4: Branch manager | AO4: Huyen retires | BN4: Pass away
A5: Huyen's husband | C5: Recruitment Assistant | F5: Recruitment Specialist | I5: Recruitment Team Leader | K5: Recruitment Manager | P5: Recruitment Director | AQ5: Huyen's husband retires
A6: Young Children | H6: Give birth and Huyen's 6 months maternity leave | Z6: Start university | AD6: Become independent
A7: Our family | M7: Buy house and pay off mortgage | Z7: Buy car
A10: INCOME
A11: Huyen's pre tax income | C11: ='7. Human capital & pension valu'!C12 -> 179400000 | D11: ='7. Human capital & pension valu'!D12 -> 183867060 | E11: ='7. Human capital & pension valu'!E12 -> 1.8901534e+08 | F11: ='7. Human capital & pension valu'!F12 -> 228800000 | G11: ='7. Human capital & pension valu'!G12 -> 2.354352e+08 | H11: ='7. Human capital & pension valu'!H12 -> 130000000 | I11: ='7. Human capital & pension valu'!I12 -> 267490600 | J11: ='7. Human capital & pension valu'!J12 -> 2.75197e+08 | ... AO11: ='7. Human capital & pension valu'!AO12 -> 1.7488415e+09 | AP11: ='7. Human capital & pension valu'!AP43 -> 5.4576416e+08 | AQ11: ='7. Human capital & pension valu'!AQ43 -> 5.4576416e+08
A12: Huyen's husband pre tax income | C12: ='7. Human capital & pension valu'!C25 -> 195000000 | D12: ='7. Human capital & pension valu'!D25 -> 1.998555e+08 | E12: ='7. Human capital & pension valu'!E25 -> 2.0545145e+08 | F12: ='7. Human capital & pension valu'!F25 -> 260000000 | G12: ='7. Human capital & pension valu'!G25 -> 2.6754e+08 | H12: ='7. Human capital & pension valu'!H25 -> 2.7529866e+08 | I12: ='7. Human capital & pension valu'!I25 -> 325000000 | J12: ='7. Human capital & pension valu'!J25 -> 334363250 | ... AQ12: ='7. Human capital & pension valu'!AQ25 -> 1.9986761e+09
A13: Interest | C13: {=TRANSPOSE('21. Monte Carlo Simulation '!Q3:Q43)} -> 3920000 | D13: 0 | E13: 0 | F13: 0 | G13: 1837179.1 | H13: 1792212.6 | I13: 5297777.5 | J13: 3557837.3 | K13: 6972159.3 | L13: 11439652 | M13: 40624670 | N13: 26024235 | O13: 22992530 | P13: 22871510 | Q13: 22164605 | R13: 33202379 | S13: 25321541 | T13: -6585607.2 | U13: 98398762 | V13: 1.7412314e+08 | W13: 1.9690751e+08 | X13: 2.9067312e+08 | Y13: 4.277708e+08 | Z13: 4.9884844e+08 | AA13: 75244092 | AB13: 1.6795618e+08 | AC13: 5.843437e+08 | AD13: 6.2257326e+08 | AE13: 6.2301053e+08 | AF13: 6.4894396e+08 | AG13: 1.0352482e+09 | AH13: 9.2352626e+08 | AI13: 1.0896735e+09 | AJ13: 1.4534354e+09 | AK13: 1.5288757e+09 | AL13: 1.4993755e+09 | AM13: 1.4560202e+09 | AN13: 2.5421175e+09 | AO13: 2.6341084e+09 | AP13: 2.030789e+09 | AQ13: 2.0863531e+09
A14: Total income | C14: =SUM(C11:C13) -> 378320000 | D14: =SUM(D11:D13) -> 383722560 | E14: =SUM(E11:E13) -> 3.9446679e+08 | F14: =SUM(F11:F13) -> 488800000 | G14: =SUM(G11:G13) -> 5.0481238e+08 | H14: =SUM(H11:H13) -> 4.0709087e+08 | I14: =SUM(I11:I13) -> 5.9778838e+08 | J14: =SUM(J11:J13) -> 6.1311809e+08 | ... AQ14: =SUM(AQ11:AQ13) -> 4.6307933e+09
A16: EXPENSE
A17: Rent | C17: =8000000*12 -> 96000000 | D17: =C17*(1+$D$3) -> 98390400 | E17: =D17*(1+$E$3) -> 1.0114533e+08 | F17: =E17*(1+$F$3) -> 1.0407855e+08 | G17: =F17*(1+$G$3) -> 1.0709682e+08 | H17: =G17*(1+$H$3) -> 1.1020263e+08 | I17: =H17*(1+$I$3) -> 1.1337757e+08 | J17: =I17*(1+$I$3) -> 1.1664398e+08 | K17: =J17*(1+$I$3) -> 1.2000449e+08 | L17: =K17*(1+$I$3) -> 1.2346182e+08
A18: Food | C18: =6000000*12 -> 72000000 | D18: =C18*(1+$D$3) -> 73792800 | E18: =D18*(1+$E$3) -> 75858998 | F18: =E18*(1+$F$3) -> 78058909 | G18: =F18*(1+$G$3) -> 80322618 | H18: =G18*(1+$H$3) -> 82651974 | I18: =H18*(1+$I$3) -> 85033177 | J18: =I18*(1+$I$3) -> 87482983 | K18: =J18*(1+$I$3) -> 90003368 | L18: =K18*(1+$I$3) -> 92596365 | M18: =L18*(1+$I$3) -> 95264066 | N18: =M18*(1+$I$3) -> 98008624 | O18: =N18*(1+$I$3) -> 1.0083225e+08 | P18: =O18*(1+$I$3) -> 1.0373723e+08 | ... AQ18: =AP18*(1+$I$3) -> 2.2334921e+08
A19: Necessities | C19: =2000000*12 -> 24000000 | D19: =C19*(1+$D$3) -> 24597600 | E19: =D19*(1+$E$3) -> 25286333 | F19: =E19*(1+$F$3) -> 26019636 | G19: =F19*(1+$G$3) -> 26774206 | H19: =G19*(1+$H$3) -> 27550658 | I19: =H19*(1+$I$3) -> 28344392 | J19: =I19*(1+$I$3) -> 29160994 | K19: =J19*(1+$I$3) -> 30001123 | L19: =K19*(1+$I$3) -> 30865455 | M19: =L19*(1+$I$3) -> 31754689 | N19: =M19*(1+$I$3) -> 32669541 | O19: =N19*(1+$I$3) -> 33610751 | P19: =O19*(1+$I$3) -> 34579076 | ... AQ19: =AP19*(1+$I$3) -> 74449737
A20: Electric and water | C20: =1500000*12 -> 18000000 | D20: =C20*(1+$D$3) -> 18448200 | E20: =D20*(1+$E$3) -> 18964750 | F20: =E20*(1+$F$3) -> 19514727 | G20: =F20*(1+$G$3) -> 20080654 | H20: =G20*(1+$H$3) -> 20662993 | I20: =H20*(1+$I$3) -> 21258294 | J20: =I20*(1+$I$3) -> 21870746 | K20: =J20*(1+$I$3) -> 22500842 | L20: =K20*(1+$I$3) -> 23149091 | M20: =L20*(1+$I$3) -> 23816016 | N20: =M20*(1+$I$3) -> 24502156 | O20: =N20*(1+$I$3) -> 25208063 | P20: =O20*(1+$I$3) -> 25934307 | ... AQ20: =AP20*(1+$I$3) -> 55837303
A21: Phone and internet | C21: =150000*12 -> 1800000 | D21: =C21*(1+$D$3) -> 1844820 | E21: =D21*(1+$E$3) -> 1896475 | F21: =E21*(1+$F$3) -> 1951472.7 | G21: =F21*(1+$G$3) -> 2008065.4 | H21: =G21*(1+$H$3) -> 2066299.3 | I21: =H21*(1+$I$3) -> 2125829.4 | J21: =I21*(1+$I$3) -> 2187074.6 | K21: =J21*(1+$I$3) -> 2250084.2 | L21: =K21*(1+$I$3) -> 2314909.1 | M21: =L21*(1+$I$3) -> 2381601.6 | N21: =M21*(1+$I$3) -> 2450215.6 | O21: =N21*(1+$I$3) -> 2520806.3 | P21: =O21*(1+$I$3) -> 2593430.7 | ... AQ21: =AP21*(1+$I$3) -> 5583730.3
A22: Fuel and gas | C22: =350000*12 -> 4200000 | D22: =C22*(1+$D$3) -> 4304580 | E22: =D22*(1+$E$3) -> 4425108.2 | F22: =E22*(1+$F$3) -> 4553436.4 | G22: =F22*(1+$G$3) -> 4685486 | H22: =G22*(1+$H$3) -> 4821365.1 | I22: =H22*(1+$I$3) -> 4960268.7 | J22: =I22*(1+$I$3) -> 5103174 | K22: =J22*(1+$I$3) -> 5250196.4 | L22: =K22*(1+$I$3) -> 5401454.6 | M22: =L22*(1+$I$3) -> 5557070.5 | N22: =M22*(1+$I$3) -> 5717169.7 | O22: =N22*(1+$I$3) -> 5881881.4 | P22: =O22*(1+$I$3) -> 6051338.4 | ... AQ22: =AP22*(1+$I$3) -> 13028704
A23: Parking | C23: =200000*12 -> 2400000 | D23: =C23*(1+$D$3) -> 2459760 | E23: =D23*(1+$E$3) -> 2528633.3 | F23: =E23*(1+$F$3) -> 2601963.6 | G23: =F23*(1+$G$3) -> 2677420.6 | H23: =G23*(1+$H$3) -> 2755065.8 | I23: =H23*(1+I3) -> 2834439.2 | J23: =I23*(1+J3) -> 2916099.4 | K23: =J23*(1+K3) -> 3000112.3 | L23: =K23*(1+L3) -> 3086545.5 | M23: =L23*(1+M3) -> 3175468.9 | N23: =M23*(1+N3) -> 3266954.1 | O23: =N23*(1+O3) -> 3361075.1 | P23: =O23*(1+P3) -> 3457907.6 | ... AQ23: =AP23*(1+AQ3) -> 7444973.7
A24: Skincare and comestic products | C24: =2500000*12 -> 30000000 | D24: =C24*(1+$D$3) -> 30747000 | E24: =D24*(1+$E$3) -> 31607916 | F24: =E24*(1+$F$3) -> 32524546 | G24: =F24*(1+$G$3) -> 33467757 | H24: =G24*(1+$H$3) -> 34438322 | I24: =H24*(1+$I$3) -> 35430490 | J24: =I24*(1+$I$3) -> 36451243 | K24: =J24*(1+$I$3) -> 37501403 | L24: =K24*(1+$I$3) -> 38581819 | M24: =L24*(1+$I$3) -> 39693361 | N24: =M24*(1+$I$3) -> 40836926 | O24: =N24*(1+$I$3) -> 42013438 | P24: =O24*(1+$I$3) -> 43223846 | ... AQ24: =AP24*(1+$I$3) -> 93062171
A25: Entertainment | C25: =850000*12 -> 10200000 | D25: =C25*(1+$D$3) -> 10453980 | E25: =D25*(1+$E$3) -> 10746691 | F25: =E25*(1+$F$3) -> 11058345 | G25: =F25*(1+$G$3) -> 11379038 | H25: =G25*(1+$H$3) -> 11709030 | I25: =H25*(1+$I$3) -> 12046367 | J25: =I25*(1+$I$3) -> 12393423 | K25: =J25*(1+$I$3) -> 12750477 | L25: =K25*(1+$I$3) -> 13117818 | M25: =L25*(1+$I$3) -> 13495743 | N25: =M25*(1+$I$3) -> 13884555 | O25: =N25*(1+$I$3) -> 14284569 | P25: =O25*(1+$I$3) -> 14696107 | ... AQ25: =AP25*(1+$I$3) -> 31641138
A26: Shopping | C26: =2000000*12 -> 24000000 | D26: =C26*(1+$D$3) -> 24597600 | E26: =D26*(1+$E$3) -> 25286333 | F26: =E26*(1+$F$3) -> 26019636 | G26: =F26*(1+$G$3) -> 26774206 | H26: =G26*(1+$H$3) -> 27550658 | I26: =H26*(1+$I$3) -> 28344392 | J26: =I26*(1+$I$3) -> 29160994 | K26: =J26*(1+$I$3) -> 30001123 | L26: =K26*(1+$I$3) -> 30865455 | M26: =L26*(1+$I$3) -> 31754689 | N26: =M26*(1+$I$3) -> 32669541 | O26: =N26*(1+$I$3) -> 33610751 | P26: =O26*(1+$I$3) -> 34579076 | ... AQ26: =AP26*(1+$I$3) -> 74449737
A27: Maternity cost | H27: 10000000
A28: Living expense for child | H28: ='9. Child living expense'!$E$3 -> 58000000 | I28: ='9. Child living expense'!$E$4*(1+I3) -> 82304800 | J28: =I28*(1+J3) -> 84676001 | K28: ='9. Child living expense'!E5*(1+K3) -> 59670980 | L28: =K28*(1+L3) -> 61390101 | M28: =L28*(1+M3) -> 63158750 | N28: ='9. Child living expense'!E6*(1+N3) -> 27777870 | O28: =N28*(1+O3) -> 28578150 | P28: =O28*(1+P3) -> 29401487 | Q28: =P28*(1+Q3) -> 30248544 | R28: =Q28*(1+R3) -> 31120004 | S28: ='9. Child living expense'!E7*(1+S3) -> 46296450 | T28: =S28*(1+T3) -> 47630251 | U28: =T28*(1+U3) -> 49002478 | V28: =U28*(1+V3) -> 50414240 | W28: ='9. Child living expense'!E8*(1+W3) -> 55555740 | X28: =W28*(1+X3) -> 57156301 | Y28: =X28*(1+Y3) -> 58802974 | Z28: ='9. Child living expense'!E9*(1+Z3) -> 128601250 | AA28: =Z28*(1+AA3) -> 1.3230625e+08 | AB28: =AA28*(1+AB3) -> 1.36118e+08 | AC28: =AB28*(1+AC3) -> 1.4003955e+08 | AD28: =AC28*(1+AD3) -> 1.4407409e+08
A29: Derivative expense such as wedding, funeral | C29: =400000*12 -> 4800000 | D29: =C29*(1+$D$3) -> 4919520 | E29: =D29*(1+$E$3) -> 5057266.6 | F29: =E29*(1+$F$3) -> 5203927.3 | G29: =F29*(1+$G$3) -> 5354841.2 | H29: =G29*(1+$H$3) -> 5510131.6 | I29: =H29*(1+$I$3) -> 5668878.5 | J29: =I29*(1+J3) -> 5832198.9 | K29: =J29*(1+K3) -> 6000224.5 | L29: =K29*(1+L3) -> 6173091 | M29: =L29*(1+M3) -> 6350937.7 | N29: =M29*(1+N3) -> 6533908.2 | O29: =N29*(1+O3) -> 6722150.1 | P29: =O29*(1+P3) -> 6915815.3 | Q29: =P29*(1+Q3) -> 7115059.9 | ... AQ29: =AP29*(1+AQ3) -> 14889947
A30: Healthcare visit | C30: =1000000*12 -> 12000000 | D30: =C30*(1+$D$3) -> 12298800 | E30: =D30*(1+$E$3) -> 12643166 | F30: =E30*(1+$F$3) -> 13009818 | G30: =F30*(1+$G$3) -> 13387103 | H30: =G30*(1+$H$3) -> 13775329 | I30: =H30*(1+$I$3) -> 14172196 | J30: =I30*(1+$I$3) -> 14580497 | K30: =J30*(1+$I$3) -> 15000561 | L30: =K30*(1+$I$3) -> 15432727 | M30: =L30*(1+$I$3) -> 15877344 | N30: =M30*(1+$I$3) -> 16334771 | O30: =N30*(1+$I$3) -> 16805375 | P30: =O30*(1+$I$3) -> 17289538 | ... AQ30: =AP30*(1+$I$3) -> 37224868
A31: Social insurance | C31: ='7. Human capital & pension valu'!C14+'7. Human capital & pension valu'!C27 -> 39312000 | D31: ='7. Human capital & pension valu'!D14+'7. Human capital & pension valu'!D27 -> 40290869 | E31: ='7. Human capital & pension valu'!E14+'7. Human capital & pension valu'!E27 -> 41419013 | F31: ='7. Human capital & pension valu'!F14+'7. Human capital & pension valu'!F27 -> 51324000 | G31: ='7. Human capital & pension valu'!G14+'7. Human capital & pension valu'!G27 -> 52812396 | H31: ='7. Human capital & pension valu'!H14+'7. Human capital & pension valu'!H27 -> 42556359 | I31: ='7. Human capital & pension valu'!I14+'7. Human capital & pension valu'!I27 -> 62211513 | J31: ='7. Human capital & pension valu'!J14+'7. Human capital & pension valu'!J27 -> 64003827 | ... AQ31: ='7. Human capital & pension valu'!AQ14+'7. Human capital & pension valu'!AQ27 -> 2.0986099e+08
A32: Tax deduction | C32: ='7. Human capital & pension valu'!C16+'7. Human capital & pension valu'!C29 -> 35544000 | D32: ='7. Human capital & pension valu'!D16+'7. Human capital & pension valu'!D29 -> 39715846 | E32: ='7. Human capital & pension valu'!E16+'7. Human capital & pension valu'!E29 -> 44523889 | F32: ='7. Human capital & pension valu'!F16+'7. Human capital & pension valu'!F29 -> 65347600 | G32: ='7. Human capital & pension valu'!G16+'7. Human capital & pension valu'!G29 -> 66616280 | H32: ='7. Human capital & pension valu'!H16+'7. Human capital & pension valu'!H29 -> 65794230 | I32: ='7. Human capital & pension valu'!I16+'7. Human capital & pension valu'!I29 -> 69347909 | J32: ='7. Human capital & pension valu'!J16+'7. Human capital & pension valu'!J29 -> 70875643 | ... AQ32: ='7. Human capital & pension valu'!AQ16+'7. Human capital & pension valu'!AQ29 -> 4.7020527e+08
A33: Motorbike insurance | C33: ='11. Motorbike insurance'!$F$7*2 -> 132000 | D33: ='11. Motorbike insurance'!$F$7*2 -> 132000 | E33: ='11. Motorbike insurance'!$F$7*2 -> 132000 | F33: ='11. Motorbike insurance'!$F$7*2 -> 132000 | G33: ='11. Motorbike insurance'!$F$7*2 -> 132000 | H33: ='11. Motorbike insurance'!$F$7*2 -> 132000 | I33: ='11. Motorbike insurance'!$F$7*2 -> 132000 | J33: ='11. Motorbike insurance'!$F$7*2 -> 132000 | ... AQ33: ='11. Motorbike insurance'!$F$7*2 -> 132000
A34: Car insurance | Z34: ='12. Car insurance '!K33 -> 11750334 | AA34: ='12. Car insurance '!K34 -> 10698371 | AB34: ='12. Car insurance '!$K$35 -> 8594444 | AC34: ='12. Car insurance '!$K$35 -> 8594444 | AD34: ='12. Car insurance '!$K$35 -> 8594444 | AE34: ='12. Car insurance '!$K$36 -> 7147994.3 | AF34: ='12. Car insurance '!$K$36 -> 7147994.3 | AG34: ='12. Car insurance '!$K$36 -> 7147994.3 | AH34: ='12. Car insurance '!$K$37 -> 5175562.8 | AI34: ='12. Car insurance '!$K$37 -> 5175562.8 | AJ34: ='12. Car insurance '!$K$37 -> 5175562.8 | AK34: ='12. Car insurance '!$K$37 -> 5175562.8 | AL34: ='12. Car insurance '!$K$38 -> 4035935.8 | AM34: ='12. Car insurance '!$K$38 -> 4035935.8 | AN34: ='12. Car insurance '!$K$38 -> 4035935.8 | AO34: ='12. Car insurance '!$K$38 -> 4035935.8 | AP34: ='12. Car insurance '!$K$38 -> 4035935.8 | AQ34: ='12. Car insurance '!$K$38 -> 4035935.8
A35: Life insurance | K35: ='14. Life insurance'!$F$5 -> 10900000 | L35: ='14. Life insurance'!$F$5 -> 10900000 | M35: =L35 -> 10900000 | N35: =M35 -> 10900000 | O35: =N35 -> 10900000 | P35: =O35 -> 10900000 | Q35: =P35 -> 10900000 | R35: =Q35 -> 10900000 | S35: =R35 -> 10900000 | T35: =S35 -> 10900000 | ... AO35: =AN35 -> 10900000
A36: Health insurance | I36: ='13. Health insurance '!$G$15+'13. Health insurance '!$G$18*2 -> 6017500 | J36: ='13. Health insurance '!$G$15+'13. Health insurance '!$G$18*2 -> 6017500 | K36: ='13. Health insurance '!$G$15+'13. Health insurance '!$G$18*2 -> 6017500 | L36: ='13. Health insurance '!$G$16+'13. Health insurance '!$G$18*2 -> 4814000 | M36: ='13. Health insurance '!$G$16+'13. Health insurance '!$G$18*2 -> 4814000 | N36: ='13. Health insurance '!$G$16+'13. Health insurance '!$G$18*2 -> 4814000 | O36: ='13. Health insurance '!$G$16+'13. Health insurance '!$G$18*2 -> 4814000 | P36: ='13. Health insurance '!$G$16+'13. Health insurance '!$G$18*2 -> 4814000 | Q36: ='13. Health insurance '!$G$16+'13. Health insurance '!$G$18*2 -> 4814000 | R36: ='13. Health insurance '!$G$16+'13. Health insurance '!$G$18*2 -> 4814000 | S36: ='13. Health insurance '!$G$17+'13. Health insurance '!$G$18*2 -> 4573300 | T36: ='13. Health insurance '!$G$17+'13. Health insurance '!$G$18*2 -> 4573300 | U36: ='13. Health insurance '!$G$17+'13. Health insurance '!$G$18*2 -> 4573300 | V36: ='13. Health insurance '!$G$17+'13. Health insurance '!$G$19*2 -> 4934350 | W36: ='13. Health insurance '!$G$17+'13. Health insurance '!$G$19*2 -> 4934350 | X36: ='13. Health insurance '!$G$17+'13. Health insurance '!$G$19*2 -> 4934350 | Y36: ='13. Health insurance '!$G$17+'13. Health insurance '!$G$19*2 -> 4934350 | Z36: ='13. Health insurance '!$G$17+'13. Health insurance '!$G$19*2 -> 4934350 | AA36: ='13. Health insurance '!$G$19*2+'13. Health insurance '!G17 -> 4934350 | AB36: ='13. Health insurance '!$G$19*2+'13. Health insurance '!G17 -> 4934350 | AC36: ='13. Health insurance '!$G$19*2+'13. Health insurance '!G17 -> 4934350 | AD36: ='13. Health insurance '!$G$19*2+'13. Health insurance '!G17 -> 4934350 | AE36: ='13. Health insurance '!$G$19*2 -> 3369800 | AF36: ='13. Health insurance '!$G$20*2 -> 3610500 | AG36: ='13. Health insurance '!$G$20*2 -> 3610500 | AH36: ='13. Health insurance '!$G$20*2 -> 3610500 | AI36: ='13. Health insurance '!$G$20*2 -> 3610500 | AJ36: ='13. Health insurance '!$G$20*2 -> 3610500 | AK36: ='13. Health insurance '!$G$20*2 -> 3610500 | AL36: ='13. Health insurance '!$G$20*2 -> 3610500 | AM36: ='13. Health insurance '!$G$20*2 -> 3610500 | ... AO36: ='13. Health insurance '!$G$20*2 -> 3610500 | AP36: ='13. Health insurance '!$G$20 -> 1805250 | AQ36: ='13. Health insurance '!$G$20 -> 1805250
A37: Mortgage payment | M37: ='10. Mortgage payment '!$M$14 -> 4.502761e+08 | N37: ='10. Mortgage payment '!$M$14 -> 4.502761e+08 | O37: ='10. Mortgage payment '!$M$14 -> 4.502761e+08 | P37: ='10. Mortgage payment '!$M$14 -> 4.502761e+08 | Q37: ='10. Mortgage payment '!$M$14 -> 4.502761e+08 | R37: ='10. Mortgage payment '!$M$14 -> 4.502761e+08 | S37: ='10. Mortgage payment '!$M$14 -> 4.502761e+08 | T37: ='10. Mortgage payment '!$M$14 -> 4.502761e+08 | ... V37: ='10. Mortgage payment '!$M$14 -> 4.502761e+08
A38: Car payment | Z38: ='3. Financial drivers '!D27*(1+D3)*(1+E3)*(1+F3)*(1+G3)*(1+H3)*(1+I3)^18 -> 8.7663619e+08
A39: Total expenses | C39: =SUM(C17:C38) -> 374388000 | D39: =SUM(D17:D38) -> 3.8699377e+08 | E39: =SUM(E17:E38) -> 4.015219e+08 | F39: =SUM(F17:F38) -> 4.4139856e+08 | G39: =SUM(G17:G38) -> 4.535689e+08 | H39: =SUM(H17:H38) -> 5.2017705e+08 | I39: =SUM(I17:I38) -> 5.7361002e+08 | J39: =SUM(J17:J38) -> 5.8948837e+08 | ... AQ39: =SUM(AQ17:AQ38) -> 1.317001e+09
A40: Surplus/Deficit | C40: =C14-C39 -> 3932000 | D40: =D14-D39 -> -3271214.4 | E40: =E14-E39 -> -7055112.4 | F40: =F14-F39 -> 47401435 | G40: =G14-G39 -> 51243484 | H40: =H14-H39 -> -1.1308617e+08 | I40: =I14-I39 -> 24178361 | J40: =J14-J39 -> 23629717 | ... AQ40: =AQ14-AQ39 -> 3.3137923e+09

Sheet 9. Child living expense
B2: Age | C2: Expense | D2: Total Amount( VND) | E2: Yearly expense | F2: Link
B3: 0-1 | C3: Diapers, milk, clothes, vaccination, medications, and incidental cost | D3: 58000000 | E3: =D3 -> 58000000
B4: 45717 | C4: Diapers, milk,,foods, education, toys, books. clothes, vaccinations, medical costs and incidental cost | D4: 160000000 | E4: =D4/2 -> 80000000
B5: 45811 | C5: Foods, clothes, educations, personal items, toys, books, medical expenses and incidental expense | D5: 174000000 | E5: =D5/3 -> 58000000
B6: 45967 | C6: Foods. education, clothes, entertainment, medical cost, and incidental expenses | D6: 135000000 | E6: =D6/5 -> 27000000
B7: 11-15 | C7: Foods. education, clothes, entertainments, medical cost and incidental expenses | D7: 180000000 | E7: =D7/4 -> 45000000
B8: 15-18 | C8: Foods, education, clothes, entertainment and Incidental cost | D8: 162000000 | E8: =D8/3 -> 54000000
B9: 18-22 | C9: Education, monthly expenses, extra classes, other expenses | D9: 500000000 | E9: =D9/4 -> 125000000
D10: Average expense | E10: =AVERAGE(E3:E9) -> 63857143
V28: =E9*(1+'8. Budget Estimate'!Z3) -> 128601250

Sheet 10. Mortgage payment 
A1: Time Line | B1: 2024 | C1: 2025 | D1: =C1+1 -> 2026 | E1: =D1+1 -> 2027 | F1: =E1+1 -> 2028 | G1: =F1+1 -> 2029 | H1: =G1+1 -> 2030 | I1: =H1+1 -> 2031 | J1: =I1+1 -> 2032 | K1: =J1+1 -> 2033 | ... BN1: =BM1+1 -> 2088
A2: Period | B2: 0 | C2: 1 | D2: 2 | E2: =D2+1 -> 3 | F2: =E2+1 -> 4 | G2: =F2+1 -> 5 | H2: =G2+1 -> 6 | I2: =H2+1 -> 7 | J2: =I2+1 -> 8 | K2: =J2+1 -> 9 | L2: =K2+1 -> 10 | ... BN2: =BM2+1 -> 64
A3: Inflation rate | C3: ='3. Financial drivers '!G26 -> 0.0295 | D3: ='3. Financial drivers '!G27 -> 0.0249 | E3: ='3. Financial drivers '!G28 -> 0.028 | F3: ='3. Financial drivers '!G29 -> 0.029 | G3: ='3. Financial drivers '!G30 -> 0.029 | H3: ='3. Financial drivers '!G31 -> 0.029 | I3: ='3. Financial drivers '!$G$32 -> 0.02881 | J3: ='3. Financial drivers '!$G$32 -> 0.02881 | K3: ='3. Financial drivers '!$G$32 -> 0.02881 | L3: ='3. Financial drivers '!$G$32 -> 0.02881 | M3: ='3. Financial drivers '!$G$32 -> 0.02881 | N3: ='3. Financial drivers '!$G$32 -> 0.02881 | O3: ='3. Financial drivers '!$G$32 -> 0.02881 | P3: ='3. Financial drivers '!$G$32 -> 0.02881 | ... BN3: ='3. Financial drivers '!$G$32 -> 0.02881
A4: Huyen | C4: Bank Teller | F4: Controller | H4: Deputy Head of Customer Service | L4: Head of Customer Service | O4: Deputy Director of Operations | R4: Brand manager | AO4: Huyen retires | BN4: Pass away
A5: Huyen's husband | C5: Recruitment Assistant | F5: Recruitment Specialist | I5: Recruitment Team Leader | K5: Recruitment Manager | P5: Recruitment Director | AQ5: Huyen's husband retires
A6: Young Children | H6: Give birth and Huyen's 6 months maternity leave
A7: Our family | M7: Buy house and pay off mortgage
A9: Housing price | C9: 2450000000 | D9: =C9*(1+D3) -> 2511005000 | E9: =D9*(1+E3) -> 2581313140 | F9: =E9*(1+F3) -> 2.6561712e+09 | G9: =F9*(1+G3) -> 2.7332002e+09 | H9: =G9*(1+H3) -> 2.812463e+09 | I9: =H9*(1+I3) -> 2.8934901e+09 | J9: =I9*(1+J3) -> 2.9768515e+09 | K9: =J9*(1+K3) -> 3.0626146e+09 | ... M9: =L9*(1+M3) -> 3.2416245e+09
A10: Payment term | M10: 10
A11: Debt payment for Mortgage
A12: Principal | M12: =M9 -> 3.2416245e+09 | N12: =IF(M17=0,0,M17) -> 3.0010565e+09 | O12: =IF(N17=0,0,N17) -> 2.7449257e+09 | P12: =IF(O17=0,0,O17) -> 2.4722252e+09 | Q12: =IF(P17=0,0,P17) -> 2.1818831e+09 | R12: =IF(Q17=0,0,Q17) -> 1.872758e+09 | S12: =IF(R17=0,0,R17) -> 1.5436349e+09 | T12: =IF(S17=0,0,S17) -> 1.1932202e+09 | U12: =IF(T17=0,0,T17) -> 8.2013623e+08 | V12: =IF(U17=0,0,U17) -> 4.2291664e+08
A13: Interest rate | M13: ='3. Financial drivers '!$H$17 -> 0.064692308 | N13: ='3. Financial drivers '!$H$17 -> 0.064692308 | O13: ='3. Financial drivers '!$H$17 -> 0.064692308 | P13: ='3. Financial drivers '!$H$17 -> 0.064692308 | Q13: ='3. Financial drivers '!$H$17 -> 0.064692308 | R13: ='3. Financial drivers '!$H$17 -> 0.064692308 | S13: ='3. Financial drivers '!$H$17 -> 0.064692308 | T13: ='3. Financial drivers '!$H$17 -> 0.064692308 | ... V13: ='3. Financial drivers '!$H$17 -> 0.064692308
A14: Payment | M14: =-PMT(M13,$M$10,M12) -> 4.502761e+08 | N14: =IF(M17=0,0,M14) -> 4.502761e+08 | O14: =IF(N17=0,0,N14) -> 4.502761e+08 | P14: =IF(O17=0,0,O14) -> 4.502761e+08 | Q14: =IF(P17=0,0,P14) -> 4.502761e+08 | R14: =IF(Q17=0,0,Q14) -> 4.502761e+08 | S14: =IF(R17=0,0,R14) -> 4.502761e+08 | T14: =IF(S17=0,0,S14) -> 4.502761e+08 | U14: =IF(T17=0,0,T14) -> 4.502761e+08 | V14: =IF(U17=0,0,U14) -> 4.502761e+08
A15: Principal payment | M15: =M14-M16 -> 2.4056793e+08 | N15: =N14-N16 -> 2.5613082e+08 | O15: =O14-O16 -> 2.7270052e+08 | P15: =P14-P16 -> 2.9034214e+08 | Q15: =Q14-Q16 -> 3.0912505e+08 | R15: =R14-R16 -> 3.2912306e+08 | S15: =S14-S16 -> 3.5041479e+08 | T15: =T14-T16 -> 3.7308393e+08 | ... V15: =V14-V16 -> 4.2291664e+08
A16: Interest payment | M16: =M12*M13 -> 2.0970817e+08 | N16: =N12*N13 -> 1.9414527e+08 | O16: =O12*O13 -> 1.7757558e+08 | P16: =P12*P13 -> 1.5993395e+08 | Q16: =Q12*Q13 -> 1.4115105e+08 | R16: =R12*R13 -> 1.2115304e+08 | S16: =S12*S13 -> 99861307 | T16: =T12*T13 -> 77192166 | ... V16: =V12*V13 -> 27359454
A17: Net principlal | M17: =M12-M15 -> 3.0010565e+09 | N17: =N12-N15 -> 2.7449257e+09 | O17: =O12-O15 -> 2.4722252e+09 | P17: =P12-P15 -> 2.1818831e+09 | Q17: =Q12-Q15 -> 1.872758e+09 | R17: =R12-R15 -> 1.5436349e+09 | S17: =S12-S15 -> 1.1932202e+09 | T17: =T12-T15 -> 8.2013623e+08 | ... V17: =V12-V15 -> 8.3446503e-07

Sheet Car payment
A1: Time Line | B1: 2024 | C1: 2025 | D1: =C1+1 -> 2026 | E1: =D1+1 -> 2027 | F1: =E1+1 -> 2028 | G1: =F1+1 -> 2029 | H1: =G1+1 -> 2030 | I1: =H1+1 -> 2031 | J1: =I1+1 -> 2032 | K1: =J1+1 -> 2033 | ... BN1: =BM1+1 -> 2088
A2: Period | B2: 0 | C2: 1 | D2: 2 | E2: =D2+1 -> 3 | F2: =E2+1 -> 4 | G2: =F2+1 -> 5 | H2: =G2+1 -> 6 | I2: =H2+1 -> 7 | J2: =I2+1 -> 8 | K2: =J2+1 -> 9 | L2: =K2+1 -> 10 | ... BN2: =BM2+1 -> 64
A3: Inflation rate | C3: ='3. Financial drivers '!G26 -> 0.0295 | D3: ='3. Financial drivers '!G27 -> 0.0249 | E3: ='3. Financial drivers '!G28 -> 0.028 | F3: ='3. Financial drivers '!G29 -> 0.029 | G3: ='3. Financial drivers '!G30 -> 0.029 | H3: ='3. Financial drivers '!G31 -> 0.029 | I3: ='3. Financial drivers '!$G$32 -> 0.02881 | J3: ='3. Financial drivers '!$G$32 -> 0.02881 | K3: ='3. Financial drivers '!$G$32 -> 0.02881 | L3: ='3. Financial drivers '!$G$32 -> 0.02881 | M3: ='3. Financial drivers '!$G$32 -> 0.02881 | N3: ='3. Financial drivers '!$G$32 -> 0.02881 | O3: ='3. Financial drivers '!$G$32 -> 0.02881 | P3: ='3. Financial drivers '!$G$32 -> 0.02881 | ... BN3: ='3. Financial drivers '!$G$32 -> 0.02881
A4: Huyen | C4: Bank Teller | F4: Controller | H4: Deputy Head of Customer Service | L4: Head of Customer Service | O4: Deputy Director of Operations | R4: Brand manager | AO4: Huyen retires | BN4: Pass away
A5: Huyen's husband | C5: Recruitment Assistant | F5: Recruitment Specialist | I5: Recruitment Team Leader | K5: Recruitment Manager | P5: Recruitment Director | T5: HR director | AQ5: Huyen's husband retires
A6: Young Children | H6: Give birth and Huyen's 6 months maternity leave | Z6: Start university | AD6: Become independent
A7: Our family | M7: Buy house and pay off mortgage | Z7: Buy car and pay off car loan
A9: Car price | C9: 458000000 | D9: =C9*(1+D3) -> 4.694042e+08 | E9: =D9*(1+E3) -> 4.8254752e+08 | F9: =E9*(1+F3) -> 4.965414e+08 | G9: =F9*(1+G3) -> 5.109411e+08 | H9: =G9*(1+H3) -> 5.2575839e+08 | I9: =H9*(1+I3) -> 5.4090549e+08 | J9: =I9*(1+J3) -> 5.5648897e+08 | K9: =J9*(1+K3) -> 5.7252142e+08 | ... Z9: =Y9*(1+Z3) -> 8.7663619e+08
B10: Car model | C10: VIOS 1.5E-MT
B11: Car price | C11: =Z9 -> 8.7663619e+08
B12: Payment term | C12: 4
B13: Debt payment for Car
B14: Principal | C14: =C11 -> 8.7663619e+08 | D14: =IF(C19=0,0,C19) -> #REF! | E14: =IF(D19=0,0,D19) -> #REF! | F14: =IF(E19=0,0,E19) -> #REF!
B15: Interest rate | C15: =#REF! -> #REF! | D15: =#REF! -> #REF! | E15: =#REF! -> #REF! | F15: =#REF! -> #REF!
B16: Payment | C16: =-PMT($C$15,$C$12,$C$14) -> #REF! | D16: =IF(C16=0,0,C16) -> #REF! | E16: =IF(D16=0,0,D16) -> #REF! | F16: =IF(E16=0,0,E16) -> #REF!
B17: Principal payment | C17: =C16-C18 -> #REF! | D17: =D16-D18 -> #REF! | E17: =E16-E18 -> #REF! | F17: =F16-F18 -> #REF!
B18: Interest payment | C18: =C15*C14 -> #REF! | D18: =D14*D15 -> #REF! | E18: =E14*E15 -> #REF! | F18: =F14*F15 -> #REF!
B19: Net principlal | C19: =C14-C17 -> #REF! | D19: =D14-D17 -> #REF! | E19: =E14-E17 -> #REF! | F19: =F14-F17 -> #REF!

Sheet 11. Motorbike insurance
B2: MOTORBIKE INSURANCE
B4: Bảo Việt | D4: Link | E4: PVI | G4: Link
B5: Coverage aspects + Damage to the body, life, and property of third parties caused by the vehicle + Bodily injury to the driver and passengers of the vehicle involved in the accident while on or getting in and out of the vehicle during traffic participation. Uncoverage aspects + Intentional acts causing damage by the motor vehicle owner, driver, or the injured party. + The driver causing an accident and intentionally fleeing without fulfilling the civil liability of the motor vehicle owner. However, if the driver intentionally flees but has fulfilled the motor vehicle owner's civil liability, it will not be considered an exclusion from insurance liability. + The driver is under or over the age limit for operating a motor vehicle as stipulated by road traffic laws; the driver does not possess a valid driver's license or uses an invalid driver's license (where the serial number on the back does not match the most recently issued serial number in the driver's license management information system), or uses a driver's license not issued by a competent authority, a forged driver's license, or a driver's license that has expired at the time of the accident, or uses a driver's license unsuitable for the type of motor vehicle for which a driver's license is mandatory. If the driver's license has been temporarily suspended or revoked, the driver will be considered as not having a driver's license. + Indirect damages, including: reduction in commercial value, damages related to the use and exploitation of the damaged property. + Damage to property caused by the driver operating the vehicle while having alcohol concentration in their blood or breath, or using narcotics and banned stimulants as regulated by law. + Damage to property that is stolen or robbed during the accident. + Damage to special property, including: gold, silver, gemstones, valuable papers (like money), antiques, rare paintings, dead bodies, and remains. + War, terrorism, earthquake. | E5: Coverage aspects + Material damage to the vehicle caused by fire, explosion, or unexpected detonation, beyond the control of the owner or driver. The vehicle will be fully compensated if the damage or loss exceeds 75% or reaches a point where it cannot be repaired or restored to ensure safe operation. + Damage to the body, life, and property of a third party caused by the vehicle. + Damage to the body of the driver and passengers in the vehicle who are injured in an accident while in the vehicle, getting on or off the vehicle, during its participation in traffic. Uncoverage aspects + Intentional damage or accidents caused by the vehicle owner, driver, or the injured party. + Using motorcycles for racing (legal or illegal), using the vehicle for robbery, or for other illegal purposes that cause accidents. + Losses under 300,000 VND. + Accidents occurring outside the territory of Vietnam. + Accidents occurring outside the territory of Vietnam. + The insured intentionally causing damage; using motorcycles for racing (legal or illegal). + The driver not possessing a valid driver's license. + Intentional damage or accidents caused by the vehicle owner, driver, or the injured party. + The driver causing an accident and intentionally fleeing without fulfilling the civil liability of the vehicle owner or driver. + The driver not possessing a valid driver's license, or the driver's license not being appropriate for the type of motor vehicle for which a driver's license is mandatory. + Indirect damages such as: reduction in commercial value, damages related to the use and exploitation of the damaged property. + Damage to property that is stolen or robbed during the accident. + War, terrorism, earthquake. + Damage to special property including gold, silver, gemstones, money, valuable papers (like money), antiques, rare paintings, dead bodies, remains, etc.
B6: Contract period | C6: 3 years | E6: Contract period | F6: 3 years
B7: Premiums (per year) | C7: 66000 | E7: Premiums (per year) | F7: 66000

Sheet 12. Car insurance 
B2: CAR INSURANCE INFORMATION
B4: PVI | C4: Link | F4: Bảo Việt | G4: Link | J4: PJICO | K4: Link
B5: Coverage Aspects with Maximum Cover Amount Up to Car's Value + Collisions, overturning, sinking, or falling objects + Fire or explosion + Natural disasters (e.g., storms, floods, earthquakes, lightning) + Theft or robbery (total loss) + Malicious acts (excluding those by the owner, insured, or driver) | F5: Coverage Aspects with A Diverse Cover Amount + Collisions, overturning, sinking, or falling objects + Fire or explosion + Natural disasters (e.g., storms, floods, earthquakes, lightning) + Theft or robbery (total loss) + Malicious acts (excluding those by the owner, insured, or driver) | J5: Coverage Aspects with A Diverse Cover Amount + Collisions, overturning, sinking, or falling objects + Fire or explosion + Natural disasters (e.g., storms, floods, earthquakes, lightning) + Theft or robbery (total loss) + Malicious acts (excluding those by the owner, insured, or driver)
B6: Exclusions: + The damage is intentional or involves fraud. + The driver has no valid or appropriate license, or is using a fake/suspended one. + The vehicle lacks valid registration or inspection, or has expired documents. + The driver is under the influence of alcohol or drugs. + The vehicle is driven against traffic rules (wrong way, ignoring signs or police). + The vehicle is used without lights at night or with illegal modifications (e.g., sirens). + It's used to transport banned or hazardous items without legal permission. + The incident occurs outside Vietnam or in restricted/military zones. + The damage is due to racing, riots, terrorism, or war. + The cause is mechanical failure, wear and tear, poor maintenance, or faulty repairs. + The engine is damaged by driving through floods or attempting to restart when submerged. + Only parts/accessories are stolen (not the whole vehicle). + The vehicle’s declared value is too low (underinsured). + The accident results from legal violations or ongoing disputes. | F6: Exclusions: + The damage is intentional or involves fraud. + The driver has no valid or appropriate license, or is using a fake/suspended one. + The vehicle lacks valid registration or inspection, or has expired documents. + The driver is under the influence of alcohol or drugs. + The vehicle is driven against traffic rules (wrong way, ignoring signs or police). + The vehicle is used without lights at night or with illegal modifications (e.g., sirens). + It's used to transport banned or hazardous items without legal permission. + The incident occurs outside Vietnam or in restricted/military zones. + The damage is due to racing, riots, terrorism, or war. + The cause is mechanical failure, wear and tear, poor maintenance, or faulty repairs. + The engine is damaged by driving through floods or attempting to restart when submerged. + Only parts/accessories are stolen (not the whole vehicle). + The vehicle’s declared value is too low (underinsured). + The accident results from legal violations or ongoing disputes. | J6: Uncoverage Aspects: + The damage is intentional or involves fraud. + The driver has no valid or appropriate license, or is using a fake/suspended one. + The vehicle lacks valid registration or inspection, or has expired documents. + The driver is under the influence of alcohol or drugs. + The vehicle is driven against traffic rules (wrong way, ignoring signs or police). + The vehicle is used without lights at night or with illegal modifications (e.g., sirens). + It's used to transport banned or hazardous items without legal permission. + The incident occurs outside Vietnam or in restricted/military zones. + The damage is due to racing, riots, terrorism, or war. + The cause is mechanical failure, wear and tear, poor maintenance, or faulty repairs. + The engine is damaged by driving through floods or attempting to restart when submerged. + Only parts/accessories are stolen (not the whole vehicle). + The vehicle’s declared value is too low (underinsured). + The accident results from legal violations or ongoing disputes.
B8: INSURANCE FEES CALCULATION FROM 3 DIFFERENT INSURANCE COMPANY
B10: PVI | D10: Link | F10: Bảo Việt | H10: Link | J10: PJICO | L10: Link
B11: Insurance Calculation For Car | F11: Insurance Calculation For Car | J11: Insurance Calculation For Car
B12: Car value | C12: ='Car payment'!$C$11 -> 8.7663619e+08 | F12: Car value | G12: ='Car payment'!$C$11 -> 8.7663619e+08 | J12: Car value | K12: ='Car payment'!$C$11 -> 8.7663619e+08
B13: Category | F13: Category | J13: Category
B14: Compulsory Motor Vehicle Owner's Civil Liability Insurance Fee | C14: 480700 | F14: Compulsory Motor Vehicle Owner's Civil Liability Insurance Fee | G14: 480700 | J14: Compulsory Motor Vehicle Owner's Civil Liability Insurance Fee | K14: 480700
B15: Physical Damage Coverage | F15: Physical Damage Coverage | J15: Physical Damage Coverage
B16: Normal Car (Under 3 years of usage) | C16: 0.015 | F16: Package: Compensation Amount > 200% Car Value | J16: Below 3 years | K16: 0.012
B17: Adjusted For Usage Years of Car | C17: Additional Fees | F17: Below 3 years | G17: 0.0181 | J17: From 03 - 06 years | K17: 0.0135
B18: From 03 - 06 years | C18: 10% higher than fees for Normal Car Under 3 years) | F18: From 03 - 06 years | G18: 0.0206 | J18: From 06 - 10 years | K18: 0.015
B19: From 06 - 10 years | C19: 20% higher than fees for Normal Car Under 3 years) | F19: From 06 - 10 years | G19: 0.0264 | J19: Above 10 years | K19: 0.016
B20: From 10 - 15 years | C20: 30% higher than fees for Normal Car Under 3 years) | F20: Above 10 years | G20: 0.0261 | J20: Fee when we have recently bought | K20: =K12*K16 -> 10519634
B21: From 15 - 20 years | C21: 40% higher than fees for Normal Car Under 3 years) | F21: Fee when we have recently bought | G21: =G12*G17 -> 15867115 | J21: Fee within 1 years after buying | K21: =K12*K16*'3. Financial drivers '!D19 -> 9467670.8
B22: Above 20 years | C22: 50% higher than fees for Normal Car Under 3 years) | F22: Fee within 1 years after buying | G22: =G12*G17*'3. Financial drivers '!D19 -> 14280404 | J22: Fee from 1 years - 3 years | K22: =K12*K16*'3. Financial drivers '!D20 -> 7363744
B23: Fee when we have recently bought | C23: =C16*C12 -> 13149543 | F23: Fee from 1 years - 3 years | G23: =G12*G17*'3. Financial drivers '!D20 -> 11106981 | J23: Fee from 3 years - 6 years | K23: =K12*K17*'3. Financial drivers '!D21 -> 5917294.3
B24: Fee within 1 years after buying | C24: =C12*C16*'3. Financial drivers '!D19 -> 11834589 | F24: Fee from 3 years - 6 years | G24: =G12*G18*'3. Financial drivers '!D21 -> 9029352.7 | J24: Fee from 6 years - 10 years | K24: =K12*K18*'3. Financial drivers '!D22 -> 3944862.8
B25: Fee from 1 years - 3 years | C25: =C12*C16*'3. Financial drivers '!D20 -> 9204680 | F25: Fee from 6 years - 10 years | G25: =G12*G19*'3. Financial drivers '!D22 -> 6942958.6 | J25: Fee above 10 years | K25: =K12*K19*'3. Financial drivers '!D23 -> 2805235.8
B26: Fee from 3 years - 6 years | C26: =C12*(C16+10%)*'3. Financial drivers '!D21 -> 50406581 | F26: Fee above 10 years | G26: =G12*G20*'3. Financial drivers '!D23 -> 4576040.9 | J26: Insurance For People Staying in Car
B27: Fee from 6 years - 10 years | C27: =C12*(C16+20%)*'3. Financial drivers '!D22 -> 56543034 | F27: Insurance Calculation For People Staying in Car | J27: Covered Amount In Case Accident/ per people | K27: Fees
B28: Fee from 10 years - 15 years | C28: =C12*(C16+30%)*'3. Financial drivers '!D23 -> 55228080 | F28: Covered Amount In Case Accident/ per people | G28: Fees | J28: Package 1: Up to VND 20 million | K28: 0.001
B29: Fee from 15 years - 20 years | C29: =C12*(C16+40%)*'3. Financial drivers '!D23 -> 72760804 | F29: Package 1: From VND 5 million to 200 million | G29: 0.001 | J29: Package 2: From VND 20 million to VND 50 million | K29: 0.0015
B30: Fee above 20 years | C30: =C12*(C16+50%)*'3. Financial drivers '!D23 -> 90293527 | F30: Package 2: From 5.000 $ to 10.000$ | G30: 0.001 | J30: Package 3: From VND 50 million to VND 100 million | K30: 0.0025
B31: Insurance Calculation For People Staying in Car | F31: Package 3: From 10.000$ to 30.000$ | G31: 0.0015 | J31: Fee with package 3 which cover VND 100 million | K31: =K30*100000000*3 -> 750000
B32: Covered Amount In Case Accident/ per people | C32: Fees | F32: Package 4: From 30.000$ to 50.000$ | G32: 0.003 | J32: Total Car insurance fees
B33: Package 1: From VND 5 million to VND 500 million | C33: 0.001 | F33: Fee with package 1 which cover VND 100 million | G33: =G29*100000000*3 -> 300000 | J33: Fee when we have recently bought | K33: =$K$14+K20+$K$31 -> 11750334
B34: Package 2: From VND 500 million to VND 1 billion | C34: 0.002 | F34: Total Car insurance fees | J34: Fee within 1 years after buying | K34: =$K$14+K21+$K$31 -> 10698371
B35: Package 3: Above VND 1 billion | C35: 0.003 | F35: Fee when we have recently bought | G35: =$G$14+G21+$G$33 -> 16647815 | J35: Fee from 1 years - 3 years | K35: =$K$14+K22+$K$31 -> 8594444
B36: Fee with package 1 which cover VND 100 million | C36: =C33*100000000*3 -> 300000 | F36: Fee within 1 years after buying | G36: =$G$14+G22+$G$33 -> 15061104 | J36: Fee from 3 years - 6 years | K36: =$K$14+K23+$K$31 -> 7147994.3
B37: Total Car insurance fees | F37: Fee from 1 years - 3 years | G37: =$G$14+G23+$G$33 -> 11887681 | J37: Fee from 6 years - 10 years | K37: =$K$14+K24+$K$31 -> 5175562.8
B38: Fee when we have recently bought | C38: =$C$14+C23+$C$36 -> 13930243 | F38: Fee from 3 years - 6 years | G38: =$G$14+G24+$G$33 -> 9810052.7 | J38: Fee above 10 years | K38: =$K$14+K25+$K$31 -> 4035935.8
B39: Fee within 1 years after buying | C39: =$C$14+C24+$C$36 -> 12615289 | F39: Fee from 6 years - 10 years | G39: =$G$14+G25+$G$33 -> 7723658.6
B40: Fee from 1 years - 3 years | C40: =$C$14+C25+$C$36 -> 9985380 | F40: Fee above 10 years | G40: =$G$14+G26+$G$33 -> 5356740.9
B41: Fee from 3 years - 6 years | C41: =$C$14+C26+$C$36 -> 51187281
B42: Fee from 6 years - 10 years | C42: =$C$14+C27+$C$36 -> 57323734
B43: Fee from 10 years - 15 years | C43: =$C$14+C28+$C$36 -> 56008780
B44: Fee from 15 years - 20 years | C44: =$C$14+C29+$C$36 -> 73541504
B45: Fee above 20 years | C45: =$C$14+C30+$C$36 -> 91074227

Sheet 13. Health insurance 
B2: HEALTH INSURANCE
B4: BẢO VIỆT AN GIA Bronze package (Inpatient and outpatient) | C4: Link | F4: PVI | G4: Link | J4: PJICO | K4: Link
B5: Coverage Aspects with Maximum Cover Amount Up to 99.800.000 VND/year/person. Main benefits: Inpatient treatment for illness and accident + Inpatient hospitalization cost. + Pre hospitalization cost. + Re examination cost. + Emergency transportation. + Surgical cost. + Rehabilitation. + Allowance funeral if death occurs at hospital. + Public hospital allowance. Supplemental benefits: + Outpatient treatment. + Accident insurance. + Life insurance. + Dental insurance. + Maternity insuarance. | F5: Coverage Aspects with Maximum Cover Amount Up to 115.000.000 VND/year/person. + Accident Insurance: Customers receive benefits for risks, death, or permanent disability due to an accident, including permanent injury to specific body parts resulting from an accident. + Inpatient Treatment: PVI covers insurance costs when the insured person requires inpatient treatment or surgery at a hospital due to illness, sickness, or accident, as well as for maternity care. + Other Benefits: These include costs incurred 30 days before hospitalization, costs incurred within 30 days of the incident, and home healthcare medical expenses for 15 days after hospital discharge. + Supplemental Health Insurance Benefits: These additional benefits cover outpatient treatment for illness, sickness, or accident, as well as dental insurance, maternity benefits, and life insurance due to illness or sickness. | J5: Coverage Aspects with Maximum Cover Amount Up to 100.000.000 VND/year/person. Main benefits: + Hospitalization Costs due to Accident, Illness/Day (maximum 60 days/year). + Surgical Costs due to Accident, Illness. + Physical Therapy, Rehabilitation due to Accident, Illness (maximum 60 days/year). + Pre-Hospitalization Treatment Costs due to Accident, Illness (within 30 days before hospitalization) + Post-Hospitalization Treatment Costs due to Accident, Illness (within 30 days after discharge) + Hospitalization Allowance due to Accident, Illness treated at a Public Hospital (Excluding Private Hospitals, International Hospitals, Service Wards/On-Demand Wards/International Wards at Public Hospitals). + Home Nursing Care due to Accident, Illness as prescribed by the Treating Doctor (within 15 days after discharge). + Emergency Ambulance Transportation Costs. + Funeral Allowance. Supplemental benefits: + Maternity. + Death and Total Permanent Disability due to accidents. + Death due to illness. + Outpatient treatment due to accidents and illness. + Dental care.
B6: Exclusions: For first year: 1. Respiratory system diseases: Adenoiditis requiring curettage, sinusitis, deviated septum, asthma. For bronchitis, bronchiolitis, and pneumonia of all types, a waiting period of 6 months is applied for children ≤ 6 years old. 2. Ear system diseases: Otitis media requiring surgery, nasopharyngeal polyps, removal of spiral bone. 3. Vascular system diseases: Phlebitis and venous thrombosis/obstruction, varicose veins of lower limbs, carpal tunnel syndrome, lymphatic vessels/nodes, hemorrhoids. 4. Metabolic disorders of all types 5. Musculoskeletal system diseases: Chronic arthritis/polyarthritis, degenerative disease of the spine, vertebral bodies, herniated discs, bone density and structure disorders, gout. 6. Digestive system diseases: Gastric and duodenal ulcers. 7. Other diseases: Stones, cysts, warts, moles of all kinds, vestibular disorders. General exclusions: 1. Nervous system: Central nervous system inflammation, atrophy affecting the nervous system, extrapyramidal movement disorders, Alzheimer's, Apalic syndrome/dementia, epilepsy, coma, cerebral palsy and other paralytic syndromes... 2. Respiratory system: Pulmonary failure, pneumothorax 3. Circulatory system: a. Heart disease. b. Hypertension/high blood pressure, idiopathic hyperdynamic vasoconstriction, c. Cerebrovascular diseases/stroke and sequelae of this disease 4. Digestive system: a. Liver diseases: hepatitis A, B, C. Liver failure/cirrhosis b. Gallbladder diseases: Gallstones | F6: Exclusions: + Individuals suffering from mental illness, leprosy, or cancer. + Individuals with a permanent disability or permanent injury of 50% or more. + Individuals currently undergoing treatment for an illness or injury. + Events occurring outside the scope clearly defined in the insurance contract. + The policyholder undergoes treatment or uses medication not in accordance with the instructions or guidance of the healthcare facility/doctor, or requests unrelated to standard treatment or surgery as regulated by the Ministry of Health. + The method of examination, treatment, or use of medication that has not undergone clinical trials or has not been proven based on widely accepted medical knowledge. + The insured person is in violation of the law and is serving a criminal sentence, intentionally committing traffic law violations according to the conclusions of the competent authority. + Consequences of the policyholder using alcohol, drugs, stimulants, etc. + Services for examination and treatment at home. | J6: Insurance Exclusions: + Intentional acts by the insured or their legal heirs. + Criminal acts or serious legal violations (e.g., illegal racing, driving without a valid license, wrong-way driving). + Accidents due to alcohol over legal limits or use of stimulants. + Fighting, unless proven as self-defense. + Medical treatment or drug use without doctor’s prescription. + Participation in aviation (except as a passenger), military training, or armed conflict. + Natural disasters: earthquakes, tsunamis, volcanic eruptions, radiation, pandemics (WHO level 6+). + War, civil unrest, terrorism, riots, strikes, rebellion, or armed uprisings. + Participation in professional sports or any type of race. + Treatment of tuberculosis, malaria, STDs (e.g., syphilis, gonorrhea), or HIV-related illnesses. + Treatment/surgery for genetic diseases, birth defects, or conditions existing before coverage start date. + Routine check-ups, fatigue treatment, medical exams, health counseling, all vaccines (except post-accident or animal/insect bites). + Vision/hearing exams or correction of degenerative or refractive issues (e.g., myopia, astigmatism). + Treatment at the request of the insured without medical necessity. + Cosmetic surgeries or treatments (e.g., acne, pigmentation, hair loss). + Treatment for metabolic or biochemical abnormalities (e.g., high cholesterol, liver enzymes). + Costs for medical aids/prosthetics, except limited coverage for trauma-related orthopedic use (10% of accident medical limit). + Supplements, dietary products, vitamins, or cosmetics not prescribed by a doctor. + Family planning, infertility treatment, artificial reproduction, gender transition, or related complications. + Weight management (gain/loss). + Treatment for mental disorders, epilepsy, sleep issues, stress, or nervous breakdown. + Treatment at unlicensed clinics or without valid invoices, unless stated otherwise in the policy. + Maternity-related costs unless maternity benefit is included. + Pre-existing and specific diseases within the first policy year.
B7: Advantages: + No time wasted collecting claim documents and no need to pay hospital fees + Fast, accurate compensation within 15 working days + Premium 24/7 hospital fee guarantee service at nearly 90 high-quality hospitals nationwide Disadvantage: + Only insured people below 65 | F7: Advantages: + The application process is simple and easy for all customers. + The insurance package does not limit the treatment and medical examination addresses nationwide. + Insurance covers hospital fees, examinations, and treatments at no cost within a network of high-quality hospitals and clinics across the country. Disadvantages: + Only insured people below 60 years old. | J7: Advantages + PJICO partners with many hospitals and clinics across Vietnam, including top-tier hospitals. + Offers relatively affordable plans that suit a broad range of customers. + Quick, streamlined, and professional procedures ensuring maximum customer benefits. + Wide insurance coverage, attractive options, and strong financial capacity for claim payments. Disadvantages +Only insured people below 65 years old.
B9: INSURANCE FEES CALCULATION FROM 3 DIFFERENT INSURANCE COMPANY
B11: BẢO VIỆT AN GIA | F11: PVI | J11: PJICO
B12: Health Insurance Calculation | F12: Health Insurance Calculation | J12: Health Insurance Calculation
B13: Category | C13: Unit: VND | F13: Category | G13: Unit: VND | J13: Category | K13: Unit: VND
B14: Adjusted For Age | F14: Adjusted For Age | J14: Adjusted For Age
B15: 1-3 Years Old | C15: 5955000 | F15: 1-3 Years Old | G15: 3008750 | J15: 1-5 Years Old | K15: =K16*150% -> 3750000
B16: 4-6 Years Old | C16: 3350000 | F16: 4-10 Years Old | G16: 1805250 | J16: 6-59 Years Old | K16: 2500000
B17: 7-9 Years Old | C17: 3040000 | F17: 11-18 Years Old | G17: 1564550 | J17: 60-65 Years Old | K17: =K16*130% -> 3250000
B18: 10-18 Years Old | C18: 2893800 | F18: 19-40 Years Old | G18: 1504375 | J18: Family Discounts | K18: 0.05
B19: 19-30 Years Old | C19: 2756000 | F19: 41-50 Years | G19: 1684900
B20: 31-40 Years Old | C20: 3031600 | F20: 51-60 Years | G20: 1805250
B21: 41-50 Years Old | C21: 3169400
B22: 51-60 Years Old | C22: 3307200

Sheet 14. Life insurance
B2: LIFE INSURANCE
B4: Sun Life - Sun Sống Mới | D4: Link | E4: Prudential - Phú Bảo An Advance Package | G4: Link | H4: Bảo Việt - An Phát Trọn Đời | J4: Link
B5: Premiums (per year) | C5: 20000000 | E5: Premiums (per year) | F5: 10900000 | H5: Premiums (per year) | I5: 36466640
B6: Benefits | E6: Protection scope | F6: Two breadwinners | H6: Protection scope | I6: Two breadwinners
B7: Death and Permanent Total Disability | C7: 1 billion VND for insured person | E7: Benefits | H7: Benefits
B8: Fatal diseases (Life-threatening cancer; End-stage renal failure; Severe traumatic brain injury) | C8: Get more 250 million VND for insured person | E8: Death and Permanent Total Disability | F8: 1 bilion VNĐ (1st breadwinner). 500 million VNĐ (2nd breadwinner)) | H8: Main products An Phát Trọn Đời | I8: - Pay 100% of the death benefit if the insured person suffers from permanent total disability due to an accident. - Advance 50% of the death benefit (up to 500 million VND) to cover treatment costs if the insured is diagnosed with a terminal illness. - Insurance coverage continues even if the insured can no longer pay premiums, provided that the surrender value of the contract (after deducting any debts) is sufficient to cover the monthly deductions."
B9: For dependants | C9: Get more 250 million VND If the insured person's parents are older than 65 years old and his children are lower than 18 years old at the time of he dies or has Permanent Total Disability (maximum 5 dependants) | E9: Death and Permanent Total Disability due to accidents | F9: 300 million VNĐ for each breadwinner | H9: Products to increase the protection
B10: Contract period | C10: 30 years | E10: 1st breadwinner has fatal diseases | F10: Waiver of premium for the entire contract | H10: Death and Permanent Total Disability | I10: 200 million VND for the other insured person
B11: Exclusions | E11: 2nd breadwinner dies or has Death and Permanent Total Disability | F11: Waiver of premiums for the entire contract and support of 100 million VND each year. | H11: Death and Permanent Total Disability due to accidents | I11: 200 million VND for the other insured person
B12: Death benefit does not apply | C12: - Suicide within two years from the Policy Effective Date, or the most recent Policy Reinstatement Date (if any). - Intentional acts by the Policyholder or Beneficiary against the Insured. - Execution by legal order. - Pre-existing conditions. | E12: Medical expenses | F12: Support for medical expenses before, during, and after hospitalization, surgery, and emergency costs due to accidents abroad. | H12: An tâm hạnh phúc | I12: 50 million VND for the main and the other insured person
B13: Permanent Total Disability benefit does not apply | C13: - Use of stimulants, narcotics, or intentional self-inflicted injury while sane or insane. - War or acts of war. - Intentional acts by the Policyholder or Beneficiary. - Serving in the military during wartime, or acting under combat orders or for public order restoration. - Participation in dangerous sports. | E13: Contract period | F13: 30 years | H13: Contract period | I13: 20 years
B14: Fatal diseases benefit does not appy | C14: 1. Critical illness diagnosed before or within 90 days from the policy effective date or the most recent policy reinstatement date (if any), whichever is later. 2. Life-threatening cancer or end-stage renal failure caused by or related to: - Congenital diseases. - Pre-existing conditions. - Treatment of radiation exposure or radioactive contamination. 3. Severe traumatic brain injury caused by or related to: - War or acts of war. - Participation in dangerous sports. - Boarding, exiting, operating, serving, or being transported on aircraft or aviation equipment not as a fare-paying passenger. - Criminal acts or violations of the law by the insured, policyholder, or beneficiary. - Consumption of alcoholic beverages exceeding the legal limit, or illegal use of stimulants, narcotics, sleeping pills, medication, sedatives, or any toxic substance. - Intentional self-inflicted injury while sane or insane within 2 years from the policy effective date or the most recent policy reinstatement date (if any). | E14: Exclusion | F14: 1. Exclusions of insurance benefits in the event of death due to direct or indirect consequences of: a. Suicide within 24 months from the date the insurance contract takes effect or the date of contract reinstatement; b. HIV infection; AIDS; or diseases related to AIDS; c. Criminal acts by the person who will receive the insurance benefits or the insured person. 2. Exclusions of insurance benefits in the event of Permanent Total Disability: a. That occurred prior to the date the insurance contract takes effect or the date of contract reinstatement (if applicable); b. Arising directly or indirectly from: - Suicide attempts or self-inflicted injuries, regardless of whether in a normal mental state or insane; - Participation in aviation activities, except as a passenger on commercial flights; - Committing criminal acts by the person who will receive the insurance benefits or the insured person. | H14: In case the insured person does not have any problem | I14: Get 40 billion at the ending year of the contract

Sheet 15. Travel tour
A1: Time Line | B1: 2024 | C1: 2025 | D1: =C1+1 -> 2026 | E1: =D1+1 -> 2027 | F1: =E1+1 -> 2028 | G1: =F1+1 -> 2029 | H1: =G1+1 -> 2030 | I1: =H1+1 -> 2031 | J1: =I1+1 -> 2032 | K1: =J1+1 -> 2033 | ... BN1: =BM1+1 -> 2088
A2: Period | B2: 0 | C2: 1 | D2: 2 | E2: =D2+1 -> 3 | F2: =E2+1 -> 4 | G2: =F2+1 -> 5 | H2: =G2+1 -> 6 | I2: =H2+1 -> 7 | J2: =I2+1 -> 8 | K2: =J2+1 -> 9 | L2: =K2+1 -> 10 | ... BN2: =BM2+1 -> 64
A3: Inflation rate | C3: ='3. Financial drivers '!G26 -> 0.0295 | D3: ='3. Financial drivers '!G27 -> 0.0249 | E3: ='3. Financial drivers '!G28 -> 0.028 | F3: ='3. Financial drivers '!G29 -> 0.029 | G3: ='3. Financial drivers '!G30 -> 0.029 | H3: ='3. Financial drivers '!G31 -> 0.029 | I3: ='3. Financial drivers '!$G$32 -> 0.02881 | J3: ='3. Financial drivers '!$G$32 -> 0.02881 | K3: ='3. Financial drivers '!$G$32 -> 0.02881 | L3: ='3. Financial drivers '!$G$32 -> 0.02881 | M3: ='3. Financial drivers '!$G$32 -> 0.02881 | N3: ='3. Financial drivers '!$G$32 -> 0.02881 | O3: ='3. Financial drivers '!$G$32 -> 0.02881 | P3: ='3. Financial drivers '!$G$32 -> 0.02881 | ... BN3: ='3. Financial drivers '!$G$32 -> 0.02881
A4: Travel tour expense
A5: Asia
A6: Malaysia - Singapore | C6: 10990000 | D6: =C6*(1+D3) -> 11263651 | E6: =D6*(1+E3) -> 11579033 | F6: =E6*(1+F3) -> 11914825 | G6: =F6*(1+G3) -> 12260355 | H6: =G6*(1+H3) -> 12615905 | I6: =H6*(1+I3) -> 12979370 | J6: =I6*(1+J3) -> 13353305 | K6: =J6*(1+K3) -> 13738014 | ... BN6: =BM6*(1+BN3) -> 65517707
A7: China | C7: 23990000 | D7: =C7*(1+D3) -> 24587351 | E7: =D7*(1+E3) -> 25275797 | F7: =E7*(1+F3) -> 26008795 | G7: =F7*(1+G3) -> 26763050 | H7: =G7*(1+H3) -> 27539178 | I7: =H7*(1+I3) -> 28332582 | J7: =I7*(1+J3) -> 29148844 | K7: =J7*(1+K3) -> 29988622 | ... BN7: =BM7*(1+BN3) -> 1.4301818e+08
A8: Korea | C8: 14990000 | D8: =C8*(1+D3) -> 15363251 | E8: =D8*(1+E3) -> 15793422 | F8: =E8*(1+F3) -> 16251431 | G8: =F8*(1+G3) -> 16722723 | H8: =G8*(1+H3) -> 17207682 | I8: =H8*(1+I3) -> 17703435 | J8: =I8*(1+J3) -> 18213471 | K8: =J8*(1+K3) -> 18738201 | ... BN8: =BM8*(1+BN3) -> 89364006
A9: Japan | C9: 29900000 | D9: =C9*(1+D3) -> 30644510 | E9: =D9*(1+E3) -> 31502556 | F9: =E9*(1+F3) -> 32416130 | G9: =F9*(1+G3) -> 33356198 | H9: =G9*(1+H3) -> 34323528 | I9: =H9*(1+I3) -> 35312389 | J9: =I9*(1+J3) -> 36329739 | K9: =J9*(1+K3) -> 37376398 | ... BN9: =BM9*(1+BN3) -> 1.7825109e+08
A11: Europe
A12: France - Luxembourg - German - Switzerland - Liechtenstein - Italy | C12: 74990000 | D12: =C12*(1+D3) -> 76857251 | E12: =D12*(1+E3) -> 79009254 | F12: =E12*(1+F3) -> 81300522 | G12: =F12*(1+G3) -> 83658238 | H12: =G12*(1+H3) -> 86084326 | I12: =H12*(1+I3) -> 88564416 | J12: =I12*(1+J3) -> 91115957 | K12: =J12*(1+K3) -> 93741007 | ... BN12: =BM12*(1+BN3) -> 4.4705849e+08
A13: Norway - Swenden - Denmark | C13: 79990000 | D13: =C13*(1+D3) -> 81981751 | E13: =D13*(1+E3) -> 84277240 | F13: =E13*(1+F3) -> 86721280 | G13: =F13*(1+G3) -> 89236197 | H13: =G13*(1+H3) -> 91824047 | I13: =H13*(1+I3) -> 94469498 | J13: =I13*(1+J3) -> 97191164 | K13: =J13*(1+K3) -> 99991241 | ... BN13: =BM13*(1+BN3) -> 4.7686636e+08
A14: Greece - Turkey | C14: 89990000 | D14: =C14*(1+D3) -> 92230751 | E14: =D14*(1+E3) -> 94813212 | F14: =E14*(1+F3) -> 97562795 | G14: =F14*(1+G3) -> 1.0039212e+08 | H14: =G14*(1+H3) -> 1.0330349e+08 | I14: =H14*(1+I3) -> 1.0627966e+08 | J14: =I14*(1+J3) -> 1.0934158e+08 | K14: =J14*(1+K3) -> 1.1249171e+08 | ... BN14: =BM14*(1+BN3) -> 5.3648211e+08
A15: England - Wales - Scotland | C15: 98990000 | D15: =C15*(1+D3) -> 1.0145485e+08 | E15: =D15*(1+E3) -> 1.0429559e+08 | F15: =E15*(1+F3) -> 1.0732016e+08 | G15: =F15*(1+G3) -> 1.1043244e+08 | H15: =G15*(1+H3) -> 1.1363498e+08 | I15: =H15*(1+I3) -> 1.1690881e+08 | J15: =I15*(1+J3) -> 1.2027695e+08 | K15: =J15*(1+K3) -> 1.2374213e+08 | ... BN15: =BM15*(1+BN3) -> 5.9013628e+08
A17: Australia
A18: Sydney - Blue Mountains - Canberra - Melbourne - Mt. Buller Snowy | C18: 64990000 | D18: =C18*(1+D3) -> 66608251 | E18: =D18*(1+E3) -> 68473282 | F18: =E18*(1+F3) -> 70459007 | G18: =F18*(1+G3) -> 72502318 | H18: =G18*(1+H3) -> 74604886 | I18: =H18*(1+I3) -> 76754252 | J18: =I18*(1+J3) -> 78965542 | K18: =J18*(1+K3) -> 81240540 | ... BN18: =BM18*(1+BN3) -> 3.8744274e+08
A20: Africa
A21: Egypt | C21: 79990000 | D21: =C21*(1+D3) -> 81981751 | E21: =D21*(1+E3) -> 84277240 | F21: =E21*(1+F3) -> 86721280 | G21: =F21*(1+G3) -> 89236197 | H21: =G21*(1+H3) -> 91824047 | I21: =H21*(1+I3) -> 94469498 | J21: =I21*(1+J3) -> 97191164 | K21: =J21*(1+K3) -> 99991241 | ... BN21: =BM21*(1+BN3) -> 4.7686636e+08
A22: South Africa | C22: 77900000 | D22: =C22*(1+D3) -> 79839710 | E22: =D22*(1+E3) -> 82075222 | F22: =E22*(1+F3) -> 84455403 | G22: =F22*(1+G3) -> 86904610 | H22: =G22*(1+H3) -> 89424844 | I22: =H22*(1+I3) -> 92001173 | J22: =I22*(1+J3) -> 94651727 | K22: =J22*(1+K3) -> 97378644 | ... BN22: =BM22*(1+BN3) -> 4.6440667e+08
A23: Morocco | C23: 79990000 | D23: =C23*(1+D3) -> 81981751 | E23: =D23*(1+E3) -> 84277240 | F23: =E23*(1+F3) -> 86721280 | G23: =F23*(1+G3) -> 89236197 | H23: =G23*(1+H3) -> 91824047 | I23: =H23*(1+I3) -> 94469498 | J23: =I23*(1+J3) -> 97191164 | K23: =J23*(1+K3) -> 99991241 | ... BN23: =BM23*(1+BN3) -> 4.7686636e+08

Sheet 16. Retirement 
A1: Time Line | B1: 2066 | C1: =B1+1 -> 2067 | D1: =C1+1 -> 2068 | E1: =D1+1 -> 2069 | F1: =E1+1 -> 2070 | G1: =F1+1 -> 2071 | H1: =G1+1 -> 2072 | I1: =H1+1 -> 2073 | J1: =I1+1 -> 2074 | ... X1: =W1+1 -> 2088
A2: Period | B2: 42 | C2: =B2+1 -> 43 | D2: =C2+1 -> 44 | E2: =D2+1 -> 45 | F2: =E2+1 -> 46 | G2: =F2+1 -> 47 | H2: =G2+1 -> 48 | I2: =H2+1 -> 49 | J2: =I2+1 -> 50 | ... X2: =W2+1 -> 64
A3: Inflation rate | B3: ='3. Financial drivers '!$G$32 -> 0.02881 | C3: ='3. Financial drivers '!$G$32 -> 0.02881 | D3: ='3. Financial drivers '!$G$32 -> 0.02881 | E3: ='3. Financial drivers '!$G$32 -> 0.02881 | F3: ='3. Financial drivers '!$G$32 -> 0.02881 | G3: ='3. Financial drivers '!$G$32 -> 0.02881 | H3: ='3. Financial drivers '!$G$32 -> 0.02881 | I3: ='3. Financial drivers '!$G$32 -> 0.02881 | ... X3: ='3. Financial drivers '!$G$32 -> 0.02881
A4: Huyen | C4: Vacation period | X4: Pass away
A5: Huyen's husband
A8: INCOME
A9: Huyen's pension | B9: ='7. Human capital & pension valu'!AR43 -> 5.4576416e+08 | C9: ='7. Human capital & pension valu'!AS43 -> 5.4576416e+08 | D9: ='7. Human capital & pension valu'!AT43 -> 5.4576416e+08 | E9: ='7. Human capital & pension valu'!AU43 -> 5.4576416e+08 | F9: ='7. Human capital & pension valu'!AV43 -> 5.4576416e+08 | G9: ='7. Human capital & pension valu'!AW43 -> 5.4576416e+08 | H9: ='7. Human capital & pension valu'!AX43 -> 5.4576416e+08 | I9: ='7. Human capital & pension valu'!AY43 -> 5.4576416e+08 | ... X9: ='7. Human capital & pension valu'!BN43 -> 5.4576416e+08
A10: Huyen's husband pension | B10: ='7. Human capital & pension valu'!AR51 -> 6.2185949e+08 | C10: ='7. Human capital & pension valu'!AS51 -> 6.2185949e+08 | D10: ='7. Human capital & pension valu'!AT51 -> 6.2185949e+08 | E10: ='7. Human capital & pension valu'!AU51 -> 6.2185949e+08 | F10: ='7. Human capital & pension valu'!AV51 -> 6.2185949e+08 | G10: ='7. Human capital & pension valu'!AW51 -> 6.2185949e+08 | H10: ='7. Human capital & pension valu'!AX51 -> 6.2185949e+08 | I10: ='7. Human capital & pension valu'!AY51 -> 6.2185949e+08 | ... X10: ='7. Human capital & pension valu'!BN51 -> 6.2185949e+08
A11: Interest | B11: {=TRANSPOSE('21. Monte Carlo Simulation '!Q44:Q66)} -> 2.3401321e+09 | C11: 2.9602391e+09 | D11: 2.8538038e+09 | E11: 3.2793817e+09 | F11: 2.9407319e+09 | G11: 3.3763829e+09 | H11: 3.2282821e+09 | I11: 3.5028097e+09 | J11: 3.8823573e+09 | K11: 3.951401e+09 | L11: 4.6477221e+09 | M11: 4.3053288e+09 | N11: 4.7577364e+09 | O11: 4.1509564e+09 | P11: 3.820835e+09 | Q11: 4.8812688e+09 | R11: 4.6579257e+09 | S11: 5.1599806e+09 | T11: 5.6146541e+09 | U11: 5.3892943e+09 | V11: 5.8671808e+09 | W11: 5.438647e+09 | X11: 7.1284037e+09
A12: Total income | B12: =SUM(B9:B11) -> 3.5077558e+09 | C12: =SUM(C9:C11) -> 4.1278627e+09 | D12: =SUM(D9:D11) -> 4.0214274e+09 | E12: =SUM(E9:E11) -> 4.4470053e+09 | F12: =SUM(F9:F11) -> 4.1083555e+09 | G12: =SUM(G9:G11) -> 4.5440065e+09 | H12: =SUM(H9:H11) -> 4.3959058e+09 | I12: =SUM(I9:I11) -> 4.6704333e+09 | ... X12: =SUM(X9:X11) -> 8.2960274e+09
A14: EXPENSE
A15: Food | B15: ='8. Budget Estimate'!AQ18*(1+B3) -> 2.297839e+08 | C15: =B15*(1+C3) -> 2.3640398e+08 | D15: =C15*(1+D3) -> 2.4321477e+08 | E15: =D15*(1+E3) -> 2.5022179e+08 | F15: =E15*(1+F3) -> 2.5743068e+08 | G15: =F15*(1+G3) -> 2.6484726e+08 | H15: =G15*(1+H3) -> 2.7247751e+08 | I15: =H15*(1+I3) -> 2.8032759e+08 | J15: =I15*(1+J3) -> 2.8840382e+08 | ... X15: =W15*(1+X3) -> 4.2923338e+08
A16: Necessities | B16: ='8. Budget Estimate'!AQ19*(1+B3) -> 76594634 | C16: =B16*(1+C3) -> 78801325 | D16: =C16*(1+D3) -> 81071591 | E16: =D16*(1+E3) -> 83407264 | F16: =E16*(1+F3) -> 85810227 | G16: =F16*(1+G3) -> 88282420 | H16: =G16*(1+H3) -> 90825836 | I16: =H16*(1+I3) -> 93442529 | J16: =I16*(1+J3) -> 96134608 | ... X16: =W16*(1+X3) -> 1.4307779e+08
A17: Electric and water | B17: ='8. Budget Estimate'!AQ20*(1+B3) -> 57445975 | C17: =B17*(1+C3) -> 59100994 | D17: =C17*(1+D3) -> 60803693 | E17: =D17*(1+E3) -> 62555448 | F17: =E17*(1+F3) -> 64357670 | G17: =F17*(1+G3) -> 66211815 | H17: =G17*(1+H3) -> 68119377 | I17: =H17*(1+I3) -> 70081896 | J17: =I17*(1+J3) -> 72100956 | ... X17: =W17*(1+X3) -> 1.0730835e+08
A18: Phone and internet | B18: ='8. Budget Estimate'!AQ21*(1+B3) -> 5744597.5 | C18: =B18*(1+C3) -> 5910099.4 | D18: =C18*(1+D3) -> 6080369.3 | E18: =D18*(1+E3) -> 6255544.8 | F18: =E18*(1+F3) -> 6435767 | G18: =F18*(1+G3) -> 6621181.5 | H18: =G18*(1+H3) -> 6811937.7 | I18: =H18*(1+I3) -> 7008189.6 | J18: =I18*(1+J3) -> 7210095.6 | ... X18: =W18*(1+X3) -> 10730835
A19: Fuel and gas | B19: ='8. Budget Estimate'!AQ22*(1+B3) -> 13404061 | C19: =B19*(1+C3) -> 13790232 | D19: =C19*(1+D3) -> 14187528 | E19: =D19*(1+E3) -> 14596271 | F19: =E19*(1+F3) -> 15016790 | G19: =F19*(1+G3) -> 15449423 | H19: =G19*(1+H3) -> 15894521 | I19: =H19*(1+I3) -> 16352442 | J19: =I19*(1+J3) -> 16823556 | ... X19: =W19*(1+X3) -> 25038614
A20: Parking | B20: ='8. Budget Estimate'!AQ23*(1+B3) -> 7659463.4 | C20: =B20*(1+C3) -> 7880132.5 | D20: =C20*(1+D3) -> 8107159.1 | E20: =D20*(1+E3) -> 8340726.4 | F20: =E20*(1+F3) -> 8581022.7 | G20: =F20*(1+G3) -> 8828242 | H20: =G20*(1+H3) -> 9082583.6 | I20: =H20*(1+I3) -> 9344252.9 | J20: =I20*(1+J3) -> 9613460.8 | ... X20: =W20*(1+X3) -> 14307779
A21: Skincare and comestic products | B21: ='8. Budget Estimate'!AQ24*(1+B3) -> 95743292 | C21: =B21*(1+C3) -> 98501656 | D21: =C21*(1+D3) -> 1.0133949e+08 | E21: =D21*(1+E3) -> 1.0425908e+08 | F21: =E21*(1+F3) -> 1.0726278e+08 | G21: =F21*(1+G3) -> 1.1035302e+08 | H21: =G21*(1+H3) -> 1.135323e+08 | I21: =H21*(1+I3) -> 1.1680316e+08 | J21: =I21*(1+J3) -> 1.2016826e+08 | ... X21: =W21*(1+X3) -> 1.7884724e+08
A22: Entertainment | B22: ='8. Budget Estimate'!AQ25*(1+B3) -> 32552719 | C22: =B22*(1+C3) -> 33490563 | D22: =C22*(1+D3) -> 34455426 | E22: =D22*(1+E3) -> 35448087 | F22: =E22*(1+F3) -> 36469346 | G22: =F22*(1+G3) -> 37520028 | H22: =G22*(1+H3) -> 38600980 | I22: =H22*(1+I3) -> 39713075 | J22: =I22*(1+J3) -> 40857208 | ... X22: =W22*(1+X3) -> 60808062
A23: Shopping | B23: ='8. Budget Estimate'!AQ26*(1+B3) -> 76594634 | C23: =B23*(1+C3) -> 78801325 | D23: =C23*(1+D3) -> 81071591 | E23: =D23*(1+E3) -> 83407264 | F23: =E23*(1+F3) -> 85810227 | G23: =F23*(1+G3) -> 88282420 | H23: =G23*(1+H3) -> 90825836 | I23: =H23*(1+I3) -> 93442529 | J23: =I23*(1+J3) -> 96134608 | ... X23: =W23*(1+X3) -> 1.4307779e+08
A24: Derivative expense such as wedding, funeral | B24: ='8. Budget Estimate'!AQ29*(1+B3) -> 15318927 | C24: =B24*(1+C3) -> 15760265 | D24: =C24*(1+D3) -> 16214318 | E24: =D24*(1+E3) -> 16681453 | F24: =E24*(1+F3) -> 17162045 | G24: =F24*(1+G3) -> 17656484 | H24: =G24*(1+H3) -> 18165167 | I24: =H24*(1+I3) -> 18688506 | J24: =I24*(1+J3) -> 19226922 | ... X24: =W24*(1+X3) -> 28615559
A25: Charitable contribution | B25: =2000000*12 -> 24000000 | C25: =B25*(1+C3) -> 24691440 | D25: =C25*(1+D3) -> 25402800 | E25: =D25*(1+E3) -> 26134655 | F25: =E25*(1+F3) -> 26887594 | G25: =F25*(1+G3) -> 27662226 | H25: =G25*(1+H3) -> 28459175 | I25: =H25*(1+I3) -> 29279084 | J25: =I25*(1+J3) -> 30122614 | ... X25: =W25*(1+X3) -> 44831692
A26: Fitness membership | B26: =2500000*12 -> 30000000 | C26: =B26*(1+C3) -> 30864300 | D26: =C26*(1+D3) -> 31753500 | E26: =D26*(1+E3) -> 32668319 | F26: =E26*(1+F3) -> 33609493 | G26: =F26*(1+G3) -> 34577783 | H26: =G26*(1+H3) -> 35573969 | I26: =H26*(1+I3) -> 36598855 | J26: =I26*(1+J3) -> 37653268 | ... X26: =W26*(1+X3) -> 56039616
A27: Healthcare visit | B27: ='8. Budget Estimate'!AQ30*(1+B3) -> 38297317 | C27: =B27*(1+C3) -> 39400663 | D27: =C27*(1+D3) -> 40535796 | E27: =D27*(1+E3) -> 41703632 | F27: =E27*(1+F3) -> 42905114 | G27: =F27*(1+G3) -> 44141210 | H27: =G27*(1+H3) -> 45412918 | I27: =H27*(1+I3) -> 46721264 | J27: =I27*(1+J3) -> 48067304 | ... X27: =W27*(1+X3) -> 71538897
A28: Travel expense | C28: ='15. Travel tour'!AS6*2 -> 72168880 | D28: ='15. Travel tour'!AT7*2 -> 1.6207562e+08 | E28: ='15. Travel tour'!AU8*2 -> 1.0418957e+08 | F28: ='15. Travel tour'!AV9*2 -> 2.1381048e+08 | G28: ='15. Travel tour'!AW12*2 -> 5.5169155e+08 | H28: ='15. Travel tour'!AX13*2 -> 6.0542989e+08 | I28: ='15. Travel tour'!AY14*2 -> 7.007411e+08 | J28: ='15. Travel tour'!AZ15*2 -> 7.930304e+08 | K28: ='15. Travel tour'!BA18*2 -> 5.3564891e+08 | L28: ='15. Travel tour'!BB21 -> 3.3913653e+08 | M28: ='15. Travel tour'!BC22 -> 3.3979071e+08 | N28: ='15. Travel tour'!BD23 -> 3.5895906e+08
A29: Motorbike insurance | B29: ='8. Budget Estimate'!$AQ$33 -> 132000 | C29: ='8. Budget Estimate'!$AQ$33 -> 132000 | D29: ='8. Budget Estimate'!$AQ$33 -> 132000 | E29: ='8. Budget Estimate'!$AQ$33 -> 132000 | F29: ='8. Budget Estimate'!$AQ$33 -> 132000 | G29: ='8. Budget Estimate'!$AQ$33 -> 132000 | H29: ='8. Budget Estimate'!$AQ$33 -> 132000 | I29: ='8. Budget Estimate'!$AQ$33 -> 132000 | ... X29: ='8. Budget Estimate'!$AQ$33 -> 132000
A30: Car insurance | B30: ='8. Budget Estimate'!$AQ$34 -> 4035935.8 | C30: ='8. Budget Estimate'!$AQ$34 -> 4035935.8 | D30: ='8. Budget Estimate'!$AQ$34 -> 4035935.8 | E30: ='8. Budget Estimate'!$AQ$34 -> 4035935.8 | F30: ='8. Budget Estimate'!$AQ$34 -> 4035935.8 | G30: ='8. Budget Estimate'!$AQ$34 -> 4035935.8 | H30: ='8. Budget Estimate'!$AQ$34 -> 4035935.8 | I30: ='8. Budget Estimate'!$AQ$34 -> 4035935.8 | ... X30: ='8. Budget Estimate'!$AQ$34 -> 4035935.8
A31: Total expense | B31: =SUM(B15:B30) -> 7.0730746e+08 | C31: =SUM(C15:C30) -> 7.9973379e+08 | D31: =SUM(D15:D30) -> 9.1048159e+08 | E31: =SUM(E15:E30) -> 8.7403704e+08 | F31: =SUM(F15:F30) -> 1.0057172e+09 | G31: =SUM(G15:G30) -> 1.366293e+09 | H31: =SUM(H15:H30) -> 1.4433799e+09 | I31: =SUM(I15:I30) -> 1.5627124e+09 | ... X31: =SUM(X15:X30) -> 1.3176235e+09
A32: Surplus/Deficit | B32: =B12-B31 -> 2.8004483e+09 | C32: =C12-C31 -> 3.3281289e+09 | D32: =D12-D31 -> 3.1109458e+09 | E32: =E12-E31 -> 3.5729683e+09 | F32: =F12-F31 -> 3.1026383e+09 | G32: =G12-G31 -> 3.1777135e+09 | H32: =H12-H31 -> 2.9525258e+09 | I32: =I12-I31 -> 3.1077209e+09 | ... X32: =X12-X31 -> 6.9784038e+09

Sheet 18. Investment assumption
B2: Three funds
B4: Fund Type | C4: Description | D4: Method
B5: Emergency Fund | C5: If monthly income falls short, this fund covers unforeseen but essential expenses. | D5: Checking Account
D6: 6x monthly expenses
B7: Saving Fund | C7: Store for future needs or emergencies with a safe account. | D7: Savings Account
B8: Investment Fund | C8: Used for investments. | D8: Stock and DCBF
B11: Instrument characteristics
B12: Instrument | C12: Characteristics
B13: Stock | C13: Highly liquid, high returns, high market risk.
B14: Bond | C14: Periodic payments, lower returns, lower risk compared to stocks.
B15: DCBF | C15: A diversified portfolio of assets, high liquidity.
B16: Gold | C16: Value influenced by supply and demand.
B17: Crypto | C17: High returns but significant risks.
B19: Age | C19: Saving | D19: Stock | E19: Bond | F19: Total %
B20: 22 | C20: 0.6 | D20: 0.2 | E20: 0.2 | F20: =SUM(C20:E20) -> 1
B21: 23 | C21: 0.6 | D21: 0.2 | E21: 0.2 | F21: =SUM(C21:E21) -> 1
B22: 24 | C22: 0.6 | D22: 0.2 | E22: 0.2 | F22: =SUM(C22:E22) -> 1
B23: 25 | C23: 0.6 | D23: 0.2 | E23: 0.2 | F23: =SUM(C23:E23) -> 1
B24: 26 | C24: 0.6 | D24: 0.2 | E24: 0.2 | F24: =SUM(C24:E24) -> 1
B25: 27 | C25: 0.6 | D25: 0.1 | E25: =1-C25-D25 -> 0.3 | F25: =SUM(C25:E25) -> 1
B26: 28 | C26: 0.6 | D26: 0.1 | E26: =1-C26-D26 -> 0.3 | F26: =SUM(C26:E26) -> 1
B27: 29 | C27: 0.6 | D27: 0.1 | E27: =1-C27-D27 -> 0.3 | F27: =SUM(C27:E27) -> 1
B28: 30 | C28: 0.6 | D28: 0.1 | E28: =1-C28-D28 -> 0.3 | F28: =SUM(C28:E28) -> 1
B29: 31 | C29: 0.6 | D29: 0.1 | E29: =1-C29-D29 -> 0.3 | F29: =SUM(C29:E29) -> 1
B30: 32 | C30: 0.6 | D30: 0.1 | E30: =1-C30-D30 -> 0.3 | F30: =SUM(C30:E30) -> 1
B31: 33 | C31: 0.6 | D31: 0.1 | E31: =1-C31-D31 -> 0.3 | F31: =SUM(C31:E31) -> 1
B32: 34 | C32: 0.6 | D32: 0.1 | E32: =1-C32-D32 -> 0.3 | F32: =SUM(C32:E32) -> 1
B33: 35 | C33: 0.6 | D33: 0.1 | E33: =1-C33-D33 -> 0.3 | F33: =SUM(C33:E33) -> 1
B34: 36 | C34: 0.6 | D34: 0.1 | E34: =1-C34-D34 -> 0.3 | F34: =SUM(C34:E34) -> 1
B35: 37 | C35: 0.6 | D35: 0.1 | E35: =1-C35-D35 -> 0.3 | F35: =SUM(C35:E35) -> 1
B36: 38 | C36: 0.6 | D36: 0.1 | E36: =1-C36-D36 -> 0.3 | F36: =SUM(C36:E36) -> 1
... B83: 85 | C83: 0.6 | D83: 0 | E83: =1-C83-D83 -> 0.4 | F83: =SUM(C83:E83) -> 1

Sheet 19. Funds 
B2: Age | C2: Income | D2: Expense | E2: Surplus/Deficit | F2: Current emergency | G2: Desired emergency | H2: Additional emergency | I2: Drawdown from emergency fund | J2: Surplus/Deficit left | K2: Saving with additional fund | L2: Drawdown from saving | M2: Surplus/Deficit left | N2: Additional investment fund | O2: Drawdown from investment | P2: Surplus/Deficit left
B3: 22 | C3: {=TRANSPOSE('8. Budget Estimate'!C14:AQ14)} -> 378320000 | D3: {=TRANSPOSE('8. Budget Estimate'!C39:AQ39)} -> 374388000 | E3: =C3-D3 -> 3932000 | F3: ='4. Balance sheet '!C8 -> 20000000 | G3: =$D$3/2 -> 187194000 | H3: =IF(G3>F3, G3-F3, 0) -> 167194000 | I3: =IF(E3<0, IF(F3>-E3, E3, -F3),0) -> 0 | J3: =IF(E3>0, E3-H3, E3-I3) -> -163262000 | K3: =IF(J3<0, 0,J3*0.6) -> 0 | L3: =IF(J3<0,IF('20. Balance '!D3>-J3,J3,-'20. Balance '!D3),0) -> -70000000 | M3: =IF(J3>0, J3-K3, J3-L3) -> -93262000 | N3: =IF(M3<0, 0, M3) -> 0 | O3: =IF(M3<0,IF('20. Balance '!E3>-M3,M3,-'20. Balance '!E3),0) -> 0 | P3: =IF(M3>0,M3-N3,N3-O3) -> 0 | AS3: ='8. Budget Estimate'!AR14 -> 0
B4: =B3+1 -> 23 | C4: 383722560 | D4: 3.8699377e+08 | E4: =C4-D4 -> -3271214.4 | F4: =F3+H3+I3 -> 187194000 | G4: =$D$3/2 -> 187194000 | H4: =IF(G4>F4, G4-F4, 0) -> 0 | I4: =IF(E4<0, IF(F4>-E4, E4, -F4),0) -> -3271214.4 | J4: =IF(E4>0, E4-H4, E4-I4) -> 0 | K4: =IF(J4<0, 0,J4*0.6) -> 0 | L4: =IF(J4<0,IF('20. Balance '!D4>-J4,J4,-'20. Balance '!D4),0) -> 0 | M4: =IF(J4>0, J4-K4, J4-L4) -> 0 | N4: =IF(M4<0, 0, M4) -> 0 | O4: =IF(M4<0,IF('20. Balance '!E4>-M4,M4,-'20. Balance '!E4),0) -> 0 | P4: =IF(M4>0,M4-N4,N4-O4) -> 0
B5: =B4+1 -> 24 | C5: 3.9446679e+08 | D5: 4.015219e+08 | E5: =C5-D5 -> -7055112.4 | F5: =F4+H4+I4 -> 1.8392279e+08 | G5: =$D$3/2 -> 187194000 | H5: =IF(G5>F5, G5-F5, 0) -> 3271214.4 | I5: =IF(E5<0, IF(F5>-E5, E5, -F5),0) -> -7055112.4 | J5: =IF(E5>0, E5-H5, E5-I5) -> 0 | K5: =IF(J5<0, 0,J5*0.6) -> 0 | L5: =IF(J5<0,IF('20. Balance '!D5>-J5,J5,-'20. Balance '!D5),0) -> 0 | M5: =IF(J5>0, J5-K5, J5-L5) -> 0 | N5: =IF(M5<0, 0, M5) -> 0 | O5: =IF(M5<0,IF('20. Balance '!E5>-M5,M5,-'20. Balance '!E5),0) -> 0 | P5: =IF(M5>0,M5-N5,N5-O5) -> 0
B6: =B5+1 -> 25 | C6: 488800000 | D6: 4.4139856e+08 | E6: =C6-D6 -> 47401435 | F6: =F5+H5+I5 -> 1.8013889e+08 | G6: =$D$3/2 -> 187194000 | H6: =IF(G6>F6, G6-F6, 0) -> 7055112.4 | I6: =IF(E6<0, IF(F6>-E6, E6, -F6),0) -> 0 | J6: =IF(E6>0, E6-H6, E6-I6) -> 40346323 | K6: =IF(J6<0, 0,J6*0.6) -> 24207794 | L6: =IF(J6<0,IF('20. Balance '!D6>-J6,J6,-'20. Balance '!D6),0) -> 0 | M6: =IF(J6>0, J6-K6, J6-L6) -> 16138529 | N6: =IF(M6<0, 0, M6) -> 16138529 | O6: =IF(M6<0,IF('20. Balance '!E6>-M6,M6,-'20. Balance '!E6),0) -> 0 | P6: =IF(M6>0,M6-N6,N6-O6) -> 0
B7: =B6+1 -> 26 | C7: 5.0481238e+08 | D7: 4.535689e+08 | E7: =C7-D7 -> 51243484 | F7: =F6+H6+I6 -> 187194000 | G7: =$D$3/2 -> 187194000 | H7: =IF(G7>F7, G7-F7, 0) -> 0 | I7: =IF(E7<0, IF(F7>-E7, E7, -F7),0) -> 0 | J7: =IF(E7>0, E7-H7, E7-I7) -> 51243484 | K7: =IF(J7<0, 0,J7*0.6) -> 30746090 | L7: =IF(J7<0,IF('20. Balance '!D7>-J7,J7,-'20. Balance '!D7),0) -> 0 | M7: =IF(J7>0, J7-K7, J7-L7) -> 20497394 | N7: =IF(M7<0, 0, M7) -> 20497394 | O7: =IF(M7<0,IF('20. Balance '!E7>-M7,M7,-'20. Balance '!E7),0) -> 0 | P7: =IF(M7>0,M7-N7,N7-O7) -> 0
B8: =B7+1 -> 27 | C8: 4.0709087e+08 | D8: 5.2017705e+08 | E8: =C8-D8 -> -1.1308617e+08 | F8: =F7+H7+I7 -> 187194000 | G8: =$D$3/2 -> 187194000 | H8: =IF(G8>F8, G8-F8, 0) -> 0 | I8: =IF(E8<0, IF(F8>-E8, E8, -F8),0) -> -1.1308617e+08 | J8: =IF(E8>0, E8-H8, E8-I8) -> 0 | K8: =IF(J8<0, 0,J8*0.6) -> 0 | L8: =IF(J8<0,IF('20. Balance '!D8>-J8,J8,-'20. Balance '!D8),0) -> 0 | M8: =IF(J8>0, J8-K8, J8-L8) -> 0 | N8: =IF(M8<0, 0, M8) -> 0 | O8: =IF(M8<0,IF('20. Balance '!E8>-M8,M8,-'20. Balance '!E8),0) -> 0 | P8: =IF(M8>0,M8-N8,N8-O8) -> 0
B9: =B8+1 -> 28 | C9: 5.9778838e+08 | D9: 5.7361002e+08 | E9: =C9-D9 -> 24178361 | F9: =F8+H8+I8 -> 74107826 | G9: =$D$9/2 -> 2.8680501e+08 | H9: =IF(G9>F9, G9-F9, 0) -> 2.1269718e+08 | I9: =IF(E9<0, IF(F9>-E9, E9, -F9),0) -> 0 | J9: =IF(E9>0, E9-H9, E9-I9) -> -1.8851882e+08 | K9: =IF(J9<0, 0,J9*0.6) -> 0 | L9: =IF(J9<0,IF('20. Balance '!D9>-J9,J9,-'20. Balance '!D9),0) -> -54953884 | M9: =IF(J9>0, J9-K9, J9-L9) -> -1.3356494e+08 | N9: =IF(M9<0, 0, M9) -> 0 | O9: =IF(M9<0,IF('20. Balance '!E9>-M9,M9,-'20. Balance '!E9),0) -> -36635923 | P9: =IF(M9>0,M9-N9,N9-O9) -> 36635923
B10: =B9+1 -> 29 | C10: 6.1311809e+08 | D10: 5.8948837e+08 | E10: =C10-D10 -> 23629717 | F10: =F9+H9+I9 -> 2.8680501e+08 | G10: =$D$9/2 -> 2.8680501e+08 | H10: =IF(G10>F10, G10-F10, 0) -> 0 | I10: =IF(E10<0, IF(F10>-E10, E10, -F10),0) -> 0 | J10: =IF(E10>0, E10-H10, E10-I10) -> 23629717 | K10: =IF(J10<0, 0,J10*0.6) -> 14177830 | L10: =IF(J10<0,IF('20. Balance '!D10>-J10,J10,-'20. Balance '!D10),0) -> 0 | M10: =IF(J10>0, J10-K10, J10-L10) -> 9451886.8 | N10: =IF(M10<0, 0, M10) -> 9451886.8 | O10: =IF(M10<0,IF('20. Balance '!E10>-M10,M10,-'20. Balance '!E10),0) -> 0 | P10: =IF(M10>0,M10-N10,N10-O10) -> 0
B11: =B10+1 -> 30 | C11: 7.4509759e+08 | D11: 6.1638224e+08 | E11: =C11-D11 -> 1.2871535e+08 | F11: =F10+H10+I10 -> 2.8680501e+08 | G11: =$D$9/2 -> 2.8680501e+08 | H11: =IF(G11>F11, G11-F11, 0) -> 0 | I11: =IF(E11<0, IF(F11>-E11, E11, -F11),0) -> 0 | J11: =IF(E11>0, E11-H11, E11-I11) -> 1.2871535e+08 | K11: =IF(J11<0, 0,J11*0.6) -> 77229208 | L11: =IF(J11<0,IF('20. Balance '!D11>-J11,J11,-'20. Balance '!D11),0) -> 0 | M11: =IF(J11>0, J11-K11, J11-L11) -> 51486139 | N11: =IF(M11<0, 0, M11) -> 51486139 | O11: =IF(M11<0,IF('20. Balance '!E11>-M11,M11,-'20. Balance '!E11),0) -> 0 | P11: =IF(M11>0,M11-N11,N11-O11) -> 0
B12: =B11+1 -> 31 | C12: 8.045482e+08 | D12: 6.4142173e+08 | E12: =C12-D12 -> 1.6312647e+08 | F12: =F11+H11+I11 -> 2.8680501e+08 | G12: =$D$9/2 -> 2.8680501e+08 | H12: =IF(G12>F12, G12-F12, 0) -> 0 | I12: =IF(E12<0, IF(F12>-E12, E12, -F12),0) -> 0 | J12: =IF(E12>0, E12-H12, E12-I12) -> 1.6312647e+08 | K12: =IF(J12<0, 0,J12*0.6) -> 97875884 | L12: =IF(J12<0,IF('20. Balance '!D12>-J12,J12,-'20. Balance '!D12),0) -> 0 | M12: =IF(J12>0, J12-K12, J12-L12) -> 65250589 | N12: =IF(M12<0, 0, M12) -> 65250589 | O12: =IF(M12<0,IF('20. Balance '!E12>-M12,M12,-'20. Balance '!E12),0) -> 0 | P12: =IF(M12>0,M12-N12,N12-O12) -> 0
B13: =B12+1 -> 32 | C13: 8.5658268e+08 | D13: 9.8361115e+08 | E13: =C13-D13 -> -1.2702847e+08 | F13: =F12+H12+I12 -> 2.8680501e+08 | G13: =$D$9/2 -> 2.8680501e+08 | H13: =IF(G13>F13, G13-F13, 0) -> 0 | I13: =IF(E13<0, IF(F13>-E13, E13, -F13),0) -> -1.2702847e+08 | J13: =IF(E13>0, E13-H13, E13-I13) -> 0 | K13: =IF(J13<0, 0,J13*0.6) -> 0 | L13: =IF(J13<0,IF('20. Balance '!D13>-J13,J13,-'20. Balance '!D13),0) -> 0 | M13: =IF(J13>0, J13-K13, J13-L13) -> 0 | N13: =IF(M13<0, 0, M13) -> 0 | O13: =IF(M13<0,IF('20. Balance '!E13>-M13,M13,-'20. Balance '!E13),0) -> 0 | P13: =IF(M13>0,M13-N13,N13-O13) -> 0
B14: =B13+1 -> 33 | C14: 8.6548999e+08 | D14: 9.6222877e+08 | E14: =C14-D14 -> -96738777 | F14: =F13+H13+I13 -> 1.5977654e+08 | G14: =$D$9/2 -> 2.8680501e+08 | H14: =IF(G14>F14, G14-F14, 0) -> 1.2702847e+08 | I14: =IF(E14<0, IF(F14>-E14, E14, -F14),0) -> -96738777 | J14: =IF(E14>0, E14-H14, E14-I14) -> 0 | K14: =IF(J14<0, 0,J14*0.6) -> 0 | L14: =IF(J14<0,IF('20. Balance '!D14>-J14,J14,-'20. Balance '!D14),0) -> 0 | M14: =IF(J14>0, J14-K14, J14-L14) -> 0 | N14: =IF(M14<0, 0, M14) -> 0 | O14: =IF(M14<0,IF('20. Balance '!E14>-M14,M14,-'20. Balance '!E14),0) -> 0 | P14: =IF(M14>0,M14-N14,N14-O14) -> 0
B15: =B14+1 -> 34 | C15: 1.0527365e+09 | D15: 1.0230386e+09 | E15: =C15-D15 -> 29697861 | F15: =F14+H14+I14 -> 1.9006623e+08 | G15: =$D$9/2 -> 2.8680501e+08 | H15: =IF(G15>F15, G15-F15, 0) -> 96738777 | I15: =IF(E15<0, IF(F15>-E15, E15, -F15),0) -> 0 | J15: =IF(E15>0, E15-H15, E15-I15) -> -67040916 | K15: =IF(J15<0, 0,J15*0.6) -> 0 | L15: =IF(J15<0,IF('20. Balance '!D15>-J15,J15,-'20. Balance '!D15),0) -> -67040916 | M15: =IF(J15>0, J15-K15, J15-L15) -> 0 | N15: =IF(M15<0, 0, M15) -> 0 | O15: =IF(M15<0,IF('20. Balance '!E15>-M15,M15,-'20. Balance '!E15),0) -> 0 | P15: =IF(M15>0,M15-N15,N15-O15) -> 0
B16: =B15+1 -> 35 | C16: 1.1428527e+09 | D16: 1.0576959e+09 | E16: =C16-D16 -> 85156795 | F16: =F15+H15+I15 -> 2.8680501e+08 | G16: =$D$9/2 -> 2.8680501e+08 | H16: =IF(G16>F16, G16-F16, 0) -> 0 | I16: =IF(E16<0, IF(F16>-E16, E16, -F16),0) -> 0 | J16: =IF(E16>0, E16-H16, E16-I16) -> 85156795 | K16: =IF(J16<0, 0,J16*0.6) -> 51094077 | L16: =IF(J16<0,IF('20. Balance '!D16>-J16,J16,-'20. Balance '!D16),0) -> 0 | M16: =IF(J16>0, J16-K16, J16-L16) -> 34062718 | N16: =IF(M16<0, 0, M16) -> 34062718 | O16: =IF(M16<0,IF('20. Balance '!E16>-M16,M16,-'20. Balance '!E16),0) -> 0 | P16: =IF(M16>0,M16-N16,N16-O16) -> 0
B17: =B16+1 -> 36 | C17: 1.1744125e+09 | D17: 1.0761497e+09 | E17: =C17-D17 -> 98262768 | F17: =F16+H16+I16 -> 2.8680501e+08 | G17: =$D$9/2 -> 2.8680501e+08 | H17: =IF(G17>F17, G17-F17, 0) -> 0 | I17: =IF(E17<0, IF(F17>-E17, E17, -F17),0) -> 0 | J17: =IF(E17>0, E17-H17, E17-I17) -> 98262768 | K17: =IF(J17<0, 0,J17*0.6) -> 58957661 | L17: =IF(J17<0,IF('20. Balance '!D17>-J17,J17,-'20. Balance '!D17),0) -> 0 | M17: =IF(J17>0, J17-K17, J17-L17) -> 39305107 | N17: =IF(M17<0, 0, M17) -> 39305107 | O17: =IF(M17<0,IF('20. Balance '!E17>-M17,M17,-'20. Balance '!E17),0) -> 0 | P17: =IF(M17>0,M17-N17,N17-O17) -> 0
B18: =B17+1 -> 37 | C18: 1.5623956e+09 | D18: 1.2106049e+09 | E18: =C18-D18 -> 3.5179075e+08 | F18: =F17+H17+I17 -> 2.8680501e+08 | G18: =$D$9/2 -> 2.8680501e+08 | H18: =IF(G18>F18, G18-F18, 0) -> 0 | I18: =IF(E18<0, IF(F18>-E18, E18, -F18),0) -> 0 | J18: =IF(E18>0, E18-H18, E18-I18) -> 3.5179075e+08 | K18: =IF(J18<0, 0,J18*0.6) -> 2.1107445e+08 | L18: =IF(J18<0,IF('20. Balance '!D18>-J18,J18,-'20. Balance '!D18),0) -> 0 | M18: =IF(J18>0, J18-K18, J18-L18) -> 1.407163e+08 | N18: =IF(M18<0, 0, M18) -> 1.407163e+08 | O18: =IF(M18<0,IF('20. Balance '!E18>-M18,M18,-'20. Balance '!E18),0) -> 0 | P18: =IF(M18>0,M18-N18,N18-O18) -> 0
B19: =B18+1 -> 38 | C19: 1.5985709e+09 | D19: 1.2494027e+09 | E19: =C19-D19 -> 3.491682e+08 | F19: =F18+H18+I18 -> 2.8680501e+08 | G19: =$D$9/2 -> 2.8680501e+08 | H19: =IF(G19>F19, G19-F19, 0) -> 0 | I19: =IF(E19<0, IF(F19>-E19, E19, -F19),0) -> 0 | J19: =IF(E19>0, E19-H19, E19-I19) -> 3.491682e+08 | K19: =IF(J19<0, 0,J19*0.6) -> 2.0950092e+08 | L19: =IF(J19<0,IF('20. Balance '!D19>-J19,J19,-'20. Balance '!D19),0) -> 0 | M19: =IF(J19>0, J19-K19, J19-L19) -> 1.3966728e+08 | N19: =IF(M19<0, 0, M19) -> 1.3966728e+08 | O19: =IF(M19<0,IF('20. Balance '!E19>-M19,M19,-'20. Balance '!E19),0) -> 0 | P19: =IF(M19>0,M19-N19,N19-O19) -> 0
B20: =B19+1 -> 39 | C20: 1.9966039e+09 | D20: 1.4085803e+09 | E20: =C20-D20 -> 5.8802365e+08 | F20: =F19+H19+I19 -> 2.8680501e+08 | G20: =$D$9/2 -> 2.8680501e+08 | H20: =IF(G20>F20, G20-F20, 0) -> 0 | I20: =IF(E20<0, IF(F20>-E20, E20, -F20),0) -> 0 | J20: =IF(E20>0, E20-H20, E20-I20) -> 5.8802365e+08 | K20: =IF(J20<0, 0,J20*0.6) -> 3.5281419e+08 | L20: =IF(J20<0,IF('20. Balance '!D20>-J20,J20,-'20. Balance '!D20),0) -> 0 | M20: =IF(J20>0, J20-K20, J20-L20) -> 2.3520946e+08 | N20: =IF(M20<0, 0, M20) -> 2.3520946e+08 | O20: =IF(M20<0,IF('20. Balance '!E20>-M20,M20,-'20. Balance '!E20),0) -> 0 | P20: =IF(M20>0,M20-N20,N20-O20) -> 0
... B43: =B42+1 -> 62 | C43: 4.6307933e+09 | D43: 1.317001e+09 | E43: =C43-D43 -> 3.3137923e+09 | F43: =F42+H42+I42 -> 2.8680501e+08 | G43: =$D$9/2 -> 2.8680501e+08 | H43: =IF(G43>F43, G43-F43, 0) -> 0 | I43: =IF(E43<0, IF(F43>-E43, E43, -F43),0) -> 0 | J43: =IF(E43>0, E43-H43, E43-I43) -> 3.3137923e+09 | K43: =IF(J43<0, 0,J43*0.6) -> 1.9882754e+09 | L43: =IF(J43<0,IF('20. Balance '!D43>-J43,J43,-'20. Balance '!D43),0) -> 0 | M43: =IF(J43>0, J43-K43, J43-L43) -> 1.3255169e+09 | N43: =IF(M43<0, 0, M43) -> 1.3255169e+09 | O43: =IF(M43<0,IF('20. Balance '!E43>-M43,M43,-'20. Balance '!E43),0) -> 0 | P43: =IF(M43>0,M43-N43,N43-O43) -> 0
B44: =B43+1 -> 63 | C44: {=TRANSPOSE('16. Retirement '!B12:X12)} -> 3.5077558e+09 | D44: {=TRANSPOSE('16. Retirement '!B31:X31)} -> 7.0730746e+08 | E44: =C44-D44 -> 2.8004483e+09 | F44: =F43+H43+I43 -> 2.8680501e+08 | G44: =$D$9/2 -> 2.8680501e+08 | H44: =IF(G44>F44, G44-F44, 0) -> 0 | I44: =IF(E44<0, IF(F44>-E44, E44, -F44),0) -> 0 | J44: =IF(E44>0, E44-H44, E44-I44) -> 2.8004483e+09 | K44: =IF(J44<0, 0,J44*0.6) -> 1.680269e+09 | L44: =IF(J44<0,IF('20. Balance '!D44>-J44,J44,-'20. Balance '!D44),0) -> 0 | M44: =IF(J44>0, J44-K44, J44-L44) -> 1.1201793e+09 | N44: =IF(M44<0, 0, M44) -> 1.1201793e+09 | O44: =IF(M44<0,IF('20. Balance '!E44>-M44,M44,-'20. Balance '!E44),0) -> 0 | P44: =IF(M44>0,M44-N44,N44-O44) -> 0
B45: =B44+1 -> 64 | C45: 4.1278627e+09 | D45: 7.9973379e+08 | E45: =C45-D45 -> 3.3281289e+09 | F45: =F44+H44+I44 -> 2.8680501e+08 | G45: =$D$9/2 -> 2.8680501e+08 | H45: =IF(G45>F45, G45-F45, 0) -> 0 | I45: =IF(E45<0, IF(F45>-E45, E45, -F45),0) -> 0 | J45: =IF(E45>0, E45-H45, E45-I45) -> 3.3281289e+09 | K45: =IF(J45<0, 0,J45*0.6) -> 1.9968774e+09 | L45: =IF(J45<0,IF('20. Balance '!D45>-J45,J45,-'20. Balance '!D45),0) -> 0 | M45: =IF(J45>0, J45-K45, J45-L45) -> 1.3312516e+09 | N45: =IF(M45<0, 0, M45) -> 1.3312516e+09 | O45: =IF(M45<0,IF('20. Balance '!E45>-M45,M45,-'20. Balance '!E45),0) -> 0 | P45: =IF(M45>0,M45-N45,N45-O45) -> 0
B46: =B45+1 -> 65 | C46: 4.0214274e+09 | D46: 9.1048159e+08 | E46: =C46-D46 -> 3.1109458e+09 | F46: =F45+H45+I45 -> 2.8680501e+08 | G46: =$D$9/2 -> 2.8680501e+08 | H46: =IF(G46>F46, G46-F46, 0) -> 0 | I46: =IF(E46<0, IF(F46>-E46, E46, -F46),0) -> 0 | J46: =IF(E46>0, E46-H46, E46-I46) -> 3.1109458e+09 | K46: =IF(J46<0, 0,J46*0.6) -> 1.8665675e+09 | L46: =IF(J46<0,IF('20. Balance '!D46>-J46,J46,-'20. Balance '!D46),0) -> 0 | M46: =IF(J46>0, J46-K46, J46-L46) -> 1.2443783e+09 | N46: =IF(M46<0, 0, M46) -> 1.2443783e+09 | O46: =IF(M46<0,IF('20. Balance '!E46>-M46,M46,-'20. Balance '!E46),0) -> 0 | P46: =IF(M46>0,M46-N46,N46-O46) -> 0
B47: =B46+1 -> 66 | C47: 4.4470053e+09 | D47: 8.7403704e+08 | E47: =C47-D47 -> 3.5729683e+09 | F47: =F46+H46+I46 -> 2.8680501e+08 | G47: =$D$9/2 -> 2.8680501e+08 | H47: =IF(G47>F47, G47-F47, 0) -> 0 | I47: =IF(E47<0, IF(F47>-E47, E47, -F47),0) -> 0 | J47: =IF(E47>0, E47-H47, E47-I47) -> 3.5729683e+09 | K47: =IF(J47<0, 0,J47*0.6) -> 2.143781e+09 | L47: =IF(J47<0,IF('20. Balance '!D47>-J47,J47,-'20. Balance '!D47),0) -> 0 | M47: =IF(J47>0, J47-K47, J47-L47) -> 1.4291873e+09 | N47: =IF(M47<0, 0, M47) -> 1.4291873e+09 | O47: =IF(M47<0,IF('20. Balance '!E47>-M47,M47,-'20. Balance '!E47),0) -> 0 | P47: =IF(M47>0,M47-N47,N47-O47) -> 0
B48: =B47+1 -> 67 | C48: 4.1083555e+09 | D48: 1.0057172e+09 | E48: =C48-D48 -> 3.1026383e+09 | F48: =F47+H47+I47 -> 2.8680501e+08 | G48: =$D$9/2 -> 2.8680501e+08 | H48: =IF(G48>F48, G48-F48, 0) -> 0 | I48: =IF(E48<0, IF(F48>-E48, E48, -F48),0) -> 0 | J48: =IF(E48>0, E48-H48, E48-I48) -> 3.1026383e+09 | K48: =IF(J48<0, 0,J48*0.6) -> 1.861583e+09 | L48: =IF(J48<0,IF('20. Balance '!D48>-J48,J48,-'20. Balance '!D48),0) -> 0 | M48: =IF(J48>0, J48-K48, J48-L48) -> 1.2410553e+09 | N48: =IF(M48<0, 0, M48) -> 1.2410553e+09 | O48: =IF(M48<0,IF('20. Balance '!E48>-M48,M48,-'20. Balance '!E48),0) -> 0 | P48: =IF(M48>0,M48-N48,N48-O48) -> 0
B49: =B48+1 -> 68 | C49: 4.5440065e+09 | D49: 1.366293e+09 | E49: =C49-D49 -> 3.1777135e+09 | F49: =F48+H48+I48 -> 2.8680501e+08 | G49: =$D$9/2 -> 2.8680501e+08 | H49: =IF(G49>F49, G49-F49, 0) -> 0 | I49: =IF(E49<0, IF(F49>-E49, E49, -F49),0) -> 0 | J49: =IF(E49>0, E49-H49, E49-I49) -> 3.1777135e+09 | K49: =IF(J49<0, 0,J49*0.6) -> 1.9066281e+09 | L49: =IF(J49<0,IF('20. Balance '!D49>-J49,J49,-'20. Balance '!D49),0) -> 0 | M49: =IF(J49>0, J49-K49, J49-L49) -> 1.2710854e+09 | N49: =IF(M49<0, 0, M49) -> 1.2710854e+09 | O49: =IF(M49<0,IF('20. Balance '!E49>-M49,M49,-'20. Balance '!E49),0) -> 0 | P49: =IF(M49>0,M49-N49,N49-O49) -> 0
B50: =B49+1 -> 69 | C50: 4.3959058e+09 | D50: 1.4433799e+09 | E50: =C50-D50 -> 2.9525258e+09 | F50: =F49+H49+I49 -> 2.8680501e+08 | G50: =$D$9/2 -> 2.8680501e+08 | H50: =IF(G50>F50, G50-F50, 0) -> 0 | I50: =IF(E50<0, IF(F50>-E50, E50, -F50),0) -> 0 | J50: =IF(E50>0, E50-H50, E50-I50) -> 2.9525258e+09 | K50: =IF(J50<0, 0,J50*0.6) -> 1.7715155e+09 | L50: =IF(J50<0,IF('20. Balance '!D50>-J50,J50,-'20. Balance '!D50),0) -> 0 | M50: =IF(J50>0, J50-K50, J50-L50) -> 1.1810103e+09 | N50: =IF(M50<0, 0, M50) -> 1.1810103e+09 | O50: =IF(M50<0,IF('20. Balance '!E50>-M50,M50,-'20. Balance '!E50),0) -> 0 | P50: =IF(M50>0,M50-N50,N50-O50) -> 0
B51: =B50+1 -> 70 | C51: 4.6704333e+09 | D51: 1.5627124e+09 | E51: =C51-D51 -> 3.1077209e+09 | F51: =F50+H50+I50 -> 2.8680501e+08 | G51: =$D$9/2 -> 2.8680501e+08 | H51: =IF(G51>F51, G51-F51, 0) -> 0 | I51: =IF(E51<0, IF(F51>-E51, E51, -F51),0) -> 0 | J51: =IF(E51>0, E51-H51, E51-I51) -> 3.1077209e+09 | K51: =IF(J51<0, 0,J51*0.6) -> 1.8646326e+09 | L51: =IF(J51<0,IF('20. Balance '!D51>-J51,J51,-'20. Balance '!D51),0) -> 0 | M51: =IF(J51>0, J51-K51, J51-L51) -> 1.2430884e+09 | N51: =IF(M51<0, 0, M51) -> 1.2430884e+09 | O51: =IF(M51<0,IF('20. Balance '!E51>-M51,M51,-'20. Balance '!E51),0) -> 0 | P51: =IF(M51>0,M51-N51,N51-O51) -> 0
B52: =B51+1 -> 71 | C52: 5.0499809e+09 | D52: 1.679715e+09 | E52: =C52-D52 -> 3.3702659e+09 | F52: =F51+H51+I51 -> 2.8680501e+08 | G52: =$D$9/2 -> 2.8680501e+08 | H52: =IF(G52>F52, G52-F52, 0) -> 0 | I52: =IF(E52<0, IF(F52>-E52, E52, -F52),0) -> 0 | J52: =IF(E52>0, E52-H52, E52-I52) -> 3.3702659e+09 | K52: =IF(J52<0, 0,J52*0.6) -> 2.0221595e+09 | L52: =IF(J52<0,IF('20. Balance '!D52>-J52,J52,-'20. Balance '!D52),0) -> 0 | M52: =IF(J52>0, J52-K52, J52-L52) -> 1.3481064e+09 | N52: =IF(M52<0, 0, M52) -> 1.3481064e+09 | O52: =IF(M52<0,IF('20. Balance '!E52>-M52,M52,-'20. Balance '!E52),0) -> 0 | P52: =IF(M52>0,M52-N52,N52-O52) -> 0
B53: =B52+1 -> 72 | C53: 5.1190246e+09 | D53: 1.4477588e+09 | E53: =C53-D53 -> 3.6712658e+09 | F53: =F52+H52+I52 -> 2.8680501e+08 | G53: =$D$9/2 -> 2.8680501e+08 | H53: =IF(G53>F53, G53-F53, 0) -> 0 | I53: =IF(E53<0, IF(F53>-E53, E53, -F53),0) -> 0 | J53: =IF(E53>0, E53-H53, E53-I53) -> 3.6712658e+09 | K53: =IF(J53<0, 0,J53*0.6) -> 2.2027595e+09 | L53: =IF(J53<0,IF('20. Balance '!D53>-J53,J53,-'20. Balance '!D53),0) -> 0 | M53: =IF(J53>0, J53-K53, J53-L53) -> 1.4685063e+09 | N53: =IF(M53<0, 0, M53) -> 1.4685063e+09 | O53: =IF(M53<0,IF('20. Balance '!E53>-M53,M53,-'20. Balance '!E53),0) -> 0 | P53: =IF(M53>0,M53-N53,N53-O53) -> 0
B54: =B53+1 -> 73 | C54: 5.8153458e+09 | D54: 1.2774043e+09 | E54: =C54-D54 -> 4.5379415e+09 | F54: =F53+H53+I53 -> 2.8680501e+08 | G54: =$D$9/2 -> 2.8680501e+08 | H54: =IF(G54>F54, G54-F54, 0) -> 0 | I54: =IF(E54<0, IF(F54>-E54, E54, -F54),0) -> 0 | J54: =IF(E54>0, E54-H54, E54-I54) -> 4.5379415e+09 | K54: =IF(J54<0, 0,J54*0.6) -> 2.7227649e+09 | L54: =IF(J54<0,IF('20. Balance '!D54>-J54,J54,-'20. Balance '!D54),0) -> 0 | M54: =IF(J54>0, J54-K54, J54-L54) -> 1.8151766e+09 | N54: =IF(M54<0, 0, M54) -> 1.8151766e+09 | O54: =IF(M54<0,IF('20. Balance '!E54>-M54,M54,-'20. Balance '!E54),0) -> 0 | P54: =IF(M54>0,M54-N54,N54-O54) -> 0
B55: =B54+1 -> 74 | C55: 5.4729525e+09 | D55: 1.3049699e+09 | E55: =C55-D55 -> 4.1679826e+09 | F55: =F54+H54+I54 -> 2.8680501e+08 | G55: =$D$9/2 -> 2.8680501e+08 | H55: =IF(G55>F55, G55-F55, 0) -> 0 | I55: =IF(E55<0, IF(F55>-E55, E55, -F55),0) -> 0 | J55: =IF(E55>0, E55-H55, E55-I55) -> 4.1679826e+09 | K55: =IF(J55<0, 0,J55*0.6) -> 2.5007896e+09 | L55: =IF(J55<0,IF('20. Balance '!D55>-J55,J55,-'20. Balance '!D55),0) -> 0 | M55: =IF(J55>0, J55-K55, J55-L55) -> 1.667193e+09 | N55: =IF(M55<0, 0, M55) -> 1.667193e+09 | O55: =IF(M55<0,IF('20. Balance '!E55>-M55,M55,-'20. Balance '!E55),0) -> 0 | P55: =IF(M55>0,M55-N55,N55-O55) -> 0
B56: =B55+1 -> 75 | C56: 5.92536e+09 | D56: 1.3518249e+09 | E56: =C56-D56 -> 4.5735351e+09 | F56: =F55+H55+I55 -> 2.8680501e+08 | G56: =$D$9/2 -> 2.8680501e+08 | H56: =IF(G56>F56, G56-F56, 0) -> 0 | I56: =IF(E56<0, IF(F56>-E56, E56, -F56),0) -> 0 | J56: =IF(E56>0, E56-H56, E56-I56) -> 4.5735351e+09 | K56: =IF(J56<0, 0,J56*0.6) -> 2.744121e+09 | L56: =IF(J56<0,IF('20. Balance '!D56>-J56,J56,-'20. Balance '!D56),0) -> 0 | M56: =IF(J56>0, J56-K56, J56-L56) -> 1.829414e+09 | N56: =IF(M56<0, 0, M56) -> 1.829414e+09 | O56: =IF(M56<0,IF('20. Balance '!E56>-M56,M56,-'20. Balance '!E56),0) -> 0 | P56: =IF(M56>0,M56-N56,N56-O56) -> 0
... B66: =B65+1 -> 85 | C66: 8.2960274e+09 | D66: 1.3176235e+09 | E66: =C66-D66 -> 6.9784038e+09 | F66: =F65+H65+I65 -> 2.8680501e+08 | G66: =$D$9/2 -> 2.8680501e+08 | H66: =IF(G66>F66, G66-F66, 0) -> 0 | I66: =IF(E66<0, IF(F66>-E66, E66, -F66),0) -> 0 | J66: =IF(E66>0, E66-H66, E66-I66) -> 6.9784038e+09 | K66: =IF(J66<0, 0,J66*0.6) -> 4.1870423e+09 | L66: =IF(J66<0,IF('20. Balance '!D66>-J66,J66,-'20. Balance '!D66),0) -> 0 | M66: =IF(J66>0, J66-K66, J66-L66) -> 2.7913615e+09 | N66: =IF(M66<0, 0, M66) -> 2.7913615e+09 | O66: =IF(M66<0,IF('20. Balance '!E66>-M66,M66,-'20. Balance '!E66),0) -> 0 | P66: =IF(M66>0,M66-N66,N66-O66) -> 0

Sheet 20. Balance 
B2: Age | C2: Beginning emergency fund | D2: Beginning saving account | E2: Beginning investment account | F2: Total balance
B3: 22 | C3: ='19. Funds '!F3 -> 20000000 | D3: ='4. Balance sheet '!L8 -> 70000000 | E3: 0 | F3: =SUM(C3:E3) -> 90000000
B4: =B3+1 -> 23 | C4: ='19. Funds '!F4 -> 187194000 | D4: =D3+'19. Funds '!K3+'19. Funds '!L3 -> 0 | E4: =SUM('19. Funds '!$N$3:N3) -> 0 | F4: =SUM(C4:E4) -> 187194000
B5: =B4+1 -> 24 | C5: ='19. Funds '!F5 -> 1.8392279e+08 | D5: =D4+'19. Funds '!K4+'19. Funds '!L4 -> 0 | E5: =SUM('19. Funds '!$N$3:N4) -> 0 | F5: =SUM(C5:E5) -> 1.8392279e+08
B6: =B5+1 -> 25 | C6: ='19. Funds '!F6 -> 1.8013889e+08 | D6: =D5+'19. Funds '!K5+'19. Funds '!L5 -> 0 | E6: =SUM('19. Funds '!$N$3:N5) -> 0 | F6: =SUM(C6:E6) -> 1.8013889e+08
B7: =B6+1 -> 26 | C7: ='19. Funds '!F7 -> 187194000 | D7: =D6+'19. Funds '!K6+'19. Funds '!L6 -> 24207794 | E7: =SUM('19. Funds '!$N$3:N6) -> 16138529 | F7: =SUM(C7:E7) -> 2.2754032e+08
B8: =B7+1 -> 27 | C8: ='19. Funds '!F8 -> 187194000 | D8: =D7+'19. Funds '!K7+'19. Funds '!L7 -> 54953884 | E8: =SUM('19. Funds '!$N$3:N7) -> 36635923 | F8: =SUM(C8:E8) -> 2.7878381e+08
B9: =B8+1 -> 28 | C9: ='19. Funds '!F9 -> 74107826 | D9: =D8+'19. Funds '!K8+'19. Funds '!L8 -> 54953884 | E9: =SUM('19. Funds '!$N$3:N8) -> 36635923 | F9: =SUM(C9:E9) -> 1.6569763e+08
B10: =B9+1 -> 29 | C10: ='19. Funds '!F10 -> 2.8680501e+08 | D10: =D9+'19. Funds '!K9+'19. Funds '!L9 -> 0 | E10: =SUM('19. Funds '!$N$3:N9) -> 36635923 | F10: =SUM(C10:E10) -> 3.2344093e+08
B11: =B10+1 -> 30 | C11: ='19. Funds '!F11 -> 2.8680501e+08 | D11: =D10+'19. Funds '!K10+'19. Funds '!L10 -> 14177830 | E11: =SUM('19. Funds '!$N$3:N10) -> 46087810 | F11: =SUM(C11:E11) -> 3.4707065e+08
B12: =B11+1 -> 31 | C12: ='19. Funds '!F12 -> 2.8680501e+08 | D12: =D11+'19. Funds '!K11+'19. Funds '!L11 -> 91407038 | E12: =SUM('19. Funds '!$N$3:N11) -> 97573948 | F12: =SUM(C12:E12) -> 4.7578599e+08
B13: =B12+1 -> 32 | C13: ='19. Funds '!F13 -> 2.8680501e+08 | D13: =D12+'19. Funds '!K12+'19. Funds '!L12 -> 1.8928292e+08 | E13: =SUM('19. Funds '!$N$3:N12) -> 1.6282454e+08 | F13: =SUM(C13:E13) -> 6.3891247e+08
B14: =B13+1 -> 33 | C14: ='19. Funds '!F14 -> 1.5977654e+08 | D14: =D13+'19. Funds '!K13+'19. Funds '!L13 -> 1.8928292e+08 | E14: =SUM('19. Funds '!$N$3:N13) -> 1.6282454e+08 | F14: =SUM(C14:E14) -> 5.1188399e+08
B15: =B14+1 -> 34 | C15: ='19. Funds '!F15 -> 1.9006623e+08 | D15: =D14+'19. Funds '!K14+'19. Funds '!L14 -> 1.8928292e+08 | E15: =SUM('19. Funds '!$N$3:N14) -> 1.6282454e+08 | F15: =SUM(C15:E15) -> 5.4217369e+08
... B66: =B65+1 -> 85 | C66: ='19. Funds '!F66 -> 2.8680501e+08 | D66: =D65+'19. Funds '!K65+'19. Funds '!L65 -> 8.6850975e+10 | E66: =SUM('19. Funds '!$N$3:N65) -> 5.798198e+10 | F66: =SUM(C66:E66) -> 1.4511976e+11

Sheet 20. Market return 
B2: Year | C2: Stock Market Annual Return | D2: Link | E2: Date | F2: Price of DCBF | G2: Semiannual Return of Bond Investment Fund (DCBF) | H2: Link
B3: 2014 | C3: 0.0812 | E3: 44000 | F3: 20036
B4: 2015 | C4: 0.0612 | E4: 44196 | F4: 20756 | G4: =(F4-F3)/F3 -> 0.035935316
B5: 2016 | C5: 0.1482 | E5: 44350 | F5: 21388 | G5: =(F5-F4)/F4 -> 0.030449027
B6: 2017 | C6: 0.4803 | E6: 44560 | F6: 22270 | G6: =(F6-F5)/F5 -> 0.041238077
B7: 2018 | C7: -0.0932 | E7: 44714 | F7: 22971 | G7: =(F7-F6)/F6 -> 0.031477324
B8: 2019 | C8: 0.0767 | E8: 44923 | F8: 23257 | G8: =(F8-F7)/F7 -> 0.012450481
B9: 2020 | C9: 0.1487 | E9: 45084 | F9: 24073 | G9: =(F9-F8)/F8 -> 0.035086211
B10: 2021 | C10: 0.3573 | E10: 45291 | F10: 25390 | G10: =(F10-F9)/F9 -> 0.054708595
B11: 2022 | C11: -0.3278 | E11: 45449 | F11: 26153 | G11: =(F11-F10)/F10 -> 0.030051201
B12: 2023 | C12: 0.122 | E12: 45610 | F12: 26863 | G12: =(F12-F11)/F11 -> 0.027147937
B13: 2024 | C13: 0.1211
B15: Standard Deviation | C15: =STDEV(C3:C13) -> 0.2094458 | E15: Standard Deviation | F15: =STDEV(G4:G12) -> 0.011324107
B16: Mean | C16: =AVERAGE(C3:C13) -> 0.10688182 | E16: Mean | F16: =AVERAGE(G4:G12) -> 0.033171574

Sheet 21. Monte Carlo Simulation 
A2: Saving | D2: Year | E2: Age | F2: Wealth at the beginning of year | G2: Savings | H2: % Stock | I2: Stock | J2: % Bond | K2: Bond | L2: Random number | M2: 1+return on stock | N2: Random number | O2: 1+return on bond | P2: Wealth at the end of year | Q2: Total return | W2: Retirement Expense | X2: =SUM('16. Retirement '!B31:X31)-SUM('16. Retirement '!B32:X32) -> -7.0250467e+10
A3: Annual saving rate | B3: ='3. Financial drivers '!L17 -> 0.056 | D3: 2025 | E3: 22 | F3: ='20. Balance '!D3+'20. Balance '!E3 -> 70000000 | G3: ='20. Balance '!D3 -> 70000000 | H3: ='18. Investment assumption'!D20/('18. Investment assumption'!D20+'18. Investment assumption'!E20) -> 0.5 | I3: =H3*'20. Balance '!E3 -> 0 | J3: =1-H3 -> 0.5 | K3: =J3*'20. Balance '!E3 -> 0 | L3: =NORMSINV(RAND()) -> -1.7077645 | M3: =1+($B$6+$B$7*L3) -> 0.74919773 | N3: =NORMSINV(RAND()) -> -1.1933265 | O3: =1+($B$10+$B$11*N3) -> 1.0196582 | P3: =G3*(1+$B$3)+I3*M3+K3*O3 -> 73920000 | Q3: =P3-F3 -> 3920000 | T3: Stimulation | U3: =P44 -> 5.6530858e+10 | W3: Average | X3: =AVERAGE(U4:U1003) -> 5.8824666e+10
D4: =D3+1 -> 2026 | E4: =E3+1 -> 23 | F4: ='20. Balance '!D4+'20. Balance '!E4 -> 0 | G4: ='20. Balance '!D4 -> 0 | H4: ='18. Investment assumption'!D21/('18. Investment assumption'!D21+'18. Investment assumption'!E21) -> 0.5 | I4: =H4*'20. Balance '!E4 -> 0 | J4: =1-H4 -> 0.5 | K4: =J4*'20. Balance '!E4 -> 0 | L4: =NORMSINV(RAND()) -> 0.35850516 | M4: =1+($B$6+$B$7*L4) -> 1.1819692 | N4: =NORMSINV(RAND()) -> -1.958964 | O4: =1+($B$10+$B$11*N4) -> 1.0109881 | P4: =G4*(1+$B$3)+I4*M4+K4*O4 -> 0 | Q4: =P4-F4 -> 0 | T4: 1 | U4: 5.5584801e+10 | W4: Volatility | X4: =_xlfn.STDEV.S(U4:U1003) -> 2.0496273e+09
A5: Stock | D5: =D4+1 -> 2027 | E5: =E4+1 -> 24 | F5: ='20. Balance '!D5+'20. Balance '!E5 -> 0 | G5: ='20. Balance '!D5 -> 0 | H5: ='18. Investment assumption'!D22/('18. Investment assumption'!D22+'18. Investment assumption'!E22) -> 0.5 | I5: =H5*'20. Balance '!E5 -> 0 | J5: =1-H5 -> 0.5 | K5: =J5*'20. Balance '!E5 -> 0 | L5: =NORMSINV(RAND()) -> 0.083042825 | M5: =1+($B$6+$B$7*L5) -> 1.1242748 | N5: =NORMSINV(RAND()) -> -0.23524366 | O5: =1+($B$10+$B$11*N5) -> 1.0305076 | P5: =G5*(1+$B$3)+I5*M5+K5*O5 -> 0 | Q5: =P5-F5 -> 0 | T5: 2 | U5: 5.8451431e+10 | W5: 25th Percentile | X5: =_xlfn.PERCENTILE.EXC(U4:U1003,0.25) -> 5.7424281e+10
A6: Expected annual return | B6: ='20. Market return '!C16 -> 0.10688182 | D6: =D5+1 -> 2028 | E6: =E5+1 -> 25 | F6: ='20. Balance '!D6+'20. Balance '!E6 -> 0 | G6: ='20. Balance '!D6 -> 0 | H6: ='18. Investment assumption'!D23/('18. Investment assumption'!D23+'18. Investment assumption'!E23) -> 0.5 | I6: =H6*'20. Balance '!E6 -> 0 | J6: =1-H6 -> 0.5 | K6: =J6*'20. Balance '!E6 -> 0 | L6: =NORMSINV(RAND()) -> -0.39405824 | M6: =1+($B$6+$B$7*L6) -> 1.024348 | N6: =NORMSINV(RAND()) -> 0.64636021 | O6: =1+($B$10+$B$11*N6) -> 1.040491 | P6: =G6*(1+$B$3)+I6*M6+K6*O6 -> 0 | Q6: =P6-F6 -> 0 | T6: 3 | U6: 5.9521104e+10 | W6: 50th Percentile | X6: =_xlfn.PERCENTILE.EXC(U4:U1003,0.5) -> 5.8724247e+10
A7: Standard deviation | B7: ='20. Market return '!C15 -> 0.2094458 | D7: =D6+1 -> 2029 | E7: =E6+1 -> 26 | F7: ='20. Balance '!D7+'20. Balance '!E7 -> 40346323 | G7: ='20. Balance '!D7 -> 24207794 | H7: ='18. Investment assumption'!D24/('18. Investment assumption'!D24+'18. Investment assumption'!E24) -> 0.5 | I7: =H7*'20. Balance '!E7 -> 8069264.6 | J7: =1-H7 -> 0.5 | K7: =J7*'20. Balance '!E7 -> 8069264.6 | L7: =NORMSINV(RAND()) -> -0.4501925 | M7: =1+($B$6+$B$7*L7) -> 1.0125909 | N7: =NORMSINV(RAND()) -> 1.2286778 | O7: =1+($B$10+$B$11*N7) -> 1.0470853 | P7: =G7*(1+$B$3)+I7*M7+K7*O7 -> 42183502 | Q7: =P7-F7 -> 1837179.1 | T7: 4 | U7: 6.2383185e+10 | W7: 75th Percentile | X7: =_xlfn.PERCENTILE.EXC(U4:U1003,0.75) -> 6.0300444e+10
D8: =D7+1 -> 2030 | E8: =E7+1 -> 27 | F8: ='20. Balance '!D8+'20. Balance '!E8 -> 91589807 | G8: ='20. Balance '!D8 -> 54953884 | H8: ='18. Investment assumption'!D25/('18. Investment assumption'!D25+'18. Investment assumption'!E25) -> 0.25 | I8: =H8*'20. Balance '!E8 -> 9158980.7 | J8: =1-H8 -> 0.75 | K8: =J8*'20. Balance '!E8 -> 27476942 | L8: =NORMSINV(RAND()) -> -1.7211315 | M8: =1+($B$6+$B$7*L8) -> 0.74639805 | N8: =NORMSINV(RAND()) -> 0.40519455 | O8: =1+($B$10+$B$11*N8) -> 1.03776 | P8: =G8*(1+$B$3)+I8*M8+K8*O8 -> 93382019 | Q8: =P8-F8 -> 1792212.6 | T8: 5 | U8: 6.0306744e+10 | W8: 95th Percentile | X8: =_xlfn.PERCENTILE.EXC(U4:U1003,0.95) -> 6.2303165e+10
A9: Bond | D9: =D8+1 -> 2031 | E9: =E8+1 -> 28 | F9: ='20. Balance '!D9+'20. Balance '!E9 -> 91589807 | G9: ='20. Balance '!D9 -> 54953884 | H9: ='18. Investment assumption'!D26/('18. Investment assumption'!D26+'18. Investment assumption'!E26) -> 0.25 | I9: =H9*'20. Balance '!E9 -> 9158980.7 | J9: =1-H9 -> 0.75 | K9: =J9*'20. Balance '!E9 -> 27476942 | L9: =NORMSINV(RAND()) -> 0.030301676 | M9: =1+($B$6+$B$7*L9) -> 1.1132284 | N9: =NORMSINV(RAND()) -> 0.87368927 | O9: =1+($B$10+$B$11*N9) -> 1.0430653 | P9: =G9*(1+$B$3)+I9*M9+K9*O9 -> 96887584 | Q9: =P9-F9 -> 5297777.5 | T9: 6 | U9: 5.8327994e+10 | W9: Prob(Successful) | X9: =COUNTIF(U4:U1003,">="&$X$2)/COUNT(T4:T1003) -> 1
A10: Expected annual return | B10: ='20. Market return '!F16 -> 0.033171574 | D10: =D9+1 -> 2032 | E10: =E9+1 -> 29 | F10: ='20. Balance '!D10+'20. Balance '!E10 -> 36635923 | G10: ='20. Balance '!D10 -> 0 | H10: ='18. Investment assumption'!D27/('18. Investment assumption'!D27+'18. Investment assumption'!E27) -> 0.25 | I10: =H10*'20. Balance '!E10 -> 9158980.7 | J10: =1-H10 -> 0.75 | K10: =J10*'20. Balance '!E10 -> 27476942 | L10: =NORMSINV(RAND()) -> 0.74752409 | M10: =1+($B$6+$B$7*L10) -> 1.2634476 | N10: =NORMSINV(RAND()) -> 0.7503487 | O10: =1+($B$10+$B$11*N10) -> 1.0416686 | P10: =G10*(1+$B$3)+I10*M10+K10*O10 -> 40193760 | Q10: =P10-F10 -> 3557837.3 | T10: 7 | U10: 5.8126647e+10
A11: Standard deviation | B11: ='20. Market return '!F15 -> 0.011324107 | D11: =D10+1 -> 2033 | E11: =E10+1 -> 30 | F11: ='20. Balance '!D11+'20. Balance '!E11 -> 60265640 | G11: ='20. Balance '!D11 -> 14177830 | H11: ='18. Investment assumption'!D28/('18. Investment assumption'!D28+'18. Investment assumption'!E28) -> 0.25 | I11: =H11*'20. Balance '!E11 -> 11521952 | J11: =1-H11 -> 0.75 | K11: =J11*'20. Balance '!E11 -> 34565857 | L11: =NORMSINV(RAND()) -> 1.7293811 | M11: =1+($B$6+$B$7*L11) -> 1.4690934 | N11: =NORMSINV(RAND()) -> -0.95362538 | O11: =1+($B$10+$B$11*N11) -> 1.0223726 | P11: =G11*(1+$B$3)+I11*M11+K11*O11 -> 67237799 | Q11: =P11-F11 -> 6972159.3 | T11: 8 | U11: 5.9240875e+10
D12: =D11+1 -> 2034 | E12: =E11+1 -> 31 | F12: ='20. Balance '!D12+'20. Balance '!E12 -> 1.8898099e+08 | G12: ='20. Balance '!D12 -> 91407038 | H12: ='18. Investment assumption'!D29/('18. Investment assumption'!D29+'18. Investment assumption'!E29) -> 0.25 | I12: =H12*'20. Balance '!E12 -> 24393487 | J12: =1-H12 -> 0.75 | K12: =J12*'20. Balance '!E12 -> 73180461 | L12: =NORMSINV(RAND()) -> 0.37977654 | M12: =1+($B$6+$B$7*L12) -> 1.1864244 | N12: =NORMSINV(RAND()) -> -0.78942021 | O12: =1+($B$10+$B$11*N12) -> 1.0242321 | P12: =G12*(1+$B$3)+I12*M12+K12*O12 -> 2.0042064e+08 | Q12: =P12-F12 -> 11439652 | T12: 9 | U12: 5.9465273e+10
D13: =D12+1 -> 2035 | E13: =E12+1 -> 32 | F13: ='20. Balance '!D13+'20. Balance '!E13 -> 3.5210746e+08 | G13: ='20. Balance '!D13 -> 1.8928292e+08 | H13: ='18. Investment assumption'!D30/('18. Investment assumption'!D30+'18. Investment assumption'!E30) -> 0.25 | I13: =H13*'20. Balance '!E13 -> 40706134 | J13: =1-H13 -> 0.75 | K13: =J13*'20. Balance '!E13 -> 1.221184e+08 | L13: =NORMSINV(RAND()) -> 2.4789855 | M13: =1+($B$6+$B$7*L13) -> 1.6260949 | N13: =NORMSINV(RAND()) -> 0.35293184 | O13: =1+($B$10+$B$11*N13) -> 1.0371682 | P13: =G13*(1+$B$3)+I13*M13+K13*O13 -> 3.9273213e+08 | Q13: =P13-F13 -> 40624670 | T13: 10 | U13: 5.6201931e+10
D14: =D13+1 -> 2036 | E14: =E13+1 -> 33 | F14: ='20. Balance '!D14+'20. Balance '!E14 -> 3.5210746e+08 | G14: ='20. Balance '!D14 -> 1.8928292e+08 | H14: ='18. Investment assumption'!D31/('18. Investment assumption'!D31+'18. Investment assumption'!E31) -> 0.25 | I14: =H14*'20. Balance '!E14 -> 40706134 | J14: =1-H14 -> 0.75 | K14: =J14*'20. Balance '!E14 -> 1.221184e+08 | L14: =NORMSINV(RAND()) -> 0.70085264 | M14: =1+($B$6+$B$7*L14) -> 1.2536725 | N14: =NORMSINV(RAND()) -> 0.75748072 | O14: =1+($B$10+$B$11*N14) -> 1.0417494 | P14: =G14*(1+$B$3)+I14*M14+K14*O14 -> 3.7813169e+08 | Q14: =P14-F14 -> 26024235 | T14: 11 | U14: 5.8782826e+10
D15: =D14+1 -> 2037 | E15: =E14+1 -> 34 | F15: ='20. Balance '!D15+'20. Balance '!E15 -> 3.5210746e+08 | G15: ='20. Balance '!D15 -> 1.8928292e+08 | H15: ='18. Investment assumption'!D32/('18. Investment assumption'!D32+'18. Investment assumption'!E32) -> 0.25 | I15: =H15*'20. Balance '!E15 -> 40706134 | J15: =1-H15 -> 0.75 | K15: =J15*'20. Balance '!E15 -> 1.221184e+08 | L15: =NORMSINV(RAND()) -> 0.52978827 | M15: =1+($B$6+$B$7*L15) -> 1.2178437 | N15: =NORMSINV(RAND()) -> -0.38018417 | O15: =1+($B$10+$B$11*N15) -> 1.0288663 | P15: =G15*(1+$B$3)+I15*M15+K15*O15 -> 3.7509999e+08 | Q15: =P15-F15 -> 22992530 | T15: 12 | U15: 5.9789467e+10
D16: =D15+1 -> 2038 | E16: =E15+1 -> 35 | F16: ='20. Balance '!D16+'20. Balance '!E16 -> 2.8506654e+08 | G16: ='20. Balance '!D16 -> 1.2224201e+08 | H16: ='18. Investment assumption'!D33/('18. Investment assumption'!D33+'18. Investment assumption'!E33) -> 0.25 | I16: =H16*'20. Balance '!E16 -> 40706134 | J16: =1-H16 -> 0.75 | K16: =J16*'20. Balance '!E16 -> 1.221184e+08 | L16: =NORMSINV(RAND()) -> 1.0308798 | M16: =1+($B$6+$B$7*L16) -> 1.3227953 | N16: =NORMSINV(RAND()) -> -0.84218999 | O16: =1+($B$10+$B$11*N16) -> 1.0236345 | P16: =G16*(1+$B$3)+I16*M16+K16*O16 -> 3.0793805e+08 | Q16: =P16-F16 -> 22871510 | T16: 13 | U16: 5.9904649e+10
D17: =D16+1 -> 2039 | E17: =E16+1 -> 36 | F17: ='20. Balance '!D17+'20. Balance '!E17 -> 3.7022334e+08 | G17: ='20. Balance '!D17 -> 1.7333608e+08 | H17: ='18. Investment assumption'!D34/('18. Investment assumption'!D34+'18. Investment assumption'!E34) -> 0.25 | I17: =H17*'20. Balance '!E17 -> 49221814 | J17: =1-H17 -> 0.75 | K17: =J17*'20. Balance '!E17 -> 1.4766544e+08 | L17: =NORMSINV(RAND()) -> 0.032338298 | M17: =1+($B$6+$B$7*L17) -> 1.1136549 | N17: =NORMSINV(RAND()) -> 1.1752248 | O17: =1+($B$10+$B$11*N17) -> 1.0464799 | P17: =G17*(1+$B$3)+I17*M17+K17*O17 -> 3.9238794e+08 | Q17: =P17-F17 -> 22164605 | T17: 14 | U17: 5.9570064e+10
D18: =D17+1 -> 2040 | E18: =E17+1 -> 37 | F18: ='20. Balance '!D18+'20. Balance '!E18 -> 4.6848611e+08 | G18: ='20. Balance '!D18 -> 2.3229374e+08 | H18: ='18. Investment assumption'!D35/('18. Investment assumption'!D35+'18. Investment assumption'!E35) -> 0.25 | I18: =H18*'20. Balance '!E18 -> 59048091 | J18: =1-H18 -> 0.75 | K18: =J18*'20. Balance '!E18 -> 1.7714427e+08 | L18: =NORMSINV(RAND()) -> 0.50505327 | M18: =1+($B$6+$B$7*L18) -> 1.2126631 | N18: =NORMSINV(RAND()) -> 0.87757939 | O18: =1+($B$10+$B$11*N18) -> 1.0431094 | P18: =G18*(1+$B$3)+I18*M18+K18*O18 -> 5.0168848e+08 | Q18: =P18-F18 -> 33202379 | T18: 15 | U18: 5.9279255e+10
D19: =D18+1 -> 2041 | E19: =E18+1 -> 38 | F19: ='20. Balance '!D19+'20. Balance '!E19 -> 8.2027686e+08 | G19: ='20. Balance '!D19 -> 4.433682e+08 | H19: ='18. Investment assumption'!D36/('18. Investment assumption'!D36+'18. Investment assumption'!E36) -> 0.25 | I19: =H19*'20. Balance '!E19 -> 94227166 | J19: =1-H19 -> 0.75 | K19: =J19*'20. Balance '!E19 -> 2.826815e+08 | L19: =NORMSINV(RAND()) -> -1.0796968 | M19: =1+($B$6+$B$7*L19) -> 0.88074386 | N19: =NORMSINV(RAND()) -> 0.73508746 | O19: =1+($B$10+$B$11*N19) -> 1.0414958 | P19: =G19*(1+$B$3)+I19*M19+K19*O19 -> 8.455984e+08 | Q19: =P19-F19 -> 25321541 | T19: 16 | U19: 5.8624823e+10
D20: =D19+1 -> 2042 | E20: =E19+1 -> 39 | F20: ='20. Balance '!D20+'20. Balance '!E20 -> 1.1694451e+09 | G20: ='20. Balance '!D20 -> 6.5286912e+08 | H20: ='18. Investment assumption'!D37/('18. Investment assumption'!D37+'18. Investment assumption'!E37) -> 0.25 | I20: =H20*'20. Balance '!E20 -> 1.2914399e+08 | J20: =1-H20 -> 0.75 | K20: =J20*'20. Balance '!E20 -> 3.8743196e+08 | L20: =NORMSINV(RAND()) -> -2.5653913 | M20: =1+($B$6+$B$7*L20) -> 0.56957139 | N20: =NORMSINV(RAND()) -> -0.093619502 | O20: =1+($B$10+$B$11*N20) -> 1.0321114 | P20: =G20*(1+$B$3)+I20*M20+K20*O20 -> 1.1628595e+09 | Q20: =P20-F20 -> -6585607.2 | T20: 17 | U20: 5.5787061e+10
D21: =D20+1 -> 2043 | E21: =E20+1 -> 40 | F21: ='20. Balance '!D21+'20. Balance '!E21 -> 1.7574687e+09 | G21: ='20. Balance '!D21 -> 1.0056833e+09 | H21: ='18. Investment assumption'!D38/('18. Investment assumption'!D38+'18. Investment assumption'!E38) -> 0.25 | I21: =H21*'20. Balance '!E21 -> 1.8794635e+08 | J21: =1-H21 -> 0.75 | K21: =J21*'20. Balance '!E21 -> 5.6383905e+08 | L21: =NORMSINV(RAND()) -> 0.13166986 | M21: =1+($B$6+$B$7*L21) -> 1.1344595 | N21: =NORMSINV(RAND()) -> -0.29665081 | O21: =1+($B$10+$B$11*N21) -> 1.0298123 | P21: =G21*(1+$B$3)+I21*M21+K21*O21 -> 1.8558675e+09 | Q21: =P21-F21 -> 98398762 | T21: 18 | U21: 5.8357465e+10
D22: =D21+1 -> 2044 | E22: =E21+1 -> 41 | F22: ='20. Balance '!D22+'20. Balance '!E22 -> 2.4758022e+09 | G22: ='20. Balance '!D22 -> 1.4366834e+09 | H22: ='18. Investment assumption'!D39/('18. Investment assumption'!D39+'18. Investment assumption'!E39) -> 0.25 | I22: =H22*'20. Balance '!E22 -> 2.597797e+08 | J22: =1-H22 -> 0.75 | K22: =J22*'20. Balance '!E22 -> 7.7933909e+08 | L22: =NORMSINV(RAND()) -> 0.79222217 | M22: =1+($B$6+$B$7*L22) -> 1.2728094 | N22: =NORMSINV(RAND()) -> -0.34597947 | O22: =1+($B$10+$B$11*N22) -> 1.0292537 | P22: =G22*(1+$B$3)+I22*M22+K22*O22 -> 2.6499253e+09 | Q22: =P22-F22 -> 1.7412314e+08 | T22: 19 | U22: 5.9668989e+10
D23: =D22+1 -> 2045 | E23: =E22+1 -> 42 | F23: ='20. Balance '!D23+'20. Balance '!E23 -> 3.2955541e+09 | G23: ='20. Balance '!D23 -> 1.9285345e+09 | H23: ='18. Investment assumption'!D40/('18. Investment assumption'!D40+'18. Investment assumption'!E40) -> 0.25 | I23: =H23*'20. Balance '!E23 -> 3.4175489e+08 | J23: =1-H23 -> 0.75 | K23: =J23*'20. Balance '!E23 -> 1.0252647e+09 | L23: =NORMSINV(RAND()) -> 0.3044125 | M23: =1+($B$6+$B$7*L23) -> 1.1706397 | N23: =NORMSINV(RAND()) -> -0.29431284 | O23: =1+($B$10+$B$11*N23) -> 1.0298387 | P23: =G23*(1+$B$3)+I23*M23+K23*O23 -> 3.4924616e+09 | Q23: =P23-F23 -> 1.9690751e+08 | T23: 20 | U23: 6.3280707e+10
... D66: =D65+1 -> 2088 | E66: =E65+1 -> 85 | F66: ='20. Balance '!D66+'20. Balance '!E66 -> 1.4483296e+11 | G66: ='20. Balance '!D66 -> 8.6850975e+10 | H66: ='18. Investment assumption'!D83/('18. Investment assumption'!D83+'18. Investment assumption'!E83) -> 0 | I66: =H66*'20. Balance '!E66 -> 0 | J66: =1-H66 -> 1 | K66: =J66*'20. Balance '!E66 -> 5.798198e+10 | L66: =NORMSINV(RAND()) -> -1.653958 | M66: =1+($B$6+$B$7*L66) -> 0.76046727 | N66: =NORMSINV(RAND()) -> 0.51994915 | O66: =1+($B$10+$B$11*N66) -> 1.0390595 | P66: =G66*(1+$B$3)+I66*M66+K66*O66 -> 1.5196136e+11 | Q66: =P66-F66 -> 7.1284037e+09 | T66: 63 | U66: 6.0172055e+10
T67: 64 | U67: 6.1436721e+10
T68: 65 | U68: 6.4374528e+10
T69: 66 | U69: 5.6119183e+10
T70: 67 | U70: 5.7880373e+10
T71: 68 | U71: 6.2475867e+10
T72: 69 | U72: 6.2290759e+10
T73: 70 | U73: 5.979676e+10
T74: 71 | U74: 5.6899114e+10
T75: 72 | U75: 5.8038843e+10
T76: 73 | U76: 5.801179e+10
T77: 74 | U77: 5.9119783e+10
T78: 75 | U78: 5.8945601e+10
... T1003: 1000 | U1003: 5.9598538e+10
